Workbook

Sheet TUDB
A1: TU DARE Angler Science DB
A2: Database | B2: Dev: DBParsing_241015_v01.xlsm
A3: Download | B3: 45580 | D3: UTC Correction
A4: Observations | B4: 2320 | D4: -6
A5: Year Load | B5: 2024 | AL5: =COUNTIF(TU_DB[None (Disturbance)],1) -> 1295
BO6: reset col references to HUC12 sheet
A7: Database | B7: ObsNo | C7: Observation Date/Time-UTC | D7: Observation Date/Time-Local | E7: Observation Date-Local | F7: Year | G7: Month No. | H7: ObserverID | I7: Monitoring Site | J7: Longitude | K7: Latitude | L7: Zonal | M7: Photo No. | N7: Photo Flag | O7: Public | P7: 5n1 Flag | Q7: ALK Bin (ppm) | R7: HRD Bin (ppm) | S7: NO2 Bin (5n1) (ppm) | T7: NO3 Bin (5n1) (ppm) | U7: pH Bin | V7: Phos Flag | W7: Orthophosphate (ppb) | X7: Water Temp Flag | Y7: Water Temperature (oF) | Z7: 2n1 Flag | AA7: NO2 Bin (2n1) (ppm) | AB7: NO3 Bin (2n1) (ppm) | AC7: Source | AD7: Disturbances | AE7: Fish Barrier | AF7: Bank Erosion | AG7: Trash | AH7: Pipe/Drain Outflow | AI7: Livestock in Water | AJ7: Algal Bloom | AK7: Fish Kill | AL7: None (Disturbance) | AM7: Dis: Not Reported | AN7: Water Level | AO7: Water Level Flag | AP7: Clarity | AQ7: Clarity Flag | AR7: Weather | AS7: Regional Rainfall | AT7: Local Thunderstorm | AU7: Snowmelt | AV7: None (Weather) | AW7: Not Reported (Weather) | AX7: Observation Comments | AY7: Obs Com Flag | AZ7: Bank Erosion4 | BA7: Trash5 | BB7: Pipe Drain6 | BC7: Livestock in Water2 | BD7: Algal Bloom3 | BE7: Fish Kill4 | BF7: None7 | BG7: Dis: Not Reported8 | BH7: All Streams | BI7: Primary Stream | BJ7: Trout Stream Flag | BK7: Brook Trout Stream Flag | BL7: Plotting Zone | BM7: TU Chapter Area | BN7: Observer Chapter Affiliation | BO7: HUC12 Code | BP7: HUC12 Name | BQ7: HUC10 Name | BR7: Column1
A8: Dev: DBParsing_231030_v01.xlsm | B8: x31pFiQ1h6Ck2GeazKZQ | C8: 45587.677 | D8: 45587.427 | E8: 45587 | F8: 2024 | G8: 10 | H8: 3ewh0JhsqndewkOhEmNvJ9cb0n83 | I8: Rush River @ 570th Ave | J8: -92.142296 | K8: 44.790396 | M8: 2024-10-22 11:14:10.552952.jpg-0 | N8: 1 | P8: 1 | Q8: 180 | R8: 180 | U8: 7 | V8: 1 | W8: 100 | X8: 1 | Y8: 50 | Z8: 1 | AA8: 0 | AB8: 2 | AC8: River/Stream | AD8: None | AE8: 0 | AF8: 0 | AG8: 0 | AH8: 0 | AI8: 0 | AJ8: 0 | AK8: 0 | AL8: 1 | AM8: 0 | AN8: Baseflow | AO8: 1 | AP8: Clear | AQ8: 1 | AR8: None | AS8: 0 | AT8: 0 | AU8: 0 | AV8: 0 | AW8: 0 | AX8: sample location moved to 200ft below Co Rd P bridge. better cell phone coverage. much easier access to water | AY8: 1 | AZ8: Absent | BA8: Absent | BB8: Absent | BC8: Absent | BD8: Absent | BE8: Absent | BF8: Absent | BG8: Present | BH8: Recorded | BJ8: 1 | BK8: 1 | BL8: 1 | BM8: Kiap-TU-Wish | BN8: Kiap-TU-Wish | BO8: 070500051003 | BP8: Cady Creek | BQ8: 0705000510
A9: Dev: DBParsing_231030_v01.xlsm | B9: WjE9qCLHdWkQVBbZYn1m | C9: 45580.679 | D9: 45580.429 | E9: 45580 | F9: 2024 | G9: 10 | H9: 7a7IFD1YT3aDXB8CbnSJjn1oLRC2 | I9: Isabelle Creek @ County Rd. EE | J9: -92.442941 | K9: 44.621467 | N9: 0 | P9: 1 | Q9: 0 | R9: 30 | U9: 7 | V9: 1 | W9: 0 | X9: 1 | Y9: 42 | Z9: 1 | AA9: 0 | AB9: 0 | AC9: River/Stream | AD9: None | AE9: 0 | AF9: 0 | AG9: 0 | AH9: 0 | AI9: 0 | AJ9: 0 | AK9: 0 | AL9: 1 | AM9: 0 | AN9: Baseflow | AO9: 1 | AP9: Clear | AQ9: 1 | AR9: None | AS9: 0 | AT9: 0 | AU9: 0 | AV9: 0 | AW9: 0 | AY9: 0 | AZ9: Absent | BA9: Absent | BB9: Absent | BC9: Absent | BD9: Absent | BE9: Absent | BF9: Absent | BG9: Present | BH9: Recorded | BJ9: 1 | BM9: Kiap-TU-Wish | BN9: Unknown | BO9: 070400010701 | BP9: Isabelle Creek | BQ9: 0704000107
A10: Dev: DBParsing_231030_v01.xlsm | B10: vSO8Z1gbM7hfp3OtebbB | C10: 45576.703 | D10: 45576.453 | E10: 45576 | F10: 2024 | G10: 10 | H10: VCf2q8JFBSOaJbmxiMqirI5xKFn2 | I10: Plum Creek @ Plum City Park | J10: -92.189548 | K10: 44.632814 | N10: 0 | P10: 1 | Q10: 120 | R10: 180 | U10: 7 | V10: 1 | W10: 0 | X10: 1 | Y10: 59 | Z10: 0 | AA10: 0 | AB10: 2 | AC10: River/Stream | AE10: -1 | AF10: -1 | AG10: -1 | AH10: -1 | AI10: -1 | AJ10: -1 | AK10: -1 | AL10: -1 | AM10: 1 | AN10: Mid-stage | AO10: 1 | AP10: Clear | AQ10: 1 | AR10: None | AS10: 0 | AT10: 0 | AU10: 0 | AV10: 0 | AW10: 0 | AY10: 0 | AZ10: No Data | BA10: No Data | BB10: No Data | BC10: No Data | BD10: No Data | BE10: No Data | BF10: No Data | BG10: No Data | BH10: No Data | BI10: Plum Creek | BJ10: 1 | BK10: 1 | BL10: 1 | BM10: Kiap-TU-Wish | BN10: Kiap-TU-Wish | BO10: 070500051101 | BP10: Nugget Lake-Plum Creek | BQ10: 0705000511
A11: Dev: DBParsing_231030_v01.xlsm | B11: ef3rXz53Wbd4V4SY7bHX | C11: 45576.678 | D11: 45576.428 | E11: 45576 | F11: 2024 | G11: 10 | H11: VCf2q8JFBSOaJbmxiMqirI5xKFn2 | I11: Pine Creek @ County Rd. AA | J11: -92.283925 | K11: 44.542201 | N11: 0 | P11: 1 | Q11: 180 | R11: 180 | U11: 7.5 | V11: 1 | W11: 0 | X11: 1 | Y11: 52 | Z11: 1 | AA11: 0 | AB11: 5 | AC11: River/Stream | AE11: -1 | AF11: -1 | AG11: -1 | AH11: -1 | AI11: -1 | AJ11: -1 | AK11: -1 | AL11: -1 | AM11: 1 | AN11: Baseflow | AO11: 1 | AP11: Clear | AQ11: 1 | AR11: None | AS11: 0 | AT11: 0 | AU11: 0 | AV11: 0 | AW11: 0 | AY11: 0 | AZ11: No Data | BA11: No Data | BB11: No Data | BC11: No Data | BD11: No Data | BE11: No Data | BF11: No Data | BG11: No Data | BH11: No Data | BI11: Pine Creek | BJ11: 1 | BK11: 1 | BL11: 1 | BM11: Wisconsin Clear Water | BN11: Kiap-TU-Wish | BO11: 070400010702 | BP11: Pine Creek | BQ11: 0704000107
A12: Dev: DBParsing_231030_v01.xlsm | B12: UC3FLgahXBrYRatX6I9T | C12: 45575.627 | D12: 45575.377 | E12: 45575 | F12: 2024 | G12: 10 | H12: VQ9bNtzttGcXOEuaXrEAEYLfT103 | J12: -92.614863 | K12: 44.454619 | N12: 0 | P12: 1 | Q12: 120 | R12: 180 | U12: 7.5 | V12: 1 | W12: 0 | X12: 1 | Y12: 50 | Z12: 1 | AA12: 0 | AB12: 10 | AC12: Springs | AD12: None | AE12: 0 | AF12: 0 | AG12: 0 | AH12: 0 | AI12: 0 | AJ12: 0 | AK12: 0 | AL12: 1 | AM12: 0 | AN12: Baseflow | AO12: 1 | AP12: Clear | AQ12: 1 | AR12: None | AS12: 0 | AT12: 0 | AU12: 0 | AV12: 0 | AW12: 0 | AY12: 0 | AZ12: Absent | BA12: Absent | BB12: Absent | BC12: Absent | BD12: Absent | BE12: Absent | BF12: Absent | BG12: Present | BH12: Recorded | BI12: Hay Creek | BJ12: 1 | BM12: Twin Cities (TCTU) | BN12: Hiawatha | BO12: 070400010401 | BP12: Hay Creek | BQ12: 0704000104
A13: Dev: DBParsing_231030_v01.xlsm | B13: RlfkVu0i6kHSPOkP0fg4 | C13: 45569.626 | D13: 45569.376 | E13: 45569 | F13: 2024 | G13: 10 | H13: 80reiKTTqGYqqpgYAhPwqypFwak1 | J13: -92.195375 | K13: 43.811325 | M13: 2024-10-04 10:02:08.954120.jpg-0 | N13: 1 | P13: 0 | V13: 1 | W13: 0 | X13: 1 | Y13: 48 | Z13: 1 | AA13: 0 | AB13: 5 | AC13: River/Stream | AD13: None | AE13: 0 | AF13: 0 | AG13: 0 | AH13: 0 | AI13: 0 | AJ13: 0 | AK13: 0 | AL13: 1 | AM13: 0 | AN13: Mid-stage | AO13: 1 | AP13: Murky | AQ13: 1 | AR13: None | AS13: 0 | AT13: 0 | AU13: 0 | AV13: 0 | AW13: 0 | AX13: Lost Creek is up a bit but no rain of late. looks murky. not sure why. | AY13: 1 | AZ13: Absent | BA13: Absent | BB13: Absent | BC13: Absent | BD13: Absent | BE13: Absent | BF13: Absent | BG13: Present | BH13: Recorded | BI13: Bear Creek | BJ13: 1 | BM13: Hiawatha | BN13: Hiawatha | BO13: 070400080207 | BP13: Bear Creek | BQ13: 0704000802
A14: Dev: DBParsing_231030_v01.xlsm | B14: 1dLTqjMBsqW0BBhzAec8 | C14: 45569.616 | D14: 45569.366 | E14: 45569 | F14: 2024 | G14: 10 | H14: 80reiKTTqGYqqpgYAhPwqypFwak1 | I14: Other Locations | J14: -92.173817 | K14: 43.822348 | M14: 2024-10-04 09:47:26.558896.jpg-0 | N14: 1 | P14: 0 | V14: 1 | W14: 0 | X14: 1 | Y14: 53 | Z14: 1 | AA14: 0 | AB14: 2 | AC14: River/Stream | AD14: None | AE14: 0 | AF14: 0 | AG14: 0 | AH14: 0 | AI14: 0 | AJ14: 0 | AK14: 0 | AL14: 1 | AM14: 0 | AN14: Mid-stage | AO14: 1 | AP14: Murky | AQ14: 1 | AR14: None | AS14: 0 | AT14: 0 | AU14: 0 | AV14: 0 | AW14: 0 | AY14: 0 | AZ14: Absent | BA14: Absent | BB14: Absent | BC14: Absent | BD14: Absent | BE14: Absent | BF14: Absent | BG14: Present | BH14: Recorded | BI14: North Branch Root River | BM14: Hiawatha | BN14: Hiawatha | BO14: 070400080108 | BP14: North Branch Root River | BQ14: 0704000801
A15: Dev: DBParsing_231030_v01.xlsm | B15: EFF0ZxM4If7mM5H7JoRZ | C15: 45568.724 | D15: 45568.474 | E15: 45568 | F15: 2024 | G15: 10 | H15: VQ9bNtzttGcXOEuaXrEAEYLfT103 | J15: -92.689313 | K15: 43.824756 | N15: 0 | P15: 1 | Q15: 0 | R15: 60 | U15: 7.5 | V15: 1 | W15: 0 | X15: 1 | Y15: 56 | Z15: 1 | AA15: 0 | AB15: 0 | AC15: River/Stream | AD15: None | AE15: 0 | AF15: 0 | AG15: 0 | AH15: 0 | AI15: 0 | AJ15: 0 | AK15: 0 | AL15: 1 | AM15: 0 | AN15: Baseflow | AO15: 1 | AP15: Clear | AQ15: 1 | AR15: None | AS15: 0 | AT15: 0 | AU15: 0 | AV15: 0 | AW15: 0 | AY15: 0 | AZ15: Absent | BA15: Absent | BB15: Absent | BC15: Absent | BD15: Absent | BE15: Absent | BF15: Absent | BG15: Present | BH15: Recorded | BI15: North Branch Root River | BM15: Hiawatha | BN15: Hiawatha | BO15: 070400080101 | BP15: Headwaters North Branch Root River | BQ15: 0704000801
A16: Dev: DBParsing_231030_v01.xlsm | B16: oGdLeYPS4ZcTpXtXYKNB | C16: 45568.689 | D16: 45568.439 | E16: 45568 | F16: 2024 | G16: 10 | H16: VQ9bNtzttGcXOEuaXrEAEYLfT103 | J16: -92.488043 | K16: 43.645086 | N16: 0 | P16: 1 | Q16: 0 | R16: 0 | U16: 7.5 | V16: 1 | W16: 0 | X16: 1 | Y16: 56 | Z16: 1 | AA16: 0 | AB16: 0 | AC16: River/Stream | AD16: None | AE16: 0 | AF16: 0 | AG16: 0 | AH16: 0 | AI16: 0 | AJ16: 0 | AK16: 0 | AL16: 1 | AM16: 0 | AN16: Baseflow | AO16: 1 | AP16: Clear | AQ16: 1 | AR16: None | AS16: 0 | AT16: 0 | AU16: 0 | AV16: 0 | AW16: 0 | AY16: 0 | AZ16: Absent | BA16: Absent | BB16: Absent | BC16: Absent | BD16: Absent | BE16: Absent | BF16: Absent | BG16: Present | BH16: Recorded | BI16: South Branch Root River | BM16: Hiawatha | BN16: Hiawatha | BO16: 070400080401 | BP16: Headwaters South Branch Root River | BQ16: 0704000804
A17: Dev: DBParsing_231030_v01.xlsm | B17: TN2fl39g5bG9uMUc1jQt | C17: 45567.959 | D17: 45567.709 | E17: 45567 | F17: 2024 | G17: 10 | H17: H4dZvxTdViejefqREn5k066JVZG3 | J17: -92.23632 | K17: 44.230641 | M17: 2024-10-02 18:01:05.677657.jpg-0 | N17: 1 | P17: 1 | Q17: 40 | R17: 180 | U17: 7 | V17: 1 | W17: 100 | X17: 1 | Y17: 64 | Z17: 1 | AA17: 0 | AB17: 5 | AC17: River/Stream | AD17: None | AE17: 0 | AF17: 0 | AG17: 0 | AH17: 0 | AI17: 0 | AJ17: 0 | AK17: 0 | AL17: 1 | AM17: 0 | AN17: Baseflow | AO17: 1 | AP17: Clear | AQ17: 1 | AR17: None | AS17: 0 | AT17: 0 | AU17: 0 | AV17: 0 | AW17: 0 | AX17: long creek downstream from Cnty 8 bridge | AY17: 1 | AZ17: Absent | BA17: Absent | BB17: Absent | BC17: Absent | BD17: Absent | BE17: Absent | BF17: Absent | BG17: Present | BH17: Recorded | BI17: Long Creek | BJ17: 1 | BK17: 1 | BL17: 1 | BM17: Hiawatha | BN17: Hiawatha | BO17: 070400040505 | BP17: Long Creek | BQ17: 0704000405
A18: Dev: DBParsing_231030_v01.xlsm | B18: y0n1PBzO2OEMuMKcHxhn | C18: 45567.94 | D18: 45567.69 | E18: 45567 | F18: 2024 | G18: 10 | H18: H4dZvxTdViejefqREn5k066JVZG3 | J18: -92.149234 | K18: 44.248828 | M18: 2024-10-02 17:33:23.653241.jpg-0 | N18: 1 | P18: 1 | Q18: 80 | R18: 0 | U18: 7 | V18: 1 | W18: 100 | X18: 1 | Y18: 63 | Z18: 1 | AA18: 0 | AB18: 5 | AC18: River/Stream | AD18: None | AE18: 0 | AF18: 0 | AG18: 0 | AH18: 0 | AI18: 0 | AJ18: 0 | AK18: 0 | AL18: 1 | AM18: 0 | AN18: Baseflow | AO18: 1 | AP18: Clear | AQ18: 1 | AR18: None | AS18: 0 | AT18: 0 | AU18: 0 | AV18: 0 | AW18: 0 | AX18: West Indian by parking lot | AY18: 1 | AZ18: Absent | BA18: Absent | BB18: Absent | BC18: Absent | BD18: Absent | BE18: Absent | BF18: Absent | BG18: Present | BH18: Recorded | BJ18: 1 | BK18: 1 | BL18: 1 | BM18: Hiawatha | BN18: Hiawatha | BO18: 070400040510 | BP18: West Indian Creek | BQ18: 0704000405
A19: Dev: DBParsing_231030_v01.xlsm | B19: rGj17OQRpq7y2LYBvGJg | C19: 45567.787 | D19: 45567.537 | E19: 45567 | F19: 2024 | G19: 10 | H19: GFBS1bSIACUVgSmsBlw0BYkB9i72 | J19: -90.887301 | K19: 43.733607 | M19: 2024-10-02 13:52:50.878327.jpg-0 | N19: 1 | P19: 1 | Q19: 180 | R19: 120 | U19: 7.5 | V19: 1 | W19: 0 | X19: 1 | Y19: 55 | Z19: 1 | AA19: 0 | AB19: 2 | AC19: River/Stream | AD19: None | AE19: 0 | AF19: 0 | AG19: 0 | AH19: 0 | AI19: 0 | AJ19: 0 | AK19: 0 | AL19: 1 | AM19: 0 | AN19: Baseflow | AO19: 1 | AP19: Clear | AQ19: 1 | AR19: None | AS19: 0 | AT19: 0 | AU19: 0 | AV19: 0 | AW19: 0 | AY19: 0 | AZ19: Absent | BA19: Absent | BB19: Absent | BC19: Absent | BD19: Absent | BE19: Absent | BF19: Absent | BG19: Present | BH19: Recorded | BI19: Rullands Coulee Creek | BJ19: 1 | BM19: Coulee Region | BN19: TU Staff | BO19: 070600010101 | BP19: Timber Coulee Creek | BQ19: 0706000101
A20: Dev: DBParsing_231030_v01.xlsm | B20: WXfDFWuy6t485zEe9Y3m | C20: 45565.689 | D20: 45565.439 | E20: 45565 | F20: 2024 | G20: 9 | H20: 80reiKTTqGYqqpgYAhPwqypFwak1 | J20: -92.649573 | K20: 44.075224 | N20: 0 | P20: 0 | V20: 0 | X20: 1 | Y20: 56 | Z20: 1 | AA20: 0 | AB20: 5 | AC20: River/Stream | AD20: None | AE20: 0 | AF20: 0 | AG20: 0 | AH20: 0 | AI20: 0 | AJ20: 0 | AK20: 0 | AL20: 1 | AM20: 0 | AN20: Baseflow | AO20: 1 | AP20: Murky | AQ20: 1 | AR20: None | AS20: 0 | AT20: 0 | AU20: 0 | AV20: 0 | AW20: 0 | AY20: 0 | AZ20: Absent | BA20: Absent | BB20: Absent | BC20: Absent | BD20: Absent | BE20: Absent | BF20: Absent | BG20: Present | BH20: Recorded | BM20: Hiawatha | BN20: Hiawatha | BO20: 070400040205 | BP20: South Branch Middle Fork Zumbro River | BQ20: 0704000402
A21: Dev: DBParsing_231030_v01.xlsm | B21: LXb54yJfypIJj3msK3G0 | C21: 45565.631 | D21: 45565.381 | E21: 45565 | F21: 2024 | G21: 9 | H21: VQ9bNtzttGcXOEuaXrEAEYLfT103 | J21: -91.970468 | K21: 44.005512 | N21: 0 | P21: 1 | Q21: 80 | R21: 180 | U21: 7 | V21: 1 | W21: 100 | X21: 1 | Y21: 56 | Z21: 1 | AA21: 0 | AB21: 2 | AC21: Springs | AD21: None | AE21: 0 | AF21: 0 | AG21: 0 | AH21: 0 | AI21: 0 | AJ21: 0 | AK21: 0 | AL21: 1 | AM21: 0 | AN21: Baseflow | AO21: 1 | AP21: Clear | AQ21: 1 | AR21: None | AS21: 0 | AT21: 0 | AU21: 0 | AV21: 0 | AW21: 0 | AY21: 0 | AZ21: Absent | BA21: Absent | BB21: Absent | BC21: Absent | BD21: Absent | BE21: Absent | BF21: Absent | BG21: Present | BH21: Recorded | BI21: South Fork Whitewater River | BJ21: 1 | BM21: Win Cres | BN21: Hiawatha | BO21: 070400030307 | BP21: Lower South Fork Whitewater River | BQ21: 0704000303
A22: Dev: DBParsing_231030_v01.xlsm | B22: k2tw9pMkejSiuCOoGngm | C22: 45562.69 | D22: 45562.44 | E22: 45562 | F22: 2024 | G22: 9 | H22: VCf2q8JFBSOaJbmxiMqirI5xKFn2 | I22: Plum Creek @ Plum City Park | J22: -92.189503 | K22: 44.632802 | N22: 0 | P22: 1 | Q22: 120 | R22: 180 | U22: 7 | V22: 1 | W22: 0 | X22: 1 | Y22: 60 | Z22: 1 | AA22: 0 | AB22: 2 | AC22: River/Stream | AE22: -1 | AF22: -1 | AG22: -1 | AH22: -1 | AI22: -1 | AJ22: -1 | AK22: -1 | AL22: -1 | AM22: 1 | AN22: Mid-stage | AO22: 1 | AP22: Clear | AQ22: 1 | AR22: None | AS22: 0 | AT22: 0 | AU22: 0 | AV22: 0 | AW22: 0 | AY22: 0 | AZ22: No Data | BA22: No Data | BB22: No Data | BC22: No Data | BD22: No Data | BE22: No Data | BF22: No Data | BG22: No Data | BH22: No Data | BI22: Plum Creek | BJ22: 1 | BK22: 1 | BL22: 1 | BM22: Kiap-TU-Wish | BN22: Kiap-TU-Wish | BO22: 070500051101 | BP22: Nugget Lake-Plum Creek | BQ22: 0705000511
A23: Dev: DBParsing_231030_v01.xlsm | B23: ATecdl8SnqOXVtJPZ01R | C23: 45562.675 | D23: 45562.425 | E23: 45562 | F23: 2024 | G23: 9 | H23: VQ9bNtzttGcXOEuaXrEAEYLfT103 | J23: -91.878951 | K23: 43.878991 | N23: 0 | P23: 1 | Q23: 80 | R23: 120 | U23: 7.5 | V23: 1 | W23: 100 | X23: 1 | Y23: 56 | Z23: 1 | AA23: 0 | AB23: 5 | AC23: Springs | AD23: None | AE23: 0 | AF23: 0 | AG23: 0 | AH23: 0 | AI23: 0 | AJ23: 0 | AK23: 0 | AL23: 1 | AM23: 0 | AN23: Baseflow | AO23: 1 | AP23: Clear | AQ23: 1 | AR23: None | AS23: 0 | AT23: 0 | AU23: 0 | AV23: 0 | AW23: 0 | AY23: 0 | AZ23: Absent | BA23: Absent | BB23: Absent | BC23: Absent | BD23: Absent | BE23: Absent | BF23: Absent | BG23: Present | BH23: Recorded | BI23: 0 | BJ23: 1 | BK23: 1 | BL23: 1 | BM23: Win Cres | BN23: Hiawatha | BO23: 070400080503 | BP23: Pine Creek | BQ23: 0704000805
A24: Dev: DBParsing_231030_v01.xlsm | B24: 315eGmQ1kn6o4MrrroBq | C24: 45561.698 | D24: 45561.448 | E24: 45561 | F24: 2024 | G24: 9 | H24: VCf2q8JFBSOaJbmxiMqirI5xKFn2 | I24: Pine Creek @ County Rd. AA | J24: -92.284235 | K24: 44.542189 | N24: 0 | P24: 1 | Q24: 180 | R24: 180 | U24: 7.5 | V24: 1 | W24: 0 | X24: 1 | Y24: 56 | Z24: 1 | AA24: 0 | AB24: 5 | AC24: River/Stream | AE24: -1 | AF24: -1 | AG24: -1 | AH24: -1 | AI24: -1 | AJ24: -1 | AK24: -1 | AL24: -1 | AM24: 1 | AN24: Baseflow | AO24: 1 | AP24: Clear | AQ24: 1 | AR24: None | AS24: 0 | AT24: 0 | AU24: 0 | AV24: 0 | AW24: 0 | AY24: 0 | AZ24: No Data | BA24: No Data | BB24: No Data | BC24: No Data | BD24: No Data | BE24: No Data | BF24: No Data | BG24: No Data | BH24: No Data | BI24: Pine Creek | BJ24: 1 | BK24: 1 | BL24: 1 | BM24: Wisconsin Clear Water | BN24: Kiap-TU-Wish | BO24: 070400010702 | BP24: Pine Creek | BQ24: 0704000107
A25: Dev: DBParsing_231030_v01.xlsm | B25: x6kNUFvkPJdmwD2Cmhr6 | C25: 45560.782 | D25: 45560.532 | E25: 45560 | F25: 2024 | G25: 9 | H25: VQ9bNtzttGcXOEuaXrEAEYLfT103 | J25: -91.580957 | K25: 43.641461 | N25: 0 | P25: 1 | Q25: 0 | R25: 60 | U25: 7 | V25: 1 | W25: 0 | X25: 1 | Y25: 52 | Z25: 1 | AA25: 0 | AB25: 5 | AC25: River/Stream | AD25: None | AE25: 0 | AF25: 0 | AG25: 0 | AH25: 0 | AI25: 0 | AJ25: 0 | AK25: 0 | AL25: 1 | AM25: 0 | AN25: Baseflow | AO25: 1 | AP25: Clear | AQ25: 1 | AR25: None | AS25: 0 | AT25: 0 | AU25: 0 | AV25: 0 | AW25: 0 | AY25: 0 | AZ25: Absent | BA25: Absent | BB25: Absent | BC25: Absent | BD25: Absent | BE25: Absent | BF25: Absent | BG25: Present | BH25: Recorded | BJ25: 1 | BM25: Win Cres | BN25: Hiawatha | BO25: 070400080805 | BP25: Beaver Creek | BQ25: 0704000808
A26: Dev: DBParsing_231030_v01.xlsm | B26: MPpX1Gv13cIjfEk9vvIF | C26: 45560.76 | D26: 45560.51 | E26: 45560 | F26: 2024 | G26: 9 | H26: VQ9bNtzttGcXOEuaXrEAEYLfT103 | J26: -91.373367 | K26: 43.603532 | N26: 0 | P26: 1 | Q26: 80 | R26: 180 | U26: 8 | V26: 1 | W26: 0 | X26: 1 | Y26: 60 | Z26: 1 | AA26: 0 | AB26: 2 | AC26: River/Stream | AD26: None | AE26: 0 | AF26: 0 | AG26: 0 | AH26: 0 | AI26: 0 | AJ26: 0 | AK26: 0 | AL26: 1 | AM26: 0 | AN26: Baseflow | AO26: 1 | AP26: Murky | AQ26: 1 | AR26: None | AS26: 0 | AT26: 0 | AU26: 0 | AV26: 0 | AW26: 0 | AY26: 0 | AZ26: Absent | BA26: Absent | BB26: Absent | BC26: Absent | BD26: Absent | BE26: Absent | BF26: Absent | BG26: Present | BH26: Recorded | BI26: Crooked Creek | BJ26: 1 | BM26: Win Cres | BN26: Hiawatha | BO26: 070600010203 | BP26: Clear Creek-Crooked Creek | BQ26: 0706000102
A27: Dev: DBParsing_231030_v01.xlsm | B27: F7QLJSHtMpAbgyE7oAgZ | C27: 45560.742 | D27: 45560.492 | E27: 45560 | F27: 2024 | G27: 9 | H27: VQ9bNtzttGcXOEuaXrEAEYLfT103 | J27: -91.413098 | K27: 43.54054 | N27: 0 | P27: 1 | Q27: 80 | R27: 120 | U27: 7.5 | V27: 1 | W27: 0 | X27: 0 | Z27: 1 | AA27: 0 | AB27: 5 | AC27: River/Stream | AD27: None | AE27: 0 | AF27: 0 | AG27: 0 | AH27: 0 | AI27: 0 | AJ27: 0 | AK27: 0 | AL27: 1 | AM27: 0 | AN27: Baseflow | AO27: 1 | AP27: Murky | AQ27: 1 | AR27: None | AS27: 0 | AT27: 0 | AU27: 0 | AV27: 0 | AW27: 0 | AY27: 0 | AZ27: Absent | BA27: Absent | BB27: Absent | BC27: Absent | BD27: Absent | BE27: Absent | BF27: Absent | BG27: Present | BH27: Recorded | BI27: Winnebago Creek | BJ27: 1 | BK27: 1 | BL27: 1 | BM27: Win Cres | BN27: Hiawatha | BO27: 070600010401 | BP27: Upper Winnebago Creek | BQ27: 0706000104
A28: Dev: DBParsing_231030_v01.xlsm | B28: K35jlV9fHdkoplQIGzc1 | C28: 45560.703 | D28: 45560.453 | E28: 45560 | F28: 2024 | G28: 9 | H28: VQ9bNtzttGcXOEuaXrEAEYLfT103 | J28: -91.569788 | K28: 43.502341 | N28: 0 | P28: 1 | Q28: 120 | R28: 180 | U28: 7.5 | V28: 1 | W28: 0 | X28: 1 | Y28: 52 | Z28: 1 | AA28: 0 | AB28: 0 | AC28: River/Stream | AD28: None | AE28: 0 | AF28: 0 | AG28: 0 | AH28: 0 | AI28: 0 | AJ28: 0 | AK28: 0 | AL28: 1 | AM28: 0 | AN28: Baseflow | AO28: 1 | AP28: Clear | AQ28: 1 | AR28: None | AS28: 0 | AT28: 0 | AU28: 0 | AV28: 0 | AW28: 0 | AY28: 0 | AZ28: Absent | BA28: Absent | BB28: Absent | BC28: Absent | BD28: Absent | BE28: Absent | BF28: Absent | BG28: Present | BH28: Recorded | BI28: Bee Creek | BJ28: 1 | BK28: 1 | BL28: 1 | BM28: Win Cres | BN28: Hiawatha | BO28: 070600020502 | BP28: Waterloo Creek | BQ28: 0706000205
A29: Dev: DBParsing_231030_v01.xlsm | B29: 5Br5G43UJ3veHyyBKWIO | C29: 45560.681 | D29: 45560.431 | E29: 45560 | F29: 2024 | G29: 9 | H29: wOnBJTAV2CZK06CRnr5oUK45EDv1 | J29: -90.471891 | K29: 43.047571 | M29: 2024-09-25 11:20:13.472036.jpg-0 | N29: 1 | P29: 1 | Q29: 180 | R29: 120 | U29: 7.5 | V29: 1 | W29: 0 | X29: 1 | Y29: 57 | Z29: 1 | AA29: 0 | AB29: 5 | AC29: River/Stream | AD29: Bank Erosion,Livestock in Water | AE29: 0 | AF29: 1 | AG29: 0 | AH29: 0 | AI29: 1 | AJ29: 0 | AK29: 0 | AL29: 0 | AM29: 0 | AN29: Mid-stage | AO29: 1 | AP29: Murky | AQ29: 1 | AR29: None | AS29: 0 | AT29: 0 | AU29: 0 | AV29: 0 | AW29: 0 | AX29: recent rain up to 4 inches depending on where. water was 3 feet higher recently | AY29: 1 | AZ29: Absent | BA29: Present | BB29: Absent | BC29: Absent | BD29: Present | BE29: Absent | BF29: Absent | BG29: Absent | BH29: Recorded | BI29: Blue River | BJ29: 1 | BM29: Harry & Laura Nohr | BN29: US FWS | BO29: 070700051406 | BP29: Big Rock Branch-Blue River | BQ29: 0707000514
A30: Dev: DBParsing_231030_v01.xlsm | B30: GMwLSDlBA4LtNP55jHS0 | C30: 45560.674 | D30: 45560.424 | E30: 45560 | F30: 2024 | G30: 9 | H30: VQ9bNtzttGcXOEuaXrEAEYLfT103 | J30: -91.814811 | K30: 43.597239 | N30: 0 | P30: 1 | Q30: 80 | R30: 180 | U30: 7.5 | V30: 1 | W30: 0 | X30: 1 | Y30: 54 | Z30: 1 | AA30: 0 | AB30: 5 | AC30: River/Stream | AD30: None | AE30: 0 | AF30: 0 | AG30: 0 | AH30: 0 | AI30: 0 | AJ30: 0 | AK30: 0 | AL30: 1 | AM30: 0 | AN30: Baseflow | AO30: 1 | AP30: Clear | AQ30: 1 | AR30: None | AS30: 0 | AT30: 0 | AU30: 0 | AV30: 0 | AW30: 0 | AY30: 0 | AZ30: Absent | BA30: Absent | BB30: Absent | BC30: Absent | BD30: Absent | BE30: Absent | BF30: Absent | BG30: Present | BH30: Recorded | BI30: Wisel Creek | BJ30: 1 | BK30: 1 | BL30: 1 | BM30: Win Cres | BN30: Hiawatha | BO30: 070400080802 | BP30: Wisel Creek | BQ30: 0704000808
A31: Dev: DBParsing_231030_v01.xlsm | B31: h3OyYyOOmRe7elBpNakO | C31: 45560.644 | D31: 45560.394 | E31: 45560 | F31: 2024 | G31: 9 | H31: VQ9bNtzttGcXOEuaXrEAEYLfT103 | J31: -91.79196 | K31: 43.67377 | N31: 0 | P31: 1 | Q31: 120 | R31: 180 | U31: 8 | V31: 1 | W31: 0 | X31: 1 | Y31: 54 | Z31: 1 | AA31: 0 | AB31: 5 | AC31: River/Stream | AD31: None | AE31: 0 | AF31: 0 | AG31: 0 | AH31: 0 | AI31: 0 | AJ31: 0 | AK31: 0 | AL31: 1 | AM31: 0 | AN31: Baseflow | AO31: 1 | AP31: Clear | AQ31: 1 | AR31: None | AS31: 0 | AT31: 0 | AU31: 0 | AV31: 0 | AW31: 0 | AY31: 0 | AZ31: Absent | BA31: Absent | BB31: Absent | BC31: Absent | BD31: Absent | BE31: Absent | BF31: Absent | BG31: Present | BH31: Recorded | BI31: 0 | BJ31: 1 | BK31: 1 | BL31: 1 | BM31: Win Cres | BN31: Hiawatha | BO31: 070400080803 | BP31: Middle South Fork Root River | BQ31: 0704000808
A32: Dev: DBParsing_231030_v01.xlsm | B32: fDbzZMAsLMrO5uJSuHyt | C32: 45559.709 | D32: 45559.459 | E32: 45559 | F32: 2024 | G32: 9 | H32: VQ9bNtzttGcXOEuaXrEAEYLfT103 | J32: -92.293851 | K32: 43.727874 | N32: 0 | P32: 1 | Q32: 80 | R32: 180 | U32: 7.5 | V32: 1 | W32: 0 | X32: 1 | Y32: 57 | Z32: 1 | AA32: 0 | AB32: 5 | AC32: River/Stream | AD32: None | AE32: 0 | AF32: 0 | AG32: 0 | AH32: 0 | AI32: 0 | AJ32: 0 | AK32: 0 | AL32: 1 | AM32: 0 | AN32: Baseflow | AO32: 1 | AP32: Clear | AQ32: 1 | AR32: None | AS32: 0 | AT32: 0 | AU32: 0 | AV32: 0 | AW32: 0 | AY32: 0 | AZ32: Absent | BA32: Absent | BB32: Absent | BC32: Absent | BD32: Absent | BE32: Absent | BF32: Absent | BG32: Present | BH32: Recorded | BI32: Spring Valley Creek | BJ32: 1 | BM32: Hiawatha | BN32: Hiawatha | BO32: 070400080205 | BP32: Spring Valley Creek | BQ32: 0704000802
A33: Dev: DBParsing_231030_v01.xlsm | B33: 6vfN6zwGtA1r1PDfqcNL | C33: 45559.681 | D33: 45559.431 | E33: 45559 | F33: 2024 | G33: 9 | H33: VQ9bNtzttGcXOEuaXrEAEYLfT103 | J33: -92.343748 | K33: 43.602327 | N33: 0 | P33: 1 | Q33: 120 | R33: 180 | U33: 7.5 | V33: 1 | W33: 0 | X33: 1 | Y33: 53 | Z33: 1 | AA33: 0 | AB33: 10 | AC33: River/Stream | AD33: None | AE33: 0 | AF33: 0 | AG33: 0 | AH33: 0 | AI33: 0 | AJ33: 0 | AK33: 0 | AL33: 1 | AM33: 0 | AN33: Baseflow | AO33: 1 | AP33: Clear | AQ33: 1 | AR33: None | AS33: 0 | AT33: 0 | AU33: 0 | AV33: 0 | AW33: 0 | AY33: 0 | AZ33: Absent | BA33: Absent | BB33: Absent | BC33: Absent | BD33: Absent | BE33: Absent | BF33: Absent | BG33: Present | BH33: Recorded | BI33: Etna Creek | BJ33: 1 | BM33: Hiawatha | BN33: Hiawatha | BO33: 070400080402 | BP33: Etna Creek-South Branch Root River | BQ33: 0704000804
A34: Dev: DBParsing_231030_v01.xlsm | B34: 8oC4USFto2fkxpH59LG7 | C34: 45548.604 | D34: 45548.354 | E34: 45548 | F34: 2024 | G34: 9 | H34: 80reiKTTqGYqqpgYAhPwqypFwak1 | J34: -92.055354 | K34: 44.092583 | M34: 2024-09-13 09:29:22.813119.jpg-0 | N34: 1 | P34: 1 | Q34: 180 | R34: 180 | U34: 8 | V34: 1 | W34: 0 | X34: 1 | Y34: 57 | Z34: 1 | AA34: 0 | AB34: 5 | AC34: River/Stream | AD34: None | AE34: 0 | AF34: 0 | AG34: 0 | AH34: 0 | AI34: 0 | AJ34: 0 | AK34: 0 | AL34: 1 | AM34: 0 | AN34: Mid-stage | AO34: 1 | AP34: Murky | AQ34: 1 | AR34: None | AS34: 0 | AT34: 0 | AU34: 0 | AV34: 0 | AW34: 0 | AX34: North Branch Whitewater is more stained than I thought it would be. Fairwater. | AY34: 1 | AZ34: Absent | BA34: Absent | BB34: Absent | BC34: Absent | BD34: Absent | BE34: Absent | BF34: Absent | BG34: Present | BH34: Recorded | BI34: North Fork Whitewater River | BJ34: 1 | BM34: Win Cres | BN34: Hiawatha | BO34: 070400030304 | BP34: Lower North Fork Whitewater River | BQ34: 0704000303
A35: Dev: DBParsing_231030_v01.xlsm | B35: hHKh8jH4j8IrBB3NZFjN | C35: 45547.695 | D35: 45547.445 | E35: 45547 | F35: 2024 | G35: 9 | H35: 7a7IFD1YT3aDXB8CbnSJjn1oLRC2 | I35: Isabelle Creek @ County Rd. EE | J35: -92.442779 | K35: 44.621391 | N35: 0 | P35: 1 | Q35: 120 | R35: 180 | U35: 8 | V35: 1 | W35: 100 | X35: 1 | Y35: 69 | Z35: 1 | AA35: 0 | AB35: 5 | AC35: River/Stream | AD35: None | AE35: 0 | AF35: 0 | AG35: 0 | AH35: 0 | AI35: 0 | AJ35: 0 | AK35: 0 | AL35: 1 | AM35: 0 | AN35: Baseflow | AO35: 1 | AP35: Murky | AQ35: 1 | AR35: None | AS35: 0 | AT35: 0 | AU35: 0 | AV35: 0 | AW35: 0 | AY35: 0 | AZ35: Absent | BA35: Absent | BB35: Absent | BC35: Absent | BD35: Absent | BE35: Absent | BF35: Absent | BG35: Present | BH35: Recorded | BI35: Isabelle Creek | BJ35: 1 | BM35: Kiap-TU-Wish | BN35: Unknown | BO35: 070400010701 | BP35: Isabelle Creek | BQ35: 0704000107
A36: Dev: DBParsing_231030_v01.xlsm | B36: TGHCciFGIqh4qNDTpWTq | C36: 45545.713 | D36: 45545.463 | E36: 45545 | F36: 2024 | G36: 9 | H36: 80reiKTTqGYqqpgYAhPwqypFwak1 | J36: -92.650029 | K36: 44.075179 | N36: 0 | P36: 0 | V36: 0 | X36: 1 | Y36: 59 | Z36: 1 | AA36: 0 | AB36: 5 | AC36: River/Stream | AD36: None | AE36: 0 | AF36: 0 | AG36: 0 | AH36: 0 | AI36: 0 | AJ36: 0 | AK36: 0 | AL36: 1 | AM36: 0 | AN36: Mid-stage | AO36: 1 | AP36: Murky | AQ36: 1 | AR36: None | AS36: 0 | AT36: 0 | AU36: 0 | AV36: 0 | AW36: 0 | AY36: 0 | AZ36: Absent | BA36: Absent | BB36: Absent | BC36: Absent | BD36: Absent | BE36: Absent | BF36: Absent | BG36: Present | BH36: Recorded | BI36: South Branch Middle Fork Zumbro River | BM36: Hiawatha | BN36: Hiawatha | BO36: 070400040205 | BP36: South Branch Middle Fork Zumbro River | BQ36: 0704000402
A37: Dev: DBParsing_231030_v01.xlsm | B37: nKBxSyTACqbPXHCVov9k | C37: 45543.702 | D37: 45543.452 | E37: 45543 | F37: 2024 | G37: 9 | H37: wOnBJTAV2CZK06CRnr5oUK45EDv1 | J37: -90.827354 | K37: 43.559228 | M37: 2024-09-08 11:50:44.402382.jpg-0 | N37: 1 | P37: 1 | Q37: 0 | R37: 30 | U37: 7.5 | V37: 1 | W37: 0 | X37: 1 | Y37: 56 | Z37: 1 | AA37: 0 | AB37: 2 | AC37: River/Stream | AD37: Bank Erosion | AE37: 0 | AF37: 1 | AG37: 0 | AH37: 0 | AI37: 0 | AJ37: 0 | AK37: 0 | AL37: 0 | AM37: 0 | AN37: Baseflow | AO37: 1 | AP37: Clear | AQ37: 1 | AR37: None | AS37: 0 | AT37: 0 | AU37: 0 | AV37: 0 | AW37: 0 | AX37: 2nd entry as first crashed. lots of brook trout. stream 51 at 9am | AY37: 1 | AZ37: Absent | BA37: Present | BB37: Absent | BC37: Absent | BD37: Absent | BE37: Absent | BF37: Absent | BG37: Absent | BH37: Recorded | BI37: Maple Dale | BK37: 1 | BL37: 1 | BM37: Coulee Region | BN37: US FWS | BO37: 070700060203 | BP37: Bishop Branch | BQ37: 0707000602
A38: Dev: DBParsing_231030_v01.xlsm | B38: gpr43ttOfpJXBgbUojU4 | C38: 45541.853 | D38: 45541.603 | E38: 45541 | F38: 2024 | G38: 9 | H38: 4etfOHFOLNgXiWPM6KYa0g0En8C2 | J38: -90.524037 | K38: 42.270183 | N38: 0 | P38: 1 | Q38: 120 | R38: 120 | U38: 7.5 | V38: 1 | W38: 0 | X38: 1 | Y38: 62 | Z38: 0 | AC38: River/Stream | AD38: None | AE38: 0 | AF38: 0 | AG38: 0 | AH38: 0 | AI38: 0 | AJ38: 0 | AK38: 0 | AL38: 1 | AM38: 0 | AN38: Baseflow | AO38: 1 | AP38: Clear | AQ38: 1 | AR38: None | AS38: 0 | AT38: 0 | AU38: 0 | AV38: 0 | AW38: 0 | AY38: 0 | AZ38: Absent | BA38: Absent | BB38: Absent | BC38: Absent | BD38: Absent | BE38: Absent | BF38: Absent | BG38: Present | BH38: Recorded | BI38: Mill Creek | BJ38: 1 | BM38: Spring Creeks | BN38: Spring Creeks | BO38: 070600050403 | BP38: Storybrook Hollow-Mill Creek | BQ38: 0706000504
A39: Dev: DBParsing_231030_v01.xlsm | B39: MjctNRhnki6R91OIE1k6 | C39: 45538.944 | D39: 45538.694 | E39: 45538 | F39: 2024 | G39: 9 | H39: mMKogvdinjOuckB5tkMQrxnYO852 | I39: Eau Galle River @ WI Hwy 29 | J39: -92.236399 | K39: 44.840174 | M39: 2024-09-03 17:40:03.476724.jpg-0 | N39: 1 | P39: 1 | Q39: 0 | R39: 60 | U39: 7 | V39: 1 | W39: 0 | X39: 1 | Y39: 67 | Z39: 1 | AA39: 0 | AB39: 2 | AC39: River/Stream | AD39: None | AE39: 0 | AF39: 0 | AG39: 0 | AH39: 0 | AI39: 0 | AJ39: 0 | AK39: 0 | AL39: 1 | AM39: 0 | AN39: Mid-stage | AO39: 1 | AP39: Clear | AQ39: 1 | AR39: None | AS39: 0 | AT39: 0 | AU39: 0 | AV39: 0 | AW39: 0 | AY39: 0 | AZ39: Absent | BA39: Absent | BB39: Absent | BC39: Absent | BD39: Absent | BE39: Absent | BF39: Absent | BG39: Present | BH39: Recorded | BI39: Burkhart Creek | BJ39: 1 | BK39: 1 | BL39: 1 | BM39: Kiap-TU-Wish | BN39: Kiap-TU-Wish | BO39: 070500051004 | BP39: Burkhart Creek-Eau Galle Creek | BQ39: 0705000510
A40: Dev: DBParsing_231030_v01.xlsm | B40: ntCQfYcOvqINI2kF431K | C40: 45538.818 | D40: 45538.568 | E40: 45538 | F40: 2024 | G40: 9 | H40: 80reiKTTqGYqqpgYAhPwqypFwak1 | J40: -92.649971 | K40: 44.075177 | N40: 0 | P40: 0 | V40: 0 | X40: 1 | Y40: 62 | Z40: 1 | AA40: 0 | AB40: 2 | AC40: River/Stream | AD40: None | AE40: 0 | AF40: 0 | AG40: 0 | AH40: 0 | AI40: 0 | AJ40: 0 | AK40: 0 | AL40: 1 | AM40: 0 | AN40: Mid-stage | AO40: 1 | AP40: Murky | AQ40: 1 | AR40: None | AS40: 0 | AT40: 0 | AU40: 0 | AV40: 0 | AW40: 0 | AX40: Zumbro is much clearer than last week. | AY40: 1 | AZ40: Absent | BA40: Absent | BB40: Absent | BC40: Absent | BD40: Absent | BE40: Absent | BF40: Absent | BG40: Present | BH40: Recorded | BI40: South Branch Middle Fork Zumbro River | BM40: Hiawatha | BN40: Hiawatha | BO40: 070400040205 | BP40: South Branch Middle Fork Zumbro River | BQ40: 0704000402
A41: Dev: DBParsing_231030_v01.xlsm | B41: gCx8fanVTxPDdVuY05nA | C41: 45534.713 | D41: 45534.463 | E41: 45534 | F41: 2024 | G41: 8 | H41: f7qMRlnlkOgrA1xpaxXrTTeRGWX2 | I41: Kinni River - 478 | J41: -92.645436 | K41: 44.843623 | N41: 0 | P41: 1 | Q41: 180 | R41: 120 | U41: 7.5 | V41: 1 | W41: 100 | X41: 0 | Z41: 1 | AA41: 0 | AB41: 5 | AC41: River/Stream | AD41: Bank Erosion | AE41: 0 | AF41: 1 | AG41: 0 | AH41: 0 | AI41: 0 | AJ41: 0 | AK41: 0 | AL41: 0 | AM41: 0 | AN41: Mid-stage | AO41: 1 | AP41: Clear | AQ41: 1 | AR41: Regional Rainfall | AS41: 1 | AT41: 0 | AU41: 0 | AV41: 0 | AW41: 0 | AX41: Secchi Tube > 100 cm | AY41: 1 | AZ41: Absent | BA41: Present | BB41: Absent | BC41: Absent | BD41: Absent | BE41: Absent | BF41: Absent | BG41: Absent | BH41: Recorded | BI41: Kinnickinnic River | BJ41: 1 | BM41: Kiap-TU-Wish | BN41: Kiap-TU-Wish | BO41: 070300051105 | BP41: Lower Kinnickinnic Pond-Kinnickinnic River | BQ41: 0703000511
A42: Dev: DBParsing_231030_v01.xlsm | B42: XBA97Xk9MYMMB9kCJFnR | C42: 45534.695 | D42: 45534.445 | E42: 45534 | F42: 2024 | G42: 8 | H42: f7qMRlnlkOgrA1xpaxXrTTeRGWX2 | I42: Kinni River - 504 | J42: -92.641665 | K42: 44.849777 | N42: 0 | P42: 1 | Q42: 180 | R42: 120 | U42: 7.5 | V42: 1 | W42: 0 | X42: 0 | Z42: 1 | AA42: 0 | AB42: 5 | AC42: River/Stream | AD42: Bank Erosion | AE42: 0 | AF42: 1 | AG42: 0 | AH42: 0 | AI42: 0 | AJ42: 0 | AK42: 0 | AL42: 0 | AM42: 0 | AN42: Mid-stage | AO42: 1 | AP42: Clear | AQ42: 1 | AR42: Regional Rainfall | AS42: 1 | AT42: 0 | AU42: 0 | AV42: 0 | AW42: 0 | AX42: Secchi Tube > 100 cm | AY42: 1 | AZ42: Absent | BA42: Present | BB42: Absent | BC42: Absent | BD42: Absent | BE42: Absent | BF42: Absent | BG42: Absent | BH42: Recorded | BJ42: 1 | BK42: 1 | BL42: 1 | BM42: Kiap-TU-Wish | BN42: Kiap-TU-Wish | BO42: 070300051105 | BP42: Lower Kinnickinnic Pond-Kinnickinnic River | BQ42: 0703000511
A43: Dev: DBParsing_231030_v01.xlsm | B43: XEoXA0SIAbS8ayyFqbiO | C43: 45534.658 | D43: 45534.408 | E43: 45534 | F43: 2024 | G43: 8 | H43: f7qMRlnlkOgrA1xpaxXrTTeRGWX2 | I43: Kinni River - 120 | J43: -92.732135 | K43: 44.831174 | N43: 0 | P43: 1 | Q43: 180 | R43: 120 | U43: 7.5 | V43: 1 | W43: 100 | X43: 0 | Z43: 1 | AA43: 0 | AB43: 5 | AD43: Bank Erosion | AE43: 0 | AF43: 1 | AG43: 0 | AH43: 0 | AI43: 0 | AJ43: 0 | AK43: 0 | AL43: 0 | AM43: 0 | AN43: Mid-stage | AO43: 1 | AP43: Clear | AQ43: 1 | AR43: Regional Rainfall | AS43: 1 | AT43: 0 | AU43: 0 | AV43: 0 | AW43: 0 | AX43: Secchi Tube > 100 cm | AY43: 1 | AZ43: Absent | BA43: Present | BB43: Absent | BC43: Absent | BD43: Absent | BE43: Absent | BF43: Absent | BG43: Absent | BH43: Recorded | BJ43: 1 | BM43: Kiap-TU-Wish | BN43: Kiap-TU-Wish | BO43: 070300051105 | BP43: Lower Kinnickinnic Pond-Kinnickinnic River | BQ43: 0703000511
A44: Dev: DBParsing_231030_v01.xlsm | B44: h1cN4lXbLqx8xdprxcA5 | C44: 45534.638 | D44: 45534.388 | E44: 45534 | F44: 2024 | G44: 8 | H44: AFSRTEftiTe1HDjxTst1HuMIU1l1 | I44: Plum Creek @ Plum City Park | J44: -92.189604 | K44: 44.632836 | N44: 0 | P44: 1 | Q44: 80 | R44: 120 | U44: 7 | V44: 1 | W44: 0 | X44: 1 | Y44: 68 | Z44: 1 | AA44: 0 | AB44: 2 | AC44: River/Stream | AD44: None | AE44: 0 | AF44: 0 | AG44: 0 | AH44: 0 | AI44: 0 | AJ44: 0 | AK44: 0 | AL44: 1 | AM44: 0 | AN44: Bankfull Stage | AO44: 1 | AP44: Muddy | AQ44: 1 | AR44: None | AS44: 0 | AT44: 0 | AU44: 0 | AV44: 0 | AW44: 0 | AY44: 0 | AZ44: Absent | BA44: Absent | BB44: Absent | BC44: Absent | BD44: Absent | BE44: Absent | BF44: Absent | BG44: Present | BH44: Recorded | BI44: Plum Creek | BJ44: 1 | BK44: 1 | BL44: 1 | BM44: Kiap-TU-Wish | BN44: Kiap-TU-Wish | BO44: 070500051101 | BP44: Nugget Lake-Plum Creek | BQ44: 0705000511
A45: Dev: DBParsing_231030_v01.xlsm | B45: S9YaJnZ6OlIKH5UdU332 | C45: 45532.758 | D45: 45532.508 | E45: 45532 | F45: 2024 | G45: 8 | H45: VQ9bNtzttGcXOEuaXrEAEYLfT103 | J45: -91.580941 | K45: 43.641428 | N45: 0 | P45: 1 | Q45: 0 | R45: 60 | U45: 7 | V45: 1 | W45: 100 | X45: 1 | Y45: 51 | Z45: 1 | AA45: 0 | AB45: 10 | AC45: River/Stream | AE45: -1 | AF45: -1 | AG45: -1 | AH45: -1 | AI45: -1 | AJ45: -1 | AK45: -1 | AL45: -1 | AM45: 1 | AN45: Baseflow | AO45: 1 | AP45: Clear | AQ45: 1 | AR45: None | AS45: 0 | AT45: 0 | AU45: 0 | AV45: 0 | AW45: 0 | AY45: 0 | AZ45: No Data | BA45: No Data | BB45: No Data | BC45: No Data | BD45: No Data | BE45: No Data | BF45: No Data | BG45: No Data | BH45: No Data | BI45: Beaver Creek East | BJ45: 1 | BM45: Win Cres | BN45: Hiawatha | BO45: 070400080805 | BP45: Beaver Creek | BQ45: 0704000808
A46: Dev: DBParsing_231030_v01.xlsm | B46: YXPAkqkW0fic3LIK8nvq | C46: 45532.735 | D46: 45532.485 | E46: 45532 | F46: 2024 | G46: 8 | H46: VQ9bNtzttGcXOEuaXrEAEYLfT103 | J46: -91.373386 | K46: 43.603593 | N46: 0 | P46: 1 | Q46: 120 | R46: 180 | U46: 8.5 | V46: 1 | W46: 0 | X46: 1 | Y46: 67 | Z46: 1 | AA46: 0 | AB46: 2 | AC46: River/Stream | AD46: None | AE46: 0 | AF46: 0 | AG46: 0 | AH46: 0 | AI46: 0 | AJ46: 0 | AK46: 0 | AL46: 1 | AM46: 0 | AN46: Baseflow | AO46: 1 | AP46: Clear | AQ46: 1 | AR46: None | AS46: 0 | AT46: 0 | AU46: 0 | AV46: 0 | AW46: 0 | AY46: 0 | AZ46: Absent | BA46: Absent | BB46: Absent | BC46: Absent | BD46: Absent | BE46: Absent | BF46: Absent | BG46: Present | BH46: Recorded | BJ46: 1 | BM46: Win Cres | BN46: Hiawatha | BO46: 070600010203 | BP46: Clear Creek-Crooked Creek | BQ46: 0706000102
A47: Dev: DBParsing_231030_v01.xlsm | B47: rHR6WWh3L29JBcOR3Juo | C47: 45532.715 | D47: 45532.465 | E47: 45532 | F47: 2024 | G47: 8 | H47: VQ9bNtzttGcXOEuaXrEAEYLfT103 | J47: -91.413099 | K47: 43.540507 | N47: 0 | P47: 1 | Q47: 40 | R47: 60 | U47: 7.5 | V47: 1 | W47: 0 | X47: 1 | Y47: 62 | Z47: 1 | AA47: 0 | AB47: 5 | AC47: River/Stream | AD47: None | AE47: 0 | AF47: 0 | AG47: 0 | AH47: 0 | AI47: 0 | AJ47: 0 | AK47: 0 | AL47: 1 | AM47: 0 | AN47: Baseflow | AO47: 1 | AP47: Clear | AQ47: 1 | AR47: None | AS47: 0 | AT47: 0 | AU47: 0 | AV47: 0 | AW47: 0 | AY47: 0 | AZ47: Absent | BA47: Absent | BB47: Absent | BC47: Absent | BD47: Absent | BE47: Absent | BF47: Absent | BG47: Present | BH47: Recorded | BI47: Winnebago Creek | BJ47: 1 | BK47: 1 | BL47: 1 | BM47: Win Cres | BN47: Hiawatha | BO47: 070600010401 | BP47: Upper Winnebago Creek | BQ47: 0706000104
A48: Dev: DBParsing_231030_v01.xlsm | B48: UAFyoy9atBmFPspCVQc2 | C48: 45532.687 | D48: 45532.437 | E48: 45532 | F48: 2024 | G48: 8 | H48: VQ9bNtzttGcXOEuaXrEAEYLfT103 | J48: -91.569713 | K48: 43.502307 | N48: 0 | P48: 1 | Q48: 0 | R48: 0 | U48: 7.5 | V48: 1 | W48: 0 | X48: 1 | Y48: 54 | Z48: 1 | AA48: 0 | AB48: 0 | AC48: River/Stream | AD48: None | AE48: 0 | AF48: 0 | AG48: 0 | AH48: 0 | AI48: 0 | AJ48: 0 | AK48: 0 | AL48: 1 | AM48: 0 | AN48: Baseflow | AO48: 1 | AP48: Clear | AQ48: 1 | AR48: None | AS48: 0 | AT48: 0 | AU48: 0 | AV48: 0 | AW48: 0 | AY48: 0 | AZ48: Absent | BA48: Absent | BB48: Absent | BC48: Absent | BD48: Absent | BE48: Absent | BF48: Absent | BG48: Present | BH48: Recorded | BI48: Bee Creek | BJ48: 1 | BK48: 1 | BL48: 1 | BM48: Win Cres | BN48: Hiawatha | BO48: 070600020502 | BP48: Waterloo Creek | BQ48: 0706000205
A49: Dev: DBParsing_231030_v01.xlsm | B49: H5YdJa99nXAY4jwhkm1o | C49: 45532.656 | D49: 45532.406 | E49: 45532 | F49: 2024 | G49: 8 | H49: VQ9bNtzttGcXOEuaXrEAEYLfT103 | J49: -91.791952 | K49: 43.67376 | N49: 0 | P49: 1 | Q49: 80 | R49: 180 | U49: 7.5 | V49: 1 | W49: 0 | X49: 1 | Y49: 62 | Z49: 1 | AA49: 0 | AB49: 0 | AC49: River/Stream | AD49: None | AE49: 0 | AF49: 0 | AG49: 0 | AH49: 0 | AI49: 0 | AJ49: 0 | AK49: 0 | AL49: 1 | AM49: 0 | AN49: Baseflow | AO49: 1 | AP49: Clear | AQ49: 1 | AR49: None | AS49: 0 | AT49: 0 | AU49: 0 | AV49: 0 | AW49: 0 | AY49: 0 | AZ49: Absent | BA49: Absent | BB49: Absent | BC49: Absent | BD49: Absent | BE49: Absent | BF49: Absent | BG49: Present | BH49: Recorded | BI49: 0 | BJ49: 1 | BK49: 1 | BL49: 1 | BM49: Win Cres | BN49: Hiawatha | BO49: 070400080803 | BP49: Middle South Fork Root River | BQ49: 0704000808
A50: Dev: DBParsing_231030_v01.xlsm | B50: r2vl8uTElWMm3a33HASt | C50: 45532.636 | D50: 45532.386 | E50: 45532 | F50: 2024 | G50: 8 | H50: VQ9bNtzttGcXOEuaXrEAEYLfT103 | J50: -91.814795 | K50: 43.59723 | N50: 0 | P50: 1 | Q50: 0 | R50: 60 | U50: 7 | V50: 1 | W50: 0 | X50: 1 | Y50: 61 | Z50: 1 | AA50: 0 | AB50: 0 | AC50: River/Stream | AD50: None | AE50: 0 | AF50: 0 | AG50: 0 | AH50: 0 | AI50: 0 | AJ50: 0 | AK50: 0 | AL50: 1 | AM50: 0 | AN50: Baseflow | AO50: 1 | AP50: Murky | AQ50: 1 | AR50: None | AS50: 0 | AT50: 0 | AU50: 0 | AV50: 0 | AW50: 0 | AY50: 0 | AZ50: Absent | BA50: Absent | BB50: Absent | BC50: Absent | BD50: Absent | BE50: Absent | BF50: Absent | BG50: Present | BH50: Recorded | BI50: Wisel Creek | BJ50: 1 | BK50: 1 | BL50: 1 | BM50: Win Cres | BN50: Hiawatha | BO50: 070400080802 | BP50: Wisel Creek | BQ50: 0704000808
A51: Dev: DBParsing_231030_v01.xlsm | B51: bf9Nh4CmQhO7hfIerdrH | C51: 45531.745 | D51: 45531.495 | E51: 45531 | F51: 2024 | G51: 8 | H51: VQ9bNtzttGcXOEuaXrEAEYLfT103 | J51: -92.293857 | K51: 43.727867 | N51: 0 | P51: 1 | Q51: 0 | R51: 60 | U51: 7 | V51: 1 | W51: 0 | X51: 1 | Y51: 68 | Z51: 1 | AA51: 0 | AB51: 5 | AC51: River/Stream | AD51: None | AE51: 0 | AF51: 0 | AG51: 0 | AH51: 0 | AI51: 0 | AJ51: 0 | AK51: 0 | AL51: 1 | AM51: 0 | AN51: Baseflow | AO51: 1 | AP51: Clear | AQ51: 1 | AR51: None | AS51: 0 | AT51: 0 | AU51: 0 | AV51: 0 | AW51: 0 | AY51: 0 | AZ51: Absent | BA51: Absent | BB51: Absent | BC51: Absent | BD51: Absent | BE51: Absent | BF51: Absent | BG51: Present | BH51: Recorded | BI51: Spring Valley Creek | BJ51: 1 | BM51: Hiawatha | BN51: Hiawatha | BO51: 070400080205 | BP51: Spring Valley Creek | BQ51: 0704000802
A52: Dev: DBParsing_231030_v01.xlsm | B52: S5JoitKqtTOslpDHr1ND | C52: 45531.719 | D52: 45531.469 | E52: 45531 | F52: 2024 | G52: 8 | H52: VQ9bNtzttGcXOEuaXrEAEYLfT103 | J52: -92.343704 | K52: 43.602309 | N52: 0 | P52: 1 | Q52: 0 | R52: 60 | U52: 7.5 | V52: 1 | W52: 0 | X52: 1 | Y52: 61 | Z52: 1 | AA52: 0 | AB52: 10 | AC52: River/Stream | AD52: None | AE52: 0 | AF52: 0 | AG52: 0 | AH52: 0 | AI52: 0 | AJ52: 0 | AK52: 0 | AL52: 1 | AM52: 0 | AN52: Baseflow | AO52: 1 | AP52: Clear | AQ52: 1 | AR52: None | AS52: 0 | AT52: 0 | AU52: 0 | AV52: 0 | AW52: 0 | AY52: 0 | AZ52: Absent | BA52: Absent | BB52: Absent | BC52: Absent | BD52: Absent | BE52: Absent | BF52: Absent | BG52: Present | BH52: Recorded | BI52: Etna Creek | BJ52: 1 | BM52: Hiawatha | BN52: Hiawatha | BO52: 070400080402 | BP52: Etna Creek-South Branch Root River | BQ52: 0704000804
A53: Dev: DBParsing_231030_v01.xlsm | B53: bdwj7y2i6XoE6rGspAd0 | C53: 45531.7 | D53: 45531.45 | E53: 45531 | F53: 2024 | G53: 8 | H53: 80reiKTTqGYqqpgYAhPwqypFwak1 | J53: -92.221224 | K53: 43.63718 | M53: 2024-08-27 11:47:19.257919.jpg-0 | N53: 1 | P53: 1 | Q53: 180 | R53: 180 | U53: 7 | V53: 0 | X53: 1 | Y53: 58 | Z53: 1 | AA53: 0 | AB53: 5 | AC53: River/Stream | AD53: None | AE53: 0 | AF53: 0 | AG53: 0 | AH53: 0 | AI53: 0 | AJ53: 0 | AK53: 0 | AL53: 1 | AM53: 0 | AN53: Baseflow | AO53: 1 | AP53: Clear | AQ53: 1 | AR53: None | AS53: 0 | AT53: 0 | AU53: 0 | AV53: 0 | AW53: 0 | AX53: Forestville looks great. | AY53: 1 | AZ53: Absent | BA53: Absent | BB53: Absent | BC53: Absent | BD53: Absent | BE53: Absent | BF53: Absent | BG53: Present | BH53: Recorded | BI53: Forestville Creek | BJ53: 1 | BM53: Hiawatha | BN53: Hiawatha | BO53: 070400080404 | BP53: Forestville Creek | BQ53: 0704000804
A54: Dev: DBParsing_231030_v01.xlsm | B54: wcw8rfDgPgr0SPvGEOGt | C54: 45531.562 | D54: 45531.312 | E54: 45531 | F54: 2024 | G54: 8 | H54: 80reiKTTqGYqqpgYAhPwqypFwak1 | J54: -92.224468 | K54: 43.622313 | M54: 2024-08-27 08:29:16.183851.jpg-0 | N54: 1 | P54: 1 | Q54: 180 | R54: 180 | U54: 7.5 | V54: 1 | W54: 0 | X54: 1 | Y54: 52 | Z54: 1 | AA54: 0 | AB54: 5 | AC54: River/Stream | AD54: None | AE54: 0 | AF54: 0 | AG54: 0 | AH54: 0 | AI54: 0 | AJ54: 0 | AK54: 0 | AL54: 1 | AM54: 0 | AN54: Baseflow | AO54: 1 | AP54: Clear | AQ54: 1 | AR54: None | AS54: 0 | AT54: 0 | AU54: 0 | AV54: 0 | AW54: 0 | AX54: Canfield looking great. debris like tree have moved in or out | AY54: 1 | AZ54: Absent | BA54: Absent | BB54: Absent | BC54: Absent | BD54: Absent | BE54: Absent | BF54: Absent | BG54: Present | BH54: Recorded | BJ54: 1 | BM54: Hiawatha | BN54: Hiawatha | BO54: 070400080405 | BP54: Town of Forestville-South Branch Root River | BQ54: 0704000804
A55: Dev: DBParsing_231030_v01.xlsm | B55: dFZbKjV6OacIxQ7LsfJW | C55: 45531.555 | D55: 45531.305 | E55: 45531 | F55: 2024 | G55: 8 | H55: 80reiKTTqGYqqpgYAhPwqypFwak1 | J55: -92.224452 | K55: 43.622702 | M55: 2024-08-27 08:19:41.048838.jpg-0 | N55: 1 | P55: 1 | Q55: 180 | R55: 180 | U55: 7.5 | V55: 1 | W55: 0 | X55: 1 | Y55: 68 | Z55: 1 | AA55: 0 | AB55: 5 | AC55: River/Stream | AD55: None | AE55: 0 | AF55: 0 | AG55: 0 | AH55: 0 | AI55: 0 | AJ55: 0 | AK55: 0 | AL55: 1 | AM55: 0 | AN55: Baseflow | AO55: 1 | AP55: Clear | AQ55: 1 | AR55: None | AS55: 0 | AT55: 0 | AU55: 0 | AV55: 0 | AW55: 0 | AX55: S Branch root looking excellent. | AY55: 1 | AZ55: Absent | BA55: Absent | BB55: Absent | BC55: Absent | BD55: Absent | BE55: Absent | BF55: Absent | BG55: Present | BH55: Recorded | BI55: Canfield Creek | BJ55: 1 | BM55: Hiawatha | BN55: Hiawatha | BO55: 070400080405 | BP55: Town of Forestville-South Branch Root River | BQ55: 0704000804
A56: Dev: DBParsing_231030_v01.xlsm | B56: 5ghSvWPlk4kMTecpv1dD | C56: 45531.52 | D56: 45531.27 | E56: 45531 | F56: 2024 | G56: 8 | H56: 80reiKTTqGYqqpgYAhPwqypFwak1 | J56: -92.270449 | K56: 43.75777 | M56: 2024-08-27 07:28:55.083212.jpg-0 | N56: 1 | P56: 1 | Q56: 180 | R56: 180 | U56: 7.5 | V56: 1 | W56: 0 | X56: 1 | Y56: 73 | Z56: 1 | AA56: 0 | AB56: 5 | AD56: None | AE56: 0 | AF56: 0 | AG56: 0 | AH56: 0 | AI56: 0 | AJ56: 0 | AK56: 0 | AL56: 1 | AM56: 0 | AN56: Mid-stage | AO56: 1 | AP56: Murky | AQ56: 1 | AR56: Local Thunderstorm | AS56: 0 | AT56: 1 | AU56: 0 | AV56: 0 | AW56: 0 | AX56: S branch Root looks good. seeing first leaves of fall on water. | AY56: 1 | AZ56: Absent | BA56: Absent | BB56: Absent | BC56: Absent | BD56: Absent | BE56: Absent | BF56: Absent | BG56: Present | BH56: Recorded | BI56: Middle Branch Root River | BM56: Hiawatha | BN56: Hiawatha | BO56: 070400080208 | BP56: Middle Branch Root River | BQ56: 0704000802
A57: Dev: DBParsing_231030_v01.xlsm | B57: jVpUIRzpUeGLDgVtoHT9 | C57: 45531.508 | D57: 45531.258 | E57: 45531 | F57: 2024 | G57: 8 | H57: 80reiKTTqGYqqpgYAhPwqypFwak1 | J57: -92.196782 | K57: 43.810569 | M57: 2024-08-27 07:11:08.646937.jpg-0 | N57: 1 | P57: 0 | V57: 1 | W57: 0 | X57: 1 | Y57: 58 | Z57: 1 | AA57: 0 | AB57: 5 | AC57: River/Stream | AD57: None | AE57: 0 | AF57: 0 | AG57: 0 | AH57: 0 | AI57: 0 | AJ57: 0 | AK57: 0 | AL57: 1 | AM57: 0 | AN57: Baseflow | AO57: 1 | AP57: Murky | AQ57: 1 | AR57: Local Thunderstorm | AS57: 0 | AT57: 1 | AU57: 0 | AV57: 0 | AW57: 0 | AX57: lost looks great. but seems a bit murky but it’s sunrise. | AY57: 1 | AZ57: Absent | BA57: Absent | BB57: Absent | BC57: Absent | BD57: Absent | BE57: Absent | BF57: Absent | BG57: Present | BH57: Recorded | BI57: Bear Creek | BJ57: 1 | BM57: Hiawatha | BN57: Hiawatha | BO57: 070400080207 | BP57: Bear Creek | BQ57: 0704000802
A58: Dev: DBParsing_231030_v01.xlsm | B58: EU4CEjM8lZfHSjit4swi | C58: 45531.502 | D58: 45531.252 | E58: 45531 | F58: 2024 | G58: 8 | H58: 80reiKTTqGYqqpgYAhPwqypFwak1 | J58: -92.196139 | K58: 43.811008 | M58: 2024-08-27 07:02:29.002843.jpg-0 | N58: 1 | P58: 1 | Q58: 180 | R58: 180 | U58: 8 | V58: 1 | W58: 0 | X58: 1 | Y58: 72 | Z58: 1 | AA58: 0 | AB58: 5 | AC58: River/Stream | AD58: None | AE58: 0 | AF58: 0 | AG58: 0 | AH58: 0 | AI58: 0 | AJ58: 0 | AK58: 0 | AL58: 1 | AM58: 0 | AN58: Mid-stage | AO58: 1 | AP58: Murky | AQ58: 1 | AR58: Local Thunderstorm | AS58: 0 | AT58: 1 | AU58: 0 | AV58: 0 | AW58: 0 | AX58: first time with North Beanch Root. good smallie stream I’m told | AY58: 1 | AZ58: Absent | BA58: Absent | BB58: Absent | BC58: Absent | BD58: Absent | BE58: Absent | BF58: Absent | BG58: Present | BH58: Recorded | BI58: Bear Creek | BJ58: 1 | BM58: Hiawatha | BN58: Hiawatha | BO58: 070400080207 | BP58: Bear Creek | BQ58: 0704000802
A59: Dev: DBParsing_231030_v01.xlsm | B59: EbF1ez7l8ygu5RU5Eenc | C59: 45530.709 | D59: 45530.459 | E59: 45530 | F59: 2024 | G59: 8 | H59: f7qMRlnlkOgrA1xpaxXrTTeRGWX2 | J59: -92.732258 | K59: 44.831063 | N59: 0 | P59: 1 | Q59: 180 | R59: 180 | U59: 8 | V59: 1 | W59: 0 | X59: 1 | Y59: 64 | Z59: 1 | AA59: 0 | AB59: 5 | AC59: River/Stream | AD59: Bank Erosion | AE59: 0 | AF59: 1 | AG59: 0 | AH59: 0 | AI59: 0 | AJ59: 0 | AK59: 0 | AL59: 0 | AM59: 0 | AN59: Baseflow | AO59: 1 | AP59: Clear | AQ59: 1 | AR59: None | AS59: 0 | AT59: 0 | AU59: 0 | AV59: 0 | AW59: 0 | AX59: Secchi Tube > 100 cm | AY59: 1 | AZ59: Absent | BA59: Present | BB59: Absent | BC59: Absent | BD59: Absent | BE59: Absent | BF59: Absent | BG59: Absent | BH59: Recorded | BI59: Kinnickinnic River | BJ59: 1 | BM59: Kiap-TU-Wish | BN59: Kiap-TU-Wish | BO59: 070300051105 | BP59: Lower Kinnickinnic Pond-Kinnickinnic River | BQ59: 0703000511
A60: Dev: DBParsing_231030_v01.xlsm | B60: FDlidRtlN5lXofVBZ9d6 | C60: 45530.673 | D60: 45530.423 | E60: 45530 | F60: 2024 | G60: 8 | H60: 80reiKTTqGYqqpgYAhPwqypFwak1 | J60: -92.650194 | K60: 44.075204 | N60: 0 | P60: 0 | V60: 0 | X60: 1 | Y60: 69 | Z60: 1 | AA60: 0 | AB60: 5 | AC60: River/Stream | AD60: None | AE60: 0 | AF60: 0 | AG60: 0 | AH60: 0 | AI60: 0 | AJ60: 0 | AK60: 0 | AL60: 1 | AM60: 0 | AN60: Mid-stage | AO60: 1 | AP60: Murky | AQ60: 1 | AR60: None | AS60: 0 | AT60: 0 | AU60: 0 | AV60: 0 | AW60: 0 | AY60: 0 | AZ60: Absent | BA60: Absent | BB60: Absent | BC60: Absent | BD60: Absent | BE60: Absent | BF60: Absent | BG60: Present | BH60: Recorded | BI60: South Branch Middle Fork Zumbro River | BM60: Hiawatha | BN60: Hiawatha | BO60: 070400040205 | BP60: South Branch Middle Fork Zumbro River | BQ60: 0704000402
A61: Dev: DBParsing_231030_v01.xlsm | B61: 0YTrZVSGjDXRi0emIwk6 | C61: 45528.981 | D61: 45528.731 | E61: 45528 | F61: 2024 | G61: 8 | H61: H4dZvxTdViejefqREn5k066JVZG3 | J61: -92.236309 | K61: 44.23063 | M61: 2024-08-24 18:32:01.129157.jpg-0 | N61: 1 | P61: 1 | Q61: 180 | R61: 180 | U61: 8 | V61: 1 | W61: 100 | X61: 1 | Y61: 62 | Z61: 1 | AA61: 0 | AB61: 2 | AC61: River/Stream | AD61: None | AE61: 0 | AF61: 0 | AG61: 0 | AH61: 0 | AI61: 0 | AJ61: 0 | AK61: 0 | AL61: 1 | AM61: 0 | AN61: Baseflow | AO61: 1 | AP61: Clear | AQ61: 1 | AR61: None | AS61: 0 | AT61: 0 | AU61: 0 | AV61: 0 | AW61: 0 | AX61: long creek downstream from cnty 8 bridge | AY61: 1 | AZ61: Absent | BA61: Absent | BB61: Absent | BC61: Absent | BD61: Absent | BE61: Absent | BF61: Absent | BG61: Present | BH61: Recorded | BI61: Long Creek | BJ61: 1 | BK61: 1 | BL61: 1 | BM61: Hiawatha | BN61: Hiawatha | BO61: 070400040505 | BP61: Long Creek | BQ61: 0704000405
A62: Dev: DBParsing_231030_v01.xlsm | B62: AcHJPq1BtT3bxDSwAxxu | C62: 45528.953 | D62: 45528.703 | E62: 45528 | F62: 2024 | G62: 8 | H62: H4dZvxTdViejefqREn5k066JVZG3 | J62: -92.149249 | K62: 44.24881 | M62: 2024-08-24 17:51:37.948445.jpg-0 | N62: 1 | P62: 1 | Q62: 0 | R62: 30 | U62: 7 | V62: 1 | W62: 100 | X62: 1 | Y62: 63 | Z62: 1 | AA62: 0 | AB62: 5 | AC62: River/Stream | AD62: None | AE62: 0 | AF62: 0 | AG62: 0 | AH62: 0 | AI62: 0 | AJ62: 0 | AK62: 0 | AL62: 1 | AM62: 0 | AN62: Baseflow | AO62: 1 | AP62: Clear | AQ62: 1 | AR62: None | AS62: 0 | AT62: 0 | AU62: 0 | AV62: 0 | AW62: 0 | AX62: West Indian near parking lot | AY62: 1 | AZ62: Absent | BA62: Absent | BB62: Absent | BC62: Absent | BD62: Absent | BE62: Absent | BF62: Absent | BG62: Present | BH62: Recorded | BI62: West Indian Creek | BJ62: 1 | BK62: 1 | BL62: 1 | BM62: Hiawatha | BN62: Hiawatha | BO62: 070400040510 | BP62: West Indian Creek | BQ62: 0704000405
A63: Dev: DBParsing_231030_v01.xlsm | B63: jCIjIROVhOkQzK2nkd8l | C63: 45527.92 | D63: 45527.67 | E63: 45527 | F63: 2024 | G63: 8 | H63: M7nEAKQN9zgYz7BtxGWTXq0oso12 | I63: Kinnickinnic River, Lower Glen Park | J63: -92.644986 | K63: 44.84355 | M63: 2024-08-23 17:04:17.032208.jpg-0 | N63: 1 | P63: 1 | Q63: 180 | R63: 180 | U63: 8 | V63: 1 | W63: 0 | X63: 1 | Y63: 61 | Z63: 1 | AA63: 0 | AB63: 5 | AC63: River/Stream | AD63: None | AE63: 0 | AF63: 0 | AG63: 0 | AH63: 0 | AI63: 0 | AJ63: 0 | AK63: 0 | AL63: 1 | AM63: 0 | AN63: Baseflow | AO63: 1 | AP63: Clear | AQ63: 1 | AR63: None | AS63: 0 | AT63: 0 | AU63: 0 | AV63: 0 | AW63: 0 | AX63: ptly cloudy, 80 degrees, calm | AY63: 1 | AZ63: Absent | BA63: Absent | BB63: Absent | BC63: Absent | BD63: Absent | BE63: Absent | BF63: Absent | BG63: Present | BH63: Recorded | BI63: Kinnickinnic River | BJ63: 1 | BM63: Kiap-TU-Wish | BN63: Kiap-TU-Wish | BO63: 070300051105 | BP63: Lower Kinnickinnic Pond-Kinnickinnic River | BQ63: 0703000511
A64: Dev: DBParsing_231030_v01.xlsm | B64: n6wlxK9eF21CdfXA8jbl | C64: 45524.677 | D64: 45524.427 | E64: 45524 | F64: 2024 | G64: 8 | H64: f7qMRlnlkOgrA1xpaxXrTTeRGWX2 | J64: -92.732156 | K64: 44.831131 | N64: 0 | P64: 1 | Q64: 180 | R64: 180 | U64: 8 | V64: 1 | W64: 0 | X64: 1 | Y64: 60 | Z64: 1 | AA64: 0 | AB64: 5 | AC64: River/Stream | AD64: Bank Erosion | AE64: 0 | AF64: 1 | AG64: 0 | AH64: 0 | AI64: 0 | AJ64: 0 | AK64: 0 | AL64: 0 | AM64: 0 | AN64: Baseflow | AO64: 1 | AP64: Clear | AQ64: 1 | AR64: None | AS64: 0 | AT64: 0 | AU64: 0 | AV64: 0 | AW64: 0 | AX64: Secchi Tube > 100 cm | AY64: 1 | AZ64: Absent | BA64: Present | BB64: Absent | BC64: Absent | BD64: Absent | BE64: Absent | BF64: Absent | BG64: Absent | BH64: Recorded | BI64: Kinnickinnic River | BJ64: 1 | BM64: Kiap-TU-Wish | BN64: Kiap-TU-Wish | BO64: 070300051105 | BP64: Lower Kinnickinnic Pond-Kinnickinnic River | BQ64: 0703000511
A65: Dev: DBParsing_231030_v01.xlsm | B65: vlNJeJgRLTM76WNqjFZy | C65: 45523.7 | D65: 45523.45 | E65: 45523 | F65: 2024 | G65: 8 | H65: 7a7IFD1YT3aDXB8CbnSJjn1oLRC2 | I65: Isabelle Creek @ County Rd. EE | J65: -92.442865 | K65: 44.621436 | N65: 0 | P65: 1 | Q65: 120 | R65: 180 | U65: 8 | V65: 1 | W65: 0 | X65: 1 | Y65: 57 | Z65: 1 | AA65: 0 | AB65: 5 | AC65: River/Stream | AD65: None | AE65: 0 | AF65: 0 | AG65: 0 | AH65: 0 | AI65: 0 | AJ65: 0 | AK65: 0 | AL65: 1 | AM65: 0 | AN65: Baseflow | AO65: 1 | AP65: Clear | AQ65: 1 | AR65: None | AS65: 0 | AT65: 0 | AU65: 0 | AV65: 0 | AW65: 0 | AY65: 0 | AZ65: Absent | BA65: Absent | BB65: Absent | BC65: Absent | BD65: Absent | BE65: Absent | BF65: Absent | BG65: Present | BH65: Recorded | BI65: Isabelle Creek | BJ65: 1 | BM65: Kiap-TU-Wish | BN65: Unknown | BO65: 070400010701 | BP65: Isabelle Creek | BQ65: 0704000107
A66: Dev: DBParsing_231030_v01.xlsm | B66: VEbzd4guAUXLIn67Zy4V | C66: 45523.679 | D66: 45523.429 | E66: 45523 | F66: 2024 | G66: 8 | H66: 80reiKTTqGYqqpgYAhPwqypFwak1 | J66: -92.649727 | K66: 44.075212 | N66: 0 | P66: 0 | V66: 0 | X66: 1 | Y66: 62 | Z66: 1 | AA66: 0 | AB66: 5 | AC66: River/Stream | AE66: -1 | AF66: -1 | AG66: -1 | AH66: -1 | AI66: -1 | AJ66: -1 | AK66: -1 | AL66: -1 | AM66: 1 | AN66: Mid-stage | AO66: 1 | AP66: Murky | AQ66: 1 | AR66: None | AS66: 0 | AT66: 0 | AU66: 0 | AV66: 0 | AW66: 0 | AX66: Zumbro still dirty. | AY66: 1 | AZ66: No Data | BA66: No Data | BB66: No Data | BC66: No Data | BD66: No Data | BE66: No Data | BF66: No Data | BG66: No Data | BH66: No Data | BI66: South Branch Middle Fork Zumbro River | BM66: Hiawatha | BN66: Hiawatha | BO66: 070400040205 | BP66: South Branch Middle Fork Zumbro River | BQ66: 0704000402
A67: Dev: DBParsing_231030_v01.xlsm | B67: DnJbyixxj62Iecmn2EAz | C67: 45516.846 | D67: 45516.596 | E67: 45516 | F67: 2024 | G67: 8 | H67: 80reiKTTqGYqqpgYAhPwqypFwak1 | J67: -92.649891 | K67: 44.075197 | N67: 0 | P67: 0 | V67: 0 | X67: 1 | Y67: 66 | Z67: 1 | AA67: 0 | AB67: 10 | AC67: River/Stream | AD67: None | AE67: 0 | AF67: 0 | AG67: 0 | AH67: 0 | AI67: 0 | AJ67: 0 | AK67: 0 | AL67: 1 | AM67: 0 | AN67: Mid-stage | AO67: 1 | AP67: Murky | AQ67: 1 | AR67: None | AS67: 0 | AT67: 0 | AU67: 0 | AV67: 0 | AW67: 0 | AX67: Zumbro looking much better. | AY67: 1 | AZ67: Absent | BA67: Absent | BB67: Absent | BC67: Absent | BD67: Absent | BE67: Absent | BF67: Absent | BG67: Present | BH67: Recorded | BI67: South Branch Middle Fork Zumbro River | BM67: Hiawatha | BN67: Hiawatha | BO67: 070400040205 | BP67: South Branch Middle Fork Zumbro River | BQ67: 0704000402
A68: Dev: DBParsing_231030_v01.xlsm | B68: CnYS9LzsHD60gsEr8WwB | C68: 45516.793 | D68: 45516.543 | E68: 45516 | F68: 2024 | G68: 8 | H68: DKq8OLTYViaAQZeR9ADiCfs22M63 | J68: -90.280878 | K68: 43.076654 | M68: 2024-08-12 14:01:55.394091.jpg-0 | N68: 1 | P68: 1 | Q68: 180 | R68: 180 | U68: 8 | V68: 1 | W68: 0 | X68: 1 | Y68: 63 | Z68: 1 | AA68: 0 | AB68: 2 | AC68: River/Stream | AD68: None | AE68: 0 | AF68: 0 | AG68: 0 | AH68: 0 | AI68: 0 | AJ68: 0 | AK68: 0 | AL68: 1 | AM68: 0 | AN68: Baseflow | AO68: 1 | AP68: Murky | AQ68: 1 | AR68: None | AS68: 0 | AT68: 0 | AU68: 0 | AV68: 0 | AW68: 0 | AY68: 0 | AZ68: Absent | BA68: Absent | BB68: Absent | BC68: Absent | BD68: Absent | BE68: Absent | BF68: Absent | BG68: Present | BH68: Recorded | BI68: Smoky Hollow Creek | BJ68: 1 | BM68: Harry & Laura Nohr | BN68: TU Staff | BO68: 070700050803 | BP68: Pillar Creek | BQ68: 0707000508
A69: Dev: DBParsing_231030_v01.xlsm | B69: nExVAbp8dhM0dLuYtw74 | C69: 45515.808 | D69: 45515.558 | E69: 45515 | F69: 2024 | G69: 8 | H69: DKq8OLTYViaAQZeR9ADiCfs22M63 | J69: -91.542775 | K69: 44.553072 | M69: 2024-08-11 14:23:00.751397.jpg-0 | N69: 1 | P69: 1 | Q69: 80 | R69: 120 | U69: 7 | V69: 1 | W69: 300 | X69: 1 | Y69: 59 | Z69: 1 | AA69: 0 | AB69: 2 | AC69: River/Stream | AD69: None | AE69: 0 | AF69: 0 | AG69: 0 | AH69: 0 | AI69: 0 | AJ69: 0 | AK69: 0 | AL69: 1 | AM69: 0 | AN69: Baseflow | AO69: 1 | AP69: Murky | AQ69: 1 | AR69: None | AS69: 0 | AT69: 0 | AU69: 0 | AV69: 0 | AW69: 0 | AX69: air high temps near 70 last few days | AY69: 1 | AZ69: Absent | BA69: Absent | BB69: Absent | BC69: Absent | BD69: Absent | BE69: Absent | BF69: Absent | BG69: Present | BH69: Recorded | BI69: Rossman Creek | BJ69: 1 | BK69: 1 | BL69: 1 | BM69: Wisconsin Clear Water | BN69: TU Staff | BO69: 070400030108 | BP69: Rossman Creek-Buffalo River | BQ69: 0704000301
A70: Dev: DBParsing_231030_v01.xlsm | B70: eBk3HGWpSJtiNPeL7vBn | C70: 45515.791 | D70: 45515.541 | E70: 45515 | F70: 2024 | G70: 8 | H70: k4Pe0JRs4tfWvDzxrT35e1UE1ce2 | J70: -92.80196 | K70: 44.543098 | N70: 0 | P70: 0 | V70: 0 | X70: 0 | Z70: 0 | AE70: -1 | AF70: -1 | AG70: -1 | AH70: -1 | AI70: -1 | AJ70: -1 | AK70: -1 | AL70: -1 | AM70: 1 | AO70: 0 | AQ70: 0 | AS70: -1 | AT70: -1 | AU70: -1 | AV70: -1 | AW70: 1 | AY70: 0 | AZ70: No Data | BA70: No Data | BB70: No Data | BC70: No Data | BD70: No Data | BE70: No Data | BF70: No Data | BG70: No Data | BH70: No Data | BI70: Cannon River | BJ70: 1 | BK70: 1 | BL70: 1 | BM70: Twin Cities (TCTU) | BN70: TCTU | BO70: 070400020902 | BP70: Trout Brook | BQ70: 0704000209
A71: Dev: DBParsing_231030_v01.xlsm | B71: VzpQia1L7BD3KZ2tQv47 | C71: 45514.938 | D71: 45514.688 | E71: 45514 | F71: 2024 | G71: 8 | H71: DKq8OLTYViaAQZeR9ADiCfs22M63 | J71: -91.890561 | K71: 44.617768 | M71: 2024-08-10 17:30:06.898443.jpg-0 | N71: 1 | P71: 1 | Q71: 120 | R71: 60 | U71: 7.5 | V71: 1 | W71: 100 | X71: 1 | Y71: 61 | Z71: 1 | AA71: 0 | AB71: 2 | AC71: River/Stream | AD71: None | AE71: 0 | AF71: 0 | AG71: 0 | AH71: 0 | AI71: 0 | AJ71: 0 | AK71: 0 | AL71: 1 | AM71: 0 | AN71: Baseflow | AO71: 1 | AP71: Murky | AQ71: 1 | AR71: None | AS71: 0 | AT71: 0 | AU71: 0 | AV71: 0 | AW71: 0 | AX71: air temp highs of low 70s last few days | AY71: 1 | AZ71: Absent | BA71: Absent | BB71: Absent | BC71: Absent | BD71: Absent | BE71: Absent | BF71: Absent | BG71: Present | BH71: Recorded | BI71: Bear Creek | BJ71: 1 | BK71: 1 | BL71: 1 | BM71: Wisconsin Clear Water | BN71: TU Staff | BO71: 070500051201 | BP71: Bear Creek | BQ71: 0705000512
A72: Dev: DBParsing_231030_v01.xlsm | B72: KE0MiWSch7L27GXpZEFb | C72: 45514.869 | D72: 45514.619 | E72: 45514 | F72: 2024 | G72: 8 | H72: DKq8OLTYViaAQZeR9ADiCfs22M63 | J72: -91.972053 | K72: 44.570981 | M72: 2024-08-10 15:51:35.534915.jpg-0 | N72: 1 | P72: 1 | Q72: 120 | R72: 120 | U72: 7 | V72: 1 | W72: 100 | X72: 1 | Y72: 58 | Z72: 1 | AA72: 0 | AB72: 2 | AC72: River/Stream | AD72: Fish Barrier | AE72: 1 | AF72: 0 | AG72: 0 | AH72: 0 | AI72: 0 | AJ72: 0 | AK72: 0 | AL72: 0 | AM72: 0 | AN72: Baseflow | AO72: 1 | AP72: Clear | AQ72: 1 | AR72: None | AS72: 0 | AT72: 0 | AU72: 0 | AV72: 0 | AW72: 0 | AX72: air temp highs in lower 70s last few days | AY72: 1 | AZ72: Present | BA72: Absent | BB72: Absent | BC72: Absent | BD72: Absent | BE72: Absent | BF72: Absent | BG72: Absent | BH72: Recorded | BI72: Spring Creek | BJ72: 1 | BK72: 1 | BL72: 1 | BM72: Wisconsin Clear Water | BN72: TU Staff | BO72: 070500051203 | BP72: Spring Creek-Chippewa River | BQ72: 0705000512
A73: Dev: DBParsing_231030_v01.xlsm | B73: e9HFbzSzwEmdSlLoFewq | C73: 45513.724 | D73: 45513.474 | E73: 45513 | F73: 2024 | G73: 8 | H73: DKq8OLTYViaAQZeR9ADiCfs22M63 | J73: -91.030597 | K73: 44.381415 | M73: 2024-08-09 12:23:06.223997.jpg-0 | N73: 1 | P73: 1 | Q73: 40 | R73: 60 | U73: 6.5 | V73: 1 | W73: 200 | X73: 1 | Y73: 58 | Z73: 1 | AA73: 0 | AB73: 0 | AC73: River/Stream | AD73: None | AE73: 0 | AF73: 0 | AG73: 0 | AH73: 0 | AI73: 0 | AJ73: 0 | AK73: 0 | AL73: 1 | AM73: 0 | AN73: Baseflow | AO73: 1 | AP73: Murky | AQ73: 1 | AR73: None | AS73: 0 | AT73: 0 | AU73: 0 | AV73: 0 | AW73: 0 | AX73: low 70s for high air temps last few days | AY73: 1 | AZ73: Absent | BA73: Absent | BB73: Absent | BC73: Absent | BD73: Absent | BE73: Absent | BF73: Absent | BG73: Present | BH73: Recorded | BI73: Holmes Creek | BJ73: 1 | BK73: 1 | BL73: 1 | BM73: Wisconsin Clear Water | BN73: TU Staff | BO73: 070400050203 | BP73: Tank Creek-Trempealeau River | BQ73: 0704000502
A74: Dev: DBParsing_231030_v01.xlsm | B74: ttqxJV793noJjbLznfjN | C74: 45513.668 | D74: 45513.418 | E74: 45513 | F74: 2024 | G74: 8 | H74: K0EjhOrGL4NGhPVbB1pKi320lLr2 | I74: Hay Creek, 325th St | J74: -92.59708 | K74: 44.472635 | M74: 2024-08-09 11:02:08.342220.jpg-0 | N74: 1 | P74: 1 | Q74: 0 | R74: 60 | U74: 7 | V74: 1 | W74: 100 | X74: 1 | Y74: 13 | Z74: 1 | AA74: 0 | AB74: 2 | AC74: River/Stream | AD74: None | AE74: 0 | AF74: 0 | AG74: 0 | AH74: 0 | AI74: 0 | AJ74: 0 | AK74: 0 | AL74: 1 | AM74: 0 | AN74: Baseflow | AO74: 1 | AP74: Clear | AQ74: 1 | AR74: None | AS74: 0 | AT74: 0 | AU74: 0 | AV74: 0 | AW74: 0 | AY74: 0 | AZ74: Absent | BA74: Absent | BB74: Absent | BC74: Absent | BD74: Absent | BE74: Absent | BF74: Absent | BG74: Present | BH74: Recorded | BI74: Hay Creek | BJ74: 1 | BM74: Twin Cities (TCTU) | BN74: TCTU | BO74: 070400010401 | BP74: Hay Creek | BQ74: 0704000104
A75: Dev: DBParsing_231030_v01.xlsm | B75: IJmdq5qeiZbHCSeRL7E3 | C75: 45513.635 | D75: 45513.385 | E75: 45513 | F75: 2024 | G75: 8 | H75: DKq8OLTYViaAQZeR9ADiCfs22M63 | J75: -90.991381 | K75: 44.397237 | M75: 2024-08-09 10:14:37.722215.jpg-0 | N75: 1 | P75: 1 | Q75: 80 | R75: 0 | U75: 7.5 | V75: 1 | W75: 100 | X75: 1 | Y75: 58 | Z75: 1 | AA75: 0 | AB75: 2 | AC75: River/Stream | AD75: None | AE75: 0 | AF75: 0 | AG75: 0 | AH75: 0 | AI75: 0 | AJ75: 0 | AK75: 0 | AL75: 1 | AM75: 0 | AN75: Baseflow | AO75: 1 | AP75: Murky | AQ75: 1 | AR75: None | AS75: 0 | AT75: 0 | AU75: 0 | AV75: 0 | AW75: 0 | AX75: low 70s for air temp highs last few days | AY75: 1 | AZ75: Absent | BA75: Absent | BB75: Absent | BC75: Absent | BD75: Absent | BE75: Absent | BF75: Absent | BG75: Present | BH75: Recorded | BI75: North Branch Trempealeau River | BJ75: 1 | BK75: 1 | BL75: 1 | BM75: Wisconsin Clear Water | BN75: TU Staff | BO75: 070400050202 | BP75: South Branch of the Trempealeau River | BQ75: 0704000502
A76: Dev: DBParsing_231030_v01.xlsm | B76: 64LhLk8vUsoyQHD6Mjfi | C76: 45513.617 | D76: 45513.367 | E76: 45513 | F76: 2024 | G76: 8 | H76: K0EjhOrGL4NGhPVbB1pKi320lLr2 | I76: Hay Creek, 320th St | J76: -92.575187 | K76: 44.488507 | M76: 2024-08-09 09:49:10.259664.jpg-0 | N76: 1 | P76: 1 | Q76: 40 | R76: 0 | U76: 8 | V76: 1 | W76: 100 | X76: 1 | Y76: 13 | Z76: 1 | AA76: 0 | AB76: 0 | AC76: River/Stream | AD76: None | AE76: 0 | AF76: 0 | AG76: 0 | AH76: 0 | AI76: 0 | AJ76: 0 | AK76: 0 | AL76: 1 | AM76: 0 | AN76: Baseflow | AO76: 1 | AP76: Murky | AQ76: 1 | AR76: None | AS76: 0 | AT76: 0 | AU76: 0 | AV76: 0 | AW76: 0 | AY76: 0 | AZ76: Absent | BA76: Absent | BB76: Absent | BC76: Absent | BD76: Absent | BE76: Absent | BF76: Absent | BG76: Present | BH76: Recorded | BI76: Hay Creek | BJ76: 1 | BM76: Twin Cities (TCTU) | BN76: TCTU | BO76: 070400010401 | BP76: Hay Creek | BQ76: 0704000104
A77: Dev: DBParsing_231030_v01.xlsm | B77: TCKoNAXkRA2eyvPW9X9m | C77: 45513.578 | D77: 45513.328 | E77: 45513 | F77: 2024 | G77: 8 | H77: K0EjhOrGL4NGhPVbB1pKi320lLr2 | J77: -92.5637 | K77: 44.502533 | M77: 2024-08-09 08:52:08.695372.jpg-0 | N77: 1 | P77: 1 | Q77: 80 | R77: 0 | U77: 7 | V77: 1 | W77: 100 | X77: 1 | Y77: 14 | Z77: 1 | AA77: 0 | AB77: 2 | AC77: River/Stream | AD77: None | AE77: 0 | AF77: 0 | AG77: 0 | AH77: 0 | AI77: 0 | AJ77: 0 | AK77: 0 | AL77: 1 | AM77: 0 | AN77: Baseflow | AO77: 1 | AQ77: 0 | AR77: None | AS77: 0 | AT77: 0 | AU77: 0 | AV77: 0 | AW77: 0 | AY77: 0 | AZ77: Absent | BA77: Absent | BB77: Absent | BC77: Absent | BD77: Absent | BE77: Absent | BF77: Absent | BG77: Present | BH77: Recorded | BI77: Hay Creek | BJ77: 1 | BM77: Twin Cities (TCTU) | BN77: TCTU | BO77: 070400010401 | BP77: Hay Creek | BQ77: 0704000104
A78: Dev: DBParsing_231030_v01.xlsm | B78: JhiMgkmHBH5XeU1LYA0E | C78: 45512.859 | D78: 45512.609 | E78: 45512 | F78: 2024 | G78: 8 | H78: DKq8OLTYViaAQZeR9ADiCfs22M63 | J78: -90.854589 | K78: 44.459752 | M78: 2024-08-08 15:36:43.736315.jpg-0 | N78: 1 | P78: 1 | Q78: 40 | R78: 30 | U78: 6 | V78: 1 | W78: 100 | X78: 1 | Y78: 64 | Z78: 1 | AA78: 0 | AB78: 0 | AC78: River/Stream | AD78: None | AE78: 0 | AF78: 0 | AG78: 0 | AH78: 0 | AI78: 0 | AJ78: 0 | AK78: 0 | AL78: 1 | AM78: 0 | AN78: Baseflow | AO78: 1 | AP78: Clear | AQ78: 1 | AR78: Local Thunderstorm | AS78: 0 | AT78: 1 | AU78: 0 | AV78: 0 | AW78: 0 | AY78: 0 | AZ78: Absent | BA78: Absent | BB78: Absent | BC78: Absent | BD78: Absent | BE78: Absent | BF78: Absent | BG78: Present | BH78: Recorded | BI78: Halls Creek | BJ78: 1 | BK78: 1 | BL78: 1 | BM78: Wisconsin Clear Water | BN78: TU Staff | BO78: 070400070802 | BP78: South Fork of Halls Creek-Halls Creek | BQ78: 0704000708
A79: Dev: DBParsing_231030_v01.xlsm | B79: eFiD1NWWy1QoNCXsctpG | C79: 45510.792 | D79: 45510.542 | E79: 45510 | F79: 2024 | G79: 8 | H79: 80reiKTTqGYqqpgYAhPwqypFwak1 | J79: -92.645258 | K79: 44.069314 | N79: 0 | P79: 0 | V79: 0 | X79: 1 | Y79: 63 | Z79: 1 | AA79: 0 | AB79: 10 | AC79: River/Stream | AE79: -1 | AF79: -1 | AG79: -1 | AH79: -1 | AI79: -1 | AJ79: -1 | AK79: -1 | AL79: -1 | AM79: 1 | AN79: Bankfull Stage | AO79: 1 | AP79: Muddy | AQ79: 1 | AR79: None | AS79: 0 | AT79: 0 | AU79: 0 | AV79: 0 | AW79: 0 | AX79: River very dirty. gullywasher overnight. | AY79: 1 | AZ79: No Data | BA79: No Data | BB79: No Data | BC79: No Data | BD79: No Data | BE79: No Data | BF79: No Data | BG79: No Data | BH79: No Data | BI79: South Branch Middle Fork Zumbro River | BM79: Hiawatha | BN79: Hiawatha | BO79: 070400040205 | BP79: South Branch Middle Fork Zumbro River | BQ79: 0704000402
A80: Dev: DBParsing_231030_v01.xlsm | B80: Cb54BjNDqKLdawUIASXO | C80: 45507.58 | D80: 45507.33 | E80: 45507 | F80: 2024 | G80: 8 | H80: 80reiKTTqGYqqpgYAhPwqypFwak1 | J80: -92.221248 | K80: 43.637165 | M80: 2024-08-03 08:54:32.960378.jpg-0 | N80: 1 | P80: 1 | Q80: 180 | R80: 180 | U80: 8 | V80: 1 | W80: 0 | X80: 1 | Y80: 55 | Z80: 1 | AA80: 0 | AB80: 5 | AC80: River/Stream | AD80: None | AE80: 0 | AF80: 0 | AG80: 0 | AH80: 0 | AI80: 0 | AJ80: 0 | AK80: 0 | AL80: 1 | AM80: 0 | AN80: Mid-stage | AO80: 1 | AP80: Clear | AQ80: 1 | AR80: None | AS80: 0 | AT80: 0 | AU80: 0 | AV80: 0 | AW80: 0 | AX80: Forestville looks excellent. | AY80: 1 | AZ80: Absent | BA80: Absent | BB80: Absent | BC80: Absent | BD80: Absent | BE80: Absent | BF80: Absent | BG80: Present | BH80: Recorded | BI80: Forestville Creek | BJ80: 1 | BM80: Hiawatha | BN80: Hiawatha | BO80: 070400080404 | BP80: Forestville Creek | BQ80: 0704000804
A81: Dev: DBParsing_231030_v01.xlsm | B81: ZB54hwI0NK2df6gQQUvh | C81: 45507.56 | D81: 45507.31 | E81: 45507 | F81: 2024 | G81: 8 | H81: 80reiKTTqGYqqpgYAhPwqypFwak1 | J81: -92.22442 | K81: 43.622694 | M81: 2024-08-03 08:26:59.088326.jpg-0 | N81: 1 | P81: 1 | Q81: 180 | R81: 180 | U81: 7 | V81: 1 | W81: 0 | X81: 1 | Y81: 65 | Z81: 1 | AA81: 0 | AB81: 5 | AC81: River/Stream | AD81: None | AE81: 0 | AF81: 0 | AG81: 0 | AH81: 0 | AI81: 0 | AJ81: 0 | AK81: 0 | AL81: 1 | AM81: 0 | AN81: Baseflow | AO81: 1 | AP81: Clear | AQ81: 1 | AR81: None | AS81: 0 | AT81: 0 | AU81: 0 | AV81: 0 | AW81: 0 | AX81: SB Root looks perfect. some rises below where I sample. | AY81: 1 | AZ81: Absent | BA81: Absent | BB81: Absent | BC81: Absent | BD81: Absent | BE81: Absent | BF81: Absent | BG81: Present | BH81: Recorded | BJ81: 1 | BM81: Hiawatha | BN81: Hiawatha | BO81: 070400080405 | BP81: Town of Forestville-South Branch Root River | BQ81: 0704000804
A82: Dev: DBParsing_231030_v01.xlsm | B82: LUEScz0pDLxQyn6czHMw | C82: 45507.546 | D82: 45507.296 | E82: 45507 | F82: 2024 | G82: 8 | H82: 80reiKTTqGYqqpgYAhPwqypFwak1 | J82: -92.224484 | K82: 43.622246 | M82: 2024-08-03 08:06:17.314779.jpg-0 | N82: 1 | P82: 1 | Q82: 180 | R82: 180 | U82: 7 | V82: 1 | W82: 0 | X82: 1 | Y82: 50 | Z82: 1 | AA82: 0 | AB82: 10 | AC82: River/Stream | AD82: None | AE82: 0 | AF82: 0 | AG82: 0 | AH82: 0 | AI82: 0 | AJ82: 0 | AK82: 0 | AL82: 1 | AM82: 0 | AN82: Mid-stage | AO82: 1 | AP82: Clear | AQ82: 1 | AR82: None | AS82: 0 | AT82: 0 | AU82: 0 | AV82: 0 | AW82: 0 | AX82: Canfield looks great but flood changed it a lot where I sample | AY82: 1 | AZ82: Absent | BA82: Absent | BB82: Absent | BC82: Absent | BD82: Absent | BE82: Absent | BF82: Absent | BG82: Present | BH82: Recorded | BI82: Canfield Creek | BJ82: 1 | BM82: Hiawatha | BN82: Hiawatha | BO82: 070400080405 | BP82: Town of Forestville-South Branch Root River | BQ82: 0704000804
A83: Dev: DBParsing_231030_v01.xlsm | B83: p8JHLsCsWjyqiJ8NUAzh | C83: 45507.51 | D83: 45507.26 | E83: 45507 | F83: 2024 | G83: 8 | H83: 80reiKTTqGYqqpgYAhPwqypFwak1 | J83: -92.270444 | K83: 43.757773 | M83: 2024-08-03 07:13:44.649431.jpg-0 | N83: 1 | P83: 1 | Q83: 180 | R83: 180 | U83: 7 | V83: 1 | W83: 0 | X83: 1 | Y83: 67 | Z83: 1 | AA83: 0 | AB83: 5 | AC83: River/Stream | AD83: None | AE83: 0 | AF83: 0 | AG83: 0 | AH83: 0 | AI83: 0 | AJ83: 0 | AK83: 0 | AL83: 1 | AM83: 0 | AN83: Mid-stage | AO83: 1 | AP83: Murky | AQ83: 1 | AR83: None | AS83: 0 | AT83: 0 | AU83: 0 | AV83: 0 | AW83: 0 | AX83: MB Root looks peaceful. | AY83: 1 | AZ83: Absent | BA83: Absent | BB83: Absent | BC83: Absent | BD83: Absent | BE83: Absent | BF83: Absent | BG83: Present | BH83: Recorded | BI83: Middle Branch Root River | BM83: Hiawatha | BN83: Hiawatha | BO83: 070400080208 | BP83: Middle Branch Root River | BQ83: 0704000802
A84: Dev: DBParsing_231030_v01.xlsm | B84: cdNo6xbc1yEnrkPYA3gz | C84: 45507.49 | D84: 45507.24 | E84: 45507 | F84: 2024 | G84: 8 | H84: 80reiKTTqGYqqpgYAhPwqypFwak1 | J84: -92.251752 | K84: 43.786536 | M84: 2024-08-03 06:45:26.695952.jpg-0 | N84: 1 | P84: 1 | Q84: 180 | R84: 180 | U84: 7 | V84: 1 | W84: 0 | X84: 1 | Y84: 55 | Z84: 1 | AA84: 0 | AB84: 5 | AC84: River/Stream | AD84: None | AE84: 0 | AF84: 0 | AG84: 0 | AH84: 0 | AI84: 0 | AJ84: 0 | AK84: 0 | AL84: 1 | AM84: 0 | AN84: Baseflow | AO84: 1 | AP84: Clear | AQ84: 1 | AR84: None | AS84: 0 | AT84: 0 | AU84: 0 | AV84: 0 | AW84: 0 | AX84: Little Jordan (Carson) looks great | AY84: 1 | AZ84: Absent | BA84: Absent | BB84: Absent | BC84: Absent | BD84: Absent | BE84: Absent | BF84: Absent | BG84: Present | BH84: Recorded | BI84: Carson Creek | BJ84: 1 | BM84: Hiawatha | BN84: Hiawatha | BO84: 070400080208 | BP84: Middle Branch Root River | BQ84: 0704000802
A85: Dev: DBParsing_231030_v01.xlsm | B85: c7DzzdLx3ErB56w2q4xx | C85: 45507.475 | D85: 45507.225 | E85: 45507 | F85: 2024 | G85: 8 | H85: 80reiKTTqGYqqpgYAhPwqypFwak1 | J85: -92.195336 | K85: 43.811328 | N85: 0 | P85: 1 | Q85: 180 | R85: 180 | U85: 7 | V85: 1 | W85: 0 | X85: 1 | Y85: 61 | Z85: 1 | AA85: 0 | AB85: 5 | AC85: River/Stream | AD85: None | AE85: 0 | AF85: 0 | AG85: 0 | AH85: 0 | AI85: 0 | AJ85: 0 | AK85: 0 | AL85: 1 | AM85: 0 | AN85: Mid-stage | AO85: 1 | AP85: Clear | AQ85: 1 | AR85: None | AS85: 0 | AT85: 0 | AU85: 0 | AV85: 0 | AW85: 0 | AX85: Loat Creek looks very good. | AY85: 1 | AZ85: Absent | BA85: Absent | BB85: Absent | BC85: Absent | BD85: Absent | BE85: Absent | BF85: Absent | BG85: Present | BH85: Recorded | BI85: Bear Creek | BJ85: 1 | BM85: Hiawatha | BN85: Hiawatha | BO85: 070400080207 | BP85: Bear Creek | BQ85: 0704000802
A86: Dev: DBParsing_231030_v01.xlsm | B86: U58sookcmKlC8EQHAhc0 | C86: 45506.746 | D86: 45506.496 | E86: 45506 | F86: 2024 | G86: 8 | H86: GFBS1bSIACUVgSmsBlw0BYkB9i72 | J86: -91.121931 | K86: 43.393476 | M86: 2024-08-02 12:54:22.759422.jpg-0 | N86: 1 | P86: 1 | Q86: 180 | R86: 120 | U86: 8 | V86: 1 | W86: 0 | X86: 1 | Y86: 66 | Z86: 1 | AA86: 0 | AB86: 2 | AC86: River/Stream | AD86: None | AE86: 0 | AF86: 0 | AG86: 0 | AH86: 0 | AI86: 0 | AJ86: 0 | AK86: 0 | AL86: 1 | AM86: 0 | AN86: Baseflow | AO86: 1 | AP86: Murky | AQ86: 1 | AR86: None | AS86: 0 | AT86: 0 | AU86: 0 | AV86: 0 | AW86: 0 | AY86: 0 | AZ86: Absent | BA86: Absent | BB86: Absent | BC86: Absent | BD86: Absent | BE86: Absent | BF86: Absent | BG86: Present | BH86: Recorded | BI86: Rush Creek | BJ86: 1 | BM86: Coulee Region | BN86: TU Staff | BO86: 070600010701 | BP86: Rush Creek | BQ86: 0706000107
A87: Dev: DBParsing_231030_v01.xlsm | B87: FbDHEFHyE0I6Cb2D663V | C87: 45506.7 | D87: 45506.45 | E87: 45506 | F87: 2024 | G87: 8 | H87: GFBS1bSIACUVgSmsBlw0BYkB9i72 | J87: -91.000732 | K87: 43.377425 | M87: 2024-08-02 11:47:26.987948.jpg-0 | N87: 1 | P87: 1 | Q87: 180 | R87: 60 | U87: 8 | V87: 1 | W87: 0 | X87: 1 | Y87: 60 | Z87: 1 | AA87: 0 | AB87: 2 | AC87: River/Stream | AD87: None | AE87: 0 | AF87: 0 | AG87: 0 | AH87: 0 | AI87: 0 | AJ87: 0 | AK87: 0 | AL87: 1 | AM87: 0 | AN87: Baseflow | AO87: 1 | AP87: Clear | AQ87: 1 | AR87: None | AS87: 0 | AT87: 0 | AU87: 0 | AV87: 0 | AW87: 0 | AY87: 0 | AZ87: Absent | BA87: Absent | BB87: Absent | BC87: Absent | BD87: Absent | BE87: Absent | BF87: Absent | BG87: Present | BH87: Recorded | BI87: Sugar Creek | BJ87: 1 | BM87: Coulee Region | BN87: TU Staff | BO87: 070600010703 | BP87: Sugar Creek | BQ87: 0706000107
A88: Dev: DBParsing_231030_v01.xlsm | B88: Hs50r1YDqIdJCs1Gl7Xd | C88: 45504.841 | D88: 45504.591 | E88: 45504 | F88: 2024 | G88: 7 | H88: DKq8OLTYViaAQZeR9ADiCfs22M63 | J88: -91.892741 | K88: 44.513258 | M88: 2024-07-31 15:11:08.429343.jpg-0 | N88: 1 | P88: 1 | Q88: 180 | R88: 180 | U88: 7.5 | V88: 1 | W88: 0 | X88: 1 | Y88: 64 | Z88: 1 | AA88: 0 | AB88: 2 | AC88: River/Stream | AD88: None | AE88: 0 | AF88: 0 | AG88: 0 | AH88: 0 | AI88: 0 | AJ88: 0 | AK88: 0 | AL88: 1 | AM88: 0 | AN88: Baseflow | AO88: 1 | AP88: Clear | AQ88: 1 | AR88: None | AS88: 0 | AT88: 0 | AU88: 0 | AV88: 0 | AW88: 0 | AY88: 0 | AZ88: Absent | BA88: Absent | BB88: Absent | BC88: Absent | BD88: Absent | BE88: Absent | BF88: Absent | BG88: Present | BH88: Recorded | BI88: 0 | BJ88: 1 | BM88: Wisconsin Clear Water | BN88: TU Staff | BO88: 070500051204 | BP88: Little Bear Creek | BQ88: 0705000512
A89: Dev: DBParsing_231030_v01.xlsm | B89: Md8XFRGdVwCmhjakc0iF | C89: 45504.756 | D89: 45504.506 | E89: 45504 | F89: 2024 | G89: 7 | H89: DKq8OLTYViaAQZeR9ADiCfs22M63 | J89: -91.882962 | K89: 44.51349 | N89: 0 | P89: 1 | Q89: 180 | R89: 120 | U89: 8 | V89: 1 | W89: 0 | X89: 1 | Y89: 59 | Z89: 1 | AA89: 0 | AB89: 1 | AC89: River/Stream | AD89: None | AE89: 0 | AF89: 0 | AG89: 0 | AH89: 0 | AI89: 0 | AJ89: 0 | AK89: 0 | AL89: 1 | AM89: 0 | AN89: Baseflow | AO89: 1 | AP89: Clear | AQ89: 1 | AR89: None | AS89: 0 | AT89: 0 | AU89: 0 | AV89: 0 | AW89: 0 | AY89: 0 | AZ89: Absent | BA89: Absent | BB89: Absent | BC89: Absent | BD89: Absent | BE89: Absent | BF89: Absent | BG89: Present | BH89: Recorded | BI89: 0 | BJ89: 1 | BM89: Wisconsin Clear Water | BN89: TU Staff | BO89: 070500051204 | BP89: Little Bear Creek | BQ89: 0705000512
A90: Dev: DBParsing_231030_v01.xlsm | B90: ZgPWstZEeHedfx6Hgi5T | C90: 45504.743 | D90: 45504.493 | E90: 45504 | F90: 2024 | G90: 7 | H90: VQ9bNtzttGcXOEuaXrEAEYLfT103 | J90: -91.581016 | K90: 43.641432 | N90: 0 | P90: 1 | Q90: 80 | R90: 180 | U90: 8.5 | V90: 1 | W90: 0 | X90: 1 | Y90: 52 | Z90: 1 | AA90: 0 | AB90: 10 | AC90: River/Stream | AD90: None | AE90: 0 | AF90: 0 | AG90: 0 | AH90: 0 | AI90: 0 | AJ90: 0 | AK90: 0 | AL90: 1 | AM90: 0 | AN90: Baseflow | AO90: 1 | AP90: Clear | AQ90: 1 | AR90: None | AS90: 0 | AT90: 0 | AU90: 0 | AV90: 0 | AW90: 0 | AY90: 0 | AZ90: Absent | BA90: Absent | BB90: Absent | BC90: Absent | BD90: Absent | BE90: Absent | BF90: Absent | BG90: Present | BH90: Recorded | BJ90: 1 | BM90: Win Cres | BN90: Hiawatha | BO90: 070400080805 | BP90: Beaver Creek | BQ90: 0704000808
A91: Dev: DBParsing_231030_v01.xlsm | B91: tlD6H0k5HegdCiUtQmuj | C91: 45504.722 | D91: 45504.472 | E91: 45504 | F91: 2024 | G91: 7 | H91: Us7gjDbTcVWrjDL157enRZKC9Tw1 | J91: -91.706024 | K91: 42.893362 | M91: 2024-07-31 12:19:12.280307.jpg-02024-07-31 12:19:12.280307.jpg-1 | N91: 1 | P91: 1 | Q91: 180 | R91: 180 | U91: 7.5 | V91: 0 | X91: 1 | Y91: 60 | Z91: 1 | AA91: 0 | AB91: 10 | AC91: River/Stream | AD91: Bank Erosion | AE91: 0 | AF91: 1 | AG91: 0 | AH91: 0 | AI91: 0 | AJ91: 0 | AK91: 0 | AL91: 0 | AM91: 0 | AN91: Baseflow | AO91: 1 | AP91: Muddy | AQ91: 1 | AR91: None | AS91: 0 | AT91: 0 | AU91: 0 | AV91: 0 | AW91: 0 | AY91: 0 | AZ91: Absent | BA91: Present | BB91: Absent | BC91: Absent | BD91: Absent | BE91: Absent | BF91: Absent | BG91: Absent | BH91: Recorded | BI91: Mink Creek | BM91: Iowa Driftless | BN91: Agency/University | BO91: 070600040602 | BP91: Mink Creek | BQ91: 0706000406
A92: Dev: DBParsing_231030_v01.xlsm | B92: QhzL5WBgj1H4znO8gszw | C92: 45504.718 | D92: 45504.468 | E92: 45504 | F92: 2024 | G92: 7 | H92: VQ9bNtzttGcXOEuaXrEAEYLfT103 | J92: -91.373409 | K92: 43.603057 | N92: 0 | P92: 1 | Q92: 80 | R92: 180 | U92: 8 | V92: 1 | W92: 0 | X92: 1 | Y92: 66 | Z92: 1 | AA92: 0 | AB92: 2 | AC92: River/Stream | AD92: None | AE92: 0 | AF92: 0 | AG92: 0 | AH92: 0 | AI92: 0 | AJ92: 0 | AK92: 0 | AL92: 1 | AM92: 0 | AN92: Baseflow | AO92: 1 | AP92: Clear | AQ92: 1 | AR92: None | AS92: 0 | AT92: 0 | AU92: 0 | AV92: 0 | AW92: 0 | AY92: 0 | AZ92: Absent | BA92: Absent | BB92: Absent | BC92: Absent | BD92: Absent | BE92: Absent | BF92: Absent | BG92: Present | BH92: Recorded | BI92: Crooked Creek | BJ92: 1 | BM92: Win Cres | BN92: Hiawatha | BO92: 070600010203 | BP92: Clear Creek-Crooked Creek | BQ92: 0706000102
A93: Dev: DBParsing_231030_v01.xlsm | B93: wta46yjCHg8a0ge6BarQ | C93: 45504.692 | D93: 45504.442 | E93: 45504 | F93: 2024 | G93: 7 | H93: VQ9bNtzttGcXOEuaXrEAEYLfT103 | J93: -91.413103 | K93: 43.540516 | N93: 0 | P93: 1 | Q93: 120 | R93: 180 | U93: 8.5 | V93: 1 | W93: 0 | X93: 1 | Y93: 62 | Z93: 1 | AA93: 0 | AB93: 5 | AC93: River/Stream | AD93: None | AE93: 0 | AF93: 0 | AG93: 0 | AH93: 0 | AI93: 0 | AJ93: 0 | AK93: 0 | AL93: 1 | AM93: 0 | AN93: Baseflow | AO93: 1 | AP93: Clear | AQ93: 1 | AR93: None | AS93: 0 | AT93: 0 | AU93: 0 | AV93: 0 | AW93: 0 | AY93: 0 | AZ93: Absent | BA93: Absent | BB93: Absent | BC93: Absent | BD93: Absent | BE93: Absent | BF93: Absent | BG93: Present | BH93: Recorded | BJ93: 1 | BK93: 1 | BL93: 1 | BM93: Win Cres | BN93: Hiawatha | BO93: 070600010401 | BP93: Upper Winnebago Creek | BQ93: 0706000104
A94: Dev: DBParsing_231030_v01.xlsm | B94: iXEujxxXuSB2k2TCRo5D | C94: 45504.663 | D94: 45504.413 | E94: 45504 | F94: 2024 | G94: 7 | H94: VQ9bNtzttGcXOEuaXrEAEYLfT103 | J94: -91.569868 | K94: 43.502244 | N94: 0 | P94: 1 | Q94: 0 | R94: 60 | U94: 8 | V94: 1 | W94: 0 | X94: 1 | Y94: 54 | Z94: 1 | AA94: 0 | AB94: 5 | AC94: River/Stream | AD94: None | AE94: 0 | AF94: 0 | AG94: 0 | AH94: 0 | AI94: 0 | AJ94: 0 | AK94: 0 | AL94: 1 | AM94: 0 | AN94: Baseflow | AO94: 1 | AP94: Clear | AQ94: 1 | AR94: None | AS94: 0 | AT94: 0 | AU94: 0 | AV94: 0 | AW94: 0 | AY94: 0 | AZ94: Absent | BA94: Absent | BB94: Absent | BC94: Absent | BD94: Absent | BE94: Absent | BF94: Absent | BG94: Present | BH94: Recorded | BI94: Bee Creek | BJ94: 1 | BK94: 1 | BL94: 1 | BM94: Win Cres | BN94: Hiawatha | BO94: 070600020502 | BP94: Waterloo Creek | BQ94: 0706000205
A95: Dev: DBParsing_231030_v01.xlsm | B95: Cf9nZIJRYGdKXWmxZnVH | C95: 45504.634 | D95: 45504.384 | E95: 45504 | F95: 2024 | G95: 7 | H95: VQ9bNtzttGcXOEuaXrEAEYLfT103 | J95: -91.813406 | K95: 43.597543 | N95: 0 | P95: 1 | Q95: 180 | R95: 180 | U95: 7.5 | V95: 1 | W95: 0 | X95: 1 | Y95: 62 | Z95: 1 | AA95: 0 | AB95: 5 | AC95: River/Stream | AD95: None | AE95: 0 | AF95: 0 | AG95: 0 | AH95: 0 | AI95: 0 | AJ95: 0 | AK95: 0 | AL95: 1 | AM95: 0 | AN95: Baseflow | AO95: 1 | AP95: Murky | AQ95: 1 | AR95: None | AS95: 0 | AT95: 0 | AU95: 0 | AV95: 0 | AW95: 0 | AY95: 0 | AZ95: Absent | BA95: Absent | BB95: Absent | BC95: Absent | BD95: Absent | BE95: Absent | BF95: Absent | BG95: Present | BH95: Recorded | BI95: Wisel Creek | BJ95: 1 | BK95: 1 | BL95: 1 | BM95: Win Cres | BN95: Hiawatha | BO95: 070400080802 | BP95: Wisel Creek | BQ95: 0704000808
A96: Dev: DBParsing_231030_v01.xlsm | B96: DvLQLLS25xWS03HRMibJ | C96: 45504.615 | D96: 45504.365 | E96: 45504 | F96: 2024 | G96: 7 | H96: VQ9bNtzttGcXOEuaXrEAEYLfT103 | J96: -91.789788 | K96: 43.677345 | N96: 0 | P96: 1 | Q96: 80 | R96: 180 | U96: 7 | V96: 1 | W96: 0 | X96: 1 | Y96: 62 | Z96: 1 | AA96: 0 | AB96: 2 | AC96: River/Stream | AD96: None | AE96: 0 | AF96: 0 | AG96: 0 | AH96: 0 | AI96: 0 | AJ96: 0 | AK96: 0 | AL96: 1 | AM96: 0 | AN96: Baseflow | AO96: 1 | AP96: Clear | AQ96: 1 | AR96: None | AS96: 0 | AT96: 0 | AU96: 0 | AV96: 0 | AW96: 0 | AY96: 0 | AZ96: Absent | BA96: Absent | BB96: Absent | BC96: Absent | BD96: Absent | BE96: Absent | BF96: Absent | BG96: Present | BH96: Recorded | BI96: 0 | BJ96: 1 | BK96: 1 | BL96: 1 | BM96: Win Cres | BN96: Hiawatha | BO96: 070400080803 | BP96: Middle South Fork Root River | BQ96: 0704000808
A97: Dev: DBParsing_231030_v01.xlsm | B97: Pm6TULI1aNaXOkNdeXQK | C97: 45504.553 | D97: 45504.303 | E97: 45504 | F97: 2024 | G97: 7 | H97: DKq8OLTYViaAQZeR9ADiCfs22M63 | J97: -91.797346 | K97: 44.454049 | M97: 2024-07-31 08:15:39.583975.jpg-0 | N97: 1 | P97: 1 | Q97: 180 | R97: 120 | U97: 8 | V97: 1 | W97: 0 | X97: 1 | Y97: 60 | Z97: 1 | AA97: 0 | AB97: 2 | AC97: River/Stream | AD97: None | AE97: 0 | AF97: 0 | AG97: 0 | AH97: 0 | AI97: 0 | AJ97: 0 | AK97: 0 | AL97: 1 | AM97: 0 | AN97: Baseflow | AO97: 1 | AP97: Murky | AQ97: 1 | AR97: None | AS97: 0 | AT97: 0 | AU97: 0 | AV97: 0 | AW97: 0 | AY97: 0 | AZ97: Absent | BA97: Absent | BB97: Absent | BC97: Absent | BD97: Absent | BE97: Absent | BF97: Absent | BG97: Present | BH97: Recorded | BI97: Tamarack Creek | BK97: 1 | BL97: 1 | BM97: Wisconsin Clear Water | BN97: TU Staff | BO97: 070400030203 | BP97: Tamarack Creek | BQ97: 0704000302
A98: Dev: DBParsing_231030_v01.xlsm | B98: 0wKH11BvKGllR5c4hr9p | C98: 45503.993 | D98: 45503.743 | E98: 45503 | F98: 2024 | G98: 7 | H98: mMKogvdinjOuckB5tkMQrxnYO852 | J98: -92.236406 | K98: 44.840205 | N98: 0 | P98: 0 | V98: 1 | W98: 0 | X98: 0 | Z98: 0 | AE98: -1 | AF98: -1 | AG98: -1 | AH98: -1 | AI98: -1 | AJ98: -1 | AK98: -1 | AL98: -1 | AM98: 1 | AO98: 0 | AQ98: 0 | AS98: -1 | AT98: -1 | AU98: -1 | AV98: -1 | AW98: 1 | AY98: 0 | AZ98: No Data | BA98: No Data | BB98: No Data | BC98: No Data | BD98: No Data | BE98: No Data | BF98: No Data | BG98: No Data | BH98: No Data | BI98: Burkhart Creek | BJ98: 1 | BK98: 1 | BL98: 1 | BM98: Kiap-TU-Wish | BN98: Kiap-TU-Wish | BO98: 070500051004 | BP98: Burkhart Creek-Eau Galle Creek | BQ98: 0705000510
A99: Dev: DBParsing_231030_v01.xlsm | B99: QUvQHFEDQEigmQdxsD4Y | C99: 45503.991 | D99: 45503.741 | E99: 45503 | F99: 2024 | G99: 7 | H99: mMKogvdinjOuckB5tkMQrxnYO852 | I99: Eau Galle River @ WI Hwy 29 | J99: -92.236407 | K99: 44.840188 | M99: 2024-07-30 18:46:37.767795.jpg-0 | N99: 1 | P99: 1 | Q99: 180 | R99: 120 | U99: 7 | V99: 0 | X99: 1 | Y99: 73 | Z99: 1 | AA99: 0 | AB99: 2 | AC99: River/Stream | AD99: None | AE99: 0 | AF99: 0 | AG99: 0 | AH99: 0 | AI99: 0 | AJ99: 0 | AK99: 0 | AL99: 1 | AM99: 0 | AN99: Baseflow | AO99: 1 | AP99: Clear | AQ99: 1 | AR99: None | AS99: 0 | AT99: 0 | AU99: 0 | AV99: 0 | AW99: 0 | AX99: beautiful day! | AY99: 1 | AZ99: Absent | BA99: Absent | BB99: Absent | BC99: Absent | BD99: Absent | BE99: Absent | BF99: Absent | BG99: Present | BH99: Recorded | BI99: Burkhart Creek | BJ99: 1 | BK99: 1 | BL99: 1 | BM99: Kiap-TU-Wish | BN99: Kiap-TU-Wish | BO99: 070500051004 | BP99: Burkhart Creek-Eau Galle Creek | BQ99: 0705000510
A100: Dev: DBParsing_231030_v01.xlsm | B100: CIv6WjFKUrqHRdt9K7Ml | C100: 45503.864 | D100: 45503.614 | E100: 45503 | F100: 2024 | G100: 7 | H100: DKq8OLTYViaAQZeR9ADiCfs22M63 | J100: -91.177782 | K100: 44.422585 | M100: 2024-07-30 15:44:39.237277.jpg-0 | N100: 1 | P100: 1 | Q100: 80 | R100: 0 | U100: 7 | V100: 1 | W100: 0 | X100: 1 | Y100: 66 | Z100: 1 | AA100: 0 | AB100: 0 | AC100: River/Stream | AD100: None | AE100: 0 | AF100: 0 | AG100: 0 | AH100: 0 | AI100: 0 | AJ100: 0 | AK100: 0 | AL100: 1 | AM100: 0 | AN100: Baseflow | AO100: 1 | AP100: Murky | AQ100: 1 | AR100: Local Thunderstorm | AS100: 0 | AT100: 1 | AU100: 0 | AV100: 0 | AW100: 0 | AY100: 0 | AZ100: Absent | BA100: Absent | BB100: Absent | BC100: Absent | BD100: Absent | BE100: Absent | BF100: Absent | BG100: Present | BH100: Recorded | BI100: Big Slough | BJ100: 1 | BM100: Wisconsin Clear Water | BN100: TU Staff | BO100: 070400050102 | BP100: Middle Pigeon Creek | BQ100: 0704000501
...

Sheet Use
A1: TU DARE Angler Science DB
B3: DRIFTLESS AREA OBSERVATIONS
B4: 2020-24 Observations (as of Oct 31st)
C5: Overall | D5: Number | E5: Percentage
C6: Target | D6: 2500 | E6: 1 | AH6: =20/90 -> 0.22222222
C7: Observations | D7: =TUDB!B4 -> 2320 | E7: =D7/D6 -> 0.928 | F7: =E7-0.05 -> 0.878
C8: Remaining | D8: =D6-D7 -> 180 | E8: =E6-E7 -> 0.072
B10: Participation
D11: Contributing Individuals | E11: 174
B12: Observations by Individuals
B13: Obs. | C13: 2020 | D13: 2021 | E13: 2022 | F13: 2023 | G13: 2024
B14: 0 | C14: {=FREQUENCY(F$50:F$171,$B$14:$B$22)} -> 111 | D14: {=FREQUENCY(G$50:G$171,$B$14:$B$22)} -> 89 | E14: {=FREQUENCY(H$50:H$171,$B$14:$B$22)} -> 61 | F14: {=FREQUENCY(I$50:I$171,$B$14:$B$22)} -> 41 | G14: {=FREQUENCY(J$50:J$171,$B$14:$B$22)} -> 85
B15: 1 | C15: 4 | D15: 2 | E15: 12 | F15: 19 | G15: 9 | S15: Observations per observer
B16: 5 | C16: 4 | D16: 10 | E16: 26 | F16: 26 | G16: 11
B17: 10 | C17: 1 | D17: 11 | E17: 10 | F17: 18 | G17: 7
B18: 15 | C18: 1 | D18: 3 | E18: 7 | F18: 5 | G18: 2
B19: 20 | C19: 0 | D19: 3 | E19: 2 | F19: 1 | G19: 1
B20: 25 | C20: 0 | D20: 2 | E20: 0 | F20: 2 | G20: 1
B21: 30 | C21: 0 | D21: 2 | E21: 1 | F21: 2 | G21: 1
B22: 35 | C22: 1 | D22: 0 | E22: 1 | F22: 0 | G22: 0
B23: 40+ | C23: 0 | D23: 0 | E23: 2 | F23: 8 | G23: 5
D26: Trout Streams | E26: =SUM(TU_DB[Trout Stream Flag]) -> 1945 | F26: =E26/(D7-60) -> 0.86061947
D27: Brook Trout Streams | E27: =SUM(TU_DB[Brook Trout Stream Flag]) -> 801 | F27: =E27/(D7-60) -> 0.35442478
B29: User Stats
B30: Year | C30: Active Observers | D30: Change from Previous Year | E30: New Observers | F30: Change from Previous Year | G30: Observations/ Observer | H30: Change from Previous Year | S30: Observations Reported | T30: Average | U30: 2020 | V30: 2021 | W30: 2022 | X30: 2023 | Y30: 2024
B31: 2019 | C31: {=TRANSPOSE(E47:J47)} -> 16 | D31: - | E31: 16 | F31: - | G31: =60/16 -> 3.75 | H31: - | S31: 0-1 | T31: =AVERAGE(U31:X31) -> 9.25 | U31: =C15 -> 4 | V31: =D15 -> 2 | W31: =E15 -> 12 | X31: =F15 -> 19 | Y31: =G15 -> 9
B32: 2020 | C32: 31 | D32: 0.98 | E32: {=TRANSPOSE(K47:O47)} -> 30 | F32: =(E32-E31)/E31 -> 0.875 | G32: {=TRANSPOSE(F48:J48)} -> 4.6451613 | H32: =(G32-G31)/G31 -> 0.23870968 | S32: 2-5 | T32: =AVERAGE(U32:X32) -> 16.5 | U32: =C16 -> 4 | V32: =D16 -> 10 | W32: =E16 -> 26 | X32: =F16 -> 26 | Y32: =G16 -> 11
B33: 2021 | C33: 54 | D33: =(C33-C32)/C32 -> 0.74193548 | E33: 43 | F33: =(E33-E32)/E32 -> 0.43333333 | G33: 7.537037 | H33: =(G33-G32)/G32 -> 0.62255658 | S33: 6-10 | T33: =AVERAGE(U33:X33) -> 10 | U33: =C17 -> 1 | V33: =D17 -> 11 | W33: =E17 -> 10 | X33: =F17 -> 18 | Y33: =G17 -> 7
B34: 2022 | C34: 61 | D34: =(C34-C33)/C33 -> 0.12962963 | E34: 33 | F34: =(E34-E33)/E33 -> -0.23255814 | G34: 7.5245902 | H34: =(G34-G33)/G33 -> -0.0016514279 | S34: 11-15 | T34: =AVERAGE(U34:X34) -> 4 | U34: =C18 -> 1 | V34: =D18 -> 3 | W34: =E18 -> 7 | X34: =F18 -> 5 | Y34: =G18 -> 2
B35: 2023 | C35: 81 | D35: =(C35-C34)/C34 -> 0.32786885 | E35: 39 | F35: =(E35-E34)/E34 -> 0.18181818 | G35: 9.962963 | H35: =(G35-G34)/G34 -> 0.3240539 | S35: 16-20 | T35: =AVERAGE(U35:X35) -> 1.5 | U35: =C19 -> 0 | V35: =D19 -> 3 | W35: =E19 -> 2 | X35: =F19 -> 1 | Y35: =G19 -> 1
B36: 2024 | C36: 37 | D36: =(C36-C35)/C35 -> -0.54320988 | E36: 13 | F36: =(E36-E31)/E31 -> -0.1875 | G36: 11.945946 | H36: =(G36-G31)/G31 -> 2.1855856 | S36: 21-25 | T36: =AVERAGE(U36:X36) -> 1 | U36: =C20 -> 0 | V36: =D20 -> 2 | W36: =E20 -> 0 | X36: =F20 -> 2 | Y36: =G20 -> 1
B37: 2025 | S37: 26-30 | T37: =AVERAGE(U37:X37) -> 1.25 | U37: =C21 -> 0 | V37: =D21 -> 2 | W37: =E21 -> 1 | X37: =F21 -> 2 | Y37: =G21 -> 1
B38: 2026 | S38: 31-35 | T38: =AVERAGE(U38:X38) -> 0.5 | U38: =C22 -> 1 | V38: =D22 -> 0 | W38: =E22 -> 1 | X38: =F22 -> 0 | Y38: =G22 -> 0
B39: 2027 | S39: 36-40+ | T39: =AVERAGE(U39:X39) -> 2.5 | U39: =C23 -> 0 | V39: =D23 -> 0 | W39: =E23 -> 2 | X39: =F23 -> 8 | Y39: =G23 -> 5
B40: 2028 | D40: =(C40-C35)/C35 -> -1 | F40: =(E40-E35)/E35 -> -1 | H40: =(G40-G35)/G35 -> -1 | T40: =SUM(T31:T39) -> 46.5 | U40: =SUM(U31:U39) -> 11 | V40: =SUM(V31:V39) -> 33 | W40: =SUM(W31:W39) -> 61 | X40: =SUM(X31:X39) -> 81 | Y40: =SUM(Y31:Y39) -> 37
B41: *Large turnover between 2019 to 2020 likely due to the change of app download from manual to through the Play Store/Apple Store
B46: DA User Data | K46: New Users | S46: App Use Stats
B47: Observers | D47: =COUNTIF(C50:C506,">"&0) -> 0 | E47: 16 | F47: =COUNTIF(F50:F506,">"&0) -> 31 | G47: =COUNTIF(G50:G506,">"&0) -> 54 | H47: =COUNTIF(H50:H506,">"&0) -> 61 | I47: =COUNTIF(I50:I506,">"&0) -> 81 | J47: =COUNTIF(J50:J506,">"&0) -> 37 | K47: =SUM(K50:K506) -> 30 | L47: =SUM(L50:L506) -> 43 | M47: =SUM(M50:M506) -> 33 | N47: =SUM(N50:N506) -> 39 | O47: =SUM(O50:O506) -> 13
B48: Obsvns/obsvr | D48: =IFERROR(SUM(C50:C506)/D47,0) -> 0 | E48: =60/E47 -> 3.75 | F48: =IFERROR(SUM(F50:F506)/F47,0) -> 4.6451613 | G48: =IFERROR(SUM(G50:G506)/G47,0) -> 7.537037 | H48: =IFERROR(SUM(H50:H506)/H47,0) -> 7.5245902 | I48: =IFERROR(SUM(I50:I506)/I47,0) -> 9.962963 | J48: =IFERROR(SUM(J50:J506)/J47,0) -> 11.945946 | S48: Year | T48: Observa-tions | U48: Observ. Water Source | V48: 5n1 Test Strip | W48: 2n1 Test Strip | X48: Phosphorus Test Strip | Y48: Water Temp. | Z48: Stream Disturb-ances | AA48: Current Conditions
B49: Obsvr ID | C49: Affilliation | D49: Sum | E49: 2019 | F49: 2020 | G49: 2021 | H49: 2022 | I49: 2023 | J49: 2024 | K49: 2020 | L49: 2021 | M49: 2022 | N49: 2023 | O49: 2024 | S49: Analyses per observation
B50: {=_xlfn.UNIQUE(TU_DB[ObserverID])} -> 3ewh0JhsqndewkOhEmNvJ9cb0n83 | C50: Kiap-TU-Wish | D50: =SUM(E50:J50) -> 25 | E50: =COUNTIFS(TUDB!$H$8:$H$2326,Use!$B50,TUDB!$F$8:$F$2326,Use!E$49) -> 0 | F50: =COUNTIFS(TUDB!$H$8:$H$2326,Use!$B50,TUDB!$F$8:$F$2326,Use!F$49) -> 1 | G50: =COUNTIFS(TUDB!$H$8:$H$2326,Use!$B50,TUDB!$F$8:$F$2326,Use!G$49) -> 8 | H50: =COUNTIFS(TUDB!$H$8:$H$2326,Use!$B50,TUDB!$F$8:$F$2326,Use!H$49) -> 7 | I50: =COUNTIFS(TUDB!$H$8:$H$2326,Use!$B50,TUDB!$F$8:$F$2326,Use!I$49) -> 4 | J50: =COUNTIFS(TUDB!$H$8:$H$2326,Use!$B50,TUDB!$F$8:$F$2326,Use!J$49) -> 5 | K50: =IF(AND(F50>0,SUM($E50)=0),1,0) -> 1 | L50: =IF(AND(G50>0,SUM($E50:F50)=0),1,0) -> 0 | M50: =IF(AND(H50>0,SUM($E50:G50)=0),1,0) -> 0 | N50: =IF(AND(I50>0,SUM($E50:H50)=0),1,0) -> 0 | O50: =IF(AND(J50>0,SUM($E50:I50)=0),1,0) -> 0 | S50: 2019* | T50: 60 | U50: 60 | V50: 46 | W50: 0 | X50: 41 | Y50: 41 | Z50: 55 | AA50: 46
B51: 7a7IFD1YT3aDXB8CbnSJjn1oLRC2 | C51: Unknown | D51: =SUM(E51:J51) -> 29 | E51: =COUNTIFS(TUDB!$H$8:$H$2326,Use!$B51,TUDB!$F$8:$F$2326,Use!E$49) -> 0 | F51: =COUNTIFS(TUDB!$H$8:$H$2326,Use!$B51,TUDB!$F$8:$F$2326,Use!F$49) -> 0 | G51: =COUNTIFS(TUDB!$H$8:$H$2326,Use!$B51,TUDB!$F$8:$F$2326,Use!G$49) -> 8 | H51: =COUNTIFS(TUDB!$H$8:$H$2326,Use!$B51,TUDB!$F$8:$F$2326,Use!H$49) -> 7 | I51: =COUNTIFS(TUDB!$H$8:$H$2326,Use!$B51,TUDB!$F$8:$F$2326,Use!I$49) -> 7 | J51: =COUNTIFS(TUDB!$H$8:$H$2326,Use!$B51,TUDB!$F$8:$F$2326,Use!J$49) -> 7 | K51: =IF(AND(F51>0,SUM($E51)=0),1,0) -> 0 | L51: =IF(AND(G51>0,SUM($E51:F51)=0),1,0) -> 1 | M51: =IF(AND(H51>0,SUM($E51:G51)=0),1,0) -> 0 | N51: =IF(AND(I51>0,SUM($E51:H51)=0),1,0) -> 0 | O51: =IF(AND(J51>0,SUM($E51:I51)=0),1,0) -> 0 | S51: 2020 | T51: =COUNTIF(TU_DB[Year],$S51) -> 144 | U51: =COUNTIFS(TU_DB[Year],$S51,TU_DB[Source],"<>"&"") -> 118 | V51: =COUNTIFS(TU_DB[Year],$S51,TU_DB[[5n1 Flag ]],1) -> 108 | W51: =COUNTIFS(TU_DB[Year],$S51,TU_DB[[2n1 Flag ]],1) -> 89 | X51: =COUNTIFS(TU_DB[Year],$S51,TU_DB[Phos Flag],1) -> 84 | Y51: =COUNTIFS(TU_DB[Year],$S51,TU_DB[Water Temp Flag],1) -> 95 | Z51: =COUNTIFS(TU_DB[Year],$S51,TU_DB[Dis: Not Reported],0) -> 103 | AA51: =COUNTIFS(TU_DB[Year],$S51,TU_DB[Water Level Flag],1) -> 118
B52: VCf2q8JFBSOaJbmxiMqirI5xKFn2 | C52: Kiap-TU-Wish | D52: =SUM(E52:J52) -> 27 | E52: =COUNTIFS(TUDB!$H$8:$H$2326,Use!$B52,TUDB!$F$8:$F$2326,Use!E$49) -> 0 | F52: =COUNTIFS(TUDB!$H$8:$H$2326,Use!$B52,TUDB!$F$8:$F$2326,Use!F$49) -> 0 | G52: =COUNTIFS(TUDB!$H$8:$H$2326,Use!$B52,TUDB!$F$8:$F$2326,Use!G$49) -> 6 | H52: =COUNTIFS(TUDB!$H$8:$H$2326,Use!$B52,TUDB!$F$8:$F$2326,Use!H$49) -> 5 | I52: =COUNTIFS(TUDB!$H$8:$H$2326,Use!$B52,TUDB!$F$8:$F$2326,Use!I$49) -> 7 | J52: =COUNTIFS(TUDB!$H$8:$H$2326,Use!$B52,TUDB!$F$8:$F$2326,Use!J$49) -> 9 | K52: =IF(AND(F52>0,SUM($E52)=0),1,0) -> 0 | L52: =IF(AND(G52>0,SUM($E52:F52)=0),1,0) -> 1 | M52: =IF(AND(H52>0,SUM($E52:G52)=0),1,0) -> 0 | N52: =IF(AND(I52>0,SUM($E52:H52)=0),1,0) -> 0 | O52: =IF(AND(J52>0,SUM($E52:I52)=0),1,0) -> 0 | S52: 2021 | T52: =COUNTIF(TU_DB[Year],$S52) -> 407 | U52: =COUNTIFS(TU_DB[Year],$S52,TU_DB[Source],"<>"&"") -> 382 | V52: =COUNTIFS(TU_DB[Year],$S52,TU_DB[[5n1 Flag ]],1) -> 361 | W52: =COUNTIFS(TU_DB[Year],$S52,TU_DB[[2n1 Flag ]],1) -> 308 | X52: =COUNTIFS(TU_DB[Year],$S52,TU_DB[Phos Flag],1) -> 324 | Y52: =COUNTIFS(TU_DB[Year],$S52,TU_DB[Water Temp Flag],1) -> 304 | Z52: =COUNTIFS(TU_DB[Year],$S52,TU_DB[Dis: Not Reported],0) -> 281 | AA52: =COUNTIFS(TU_DB[Year],$S52,TU_DB[Water Level Flag],1) -> 337
B53: VQ9bNtzttGcXOEuaXrEAEYLfT103 | C53: Hiawatha | D53: =SUM(E53:J53) -> 108 | E53: =COUNTIFS(TUDB!$H$8:$H$2326,Use!$B53,TUDB!$F$8:$F$2326,Use!E$49) -> 0 | F53: =COUNTIFS(TUDB!$H$8:$H$2326,Use!$B53,TUDB!$F$8:$F$2326,Use!F$49) -> 0 | G53: =COUNTIFS(TUDB!$H$8:$H$2326,Use!$B53,TUDB!$F$8:$F$2326,Use!G$49) -> 0 | H53: =COUNTIFS(TUDB!$H$8:$H$2326,Use!$B53,TUDB!$F$8:$F$2326,Use!H$49) -> 14 | I53: =COUNTIFS(TUDB!$H$8:$H$2326,Use!$B53,TUDB!$F$8:$F$2326,Use!I$49) -> 47 | J53: =COUNTIFS(TUDB!$H$8:$H$2326,Use!$B53,TUDB!$F$8:$F$2326,Use!J$49) -> 47 | K53: =IF(AND(F53>0,SUM($E53)=0),1,0) -> 0 | L53: =IF(AND(G53>0,SUM($E53:F53)=0),1,0) -> 0 | M53: =IF(AND(H53>0,SUM($E53:G53)=0),1,0) -> 1 | N53: =IF(AND(I53>0,SUM($E53:H53)=0),1,0) -> 0 | O53: =IF(AND(J53>0,SUM($E53:I53)=0),1,0) -> 0 | S53: 2022 | T53: =COUNTIF(TU_DB[Year],$S53) -> 459 | U53: =COUNTIFS(TU_DB[Year],$S53,TU_DB[Source],"<>"&"") -> 436 | V53: =COUNTIFS(TU_DB[Year],$S53,TU_DB[[5n1 Flag ]],1) -> 419 | W53: =COUNTIFS(TU_DB[Year],$S53,TU_DB[[2n1 Flag ]],1) -> 381 | X53: =COUNTIFS(TU_DB[Year],$S53,TU_DB[Phos Flag],1) -> 374 | Y53: =COUNTIFS(TU_DB[Year],$S53,TU_DB[Water Temp Flag],1) -> 366 | Z53: =COUNTIFS(TU_DB[Year],$S53,TU_DB[Dis: Not Reported],0) -> 356 | AA53: =COUNTIFS(TU_DB[Year],$S53,TU_DB[Water Level Flag],1) -> 389
B54: 80reiKTTqGYqqpgYAhPwqypFwak1 | C54: Hiawatha | D54: =SUM(E54:J54) -> 160 | E54: =COUNTIFS(TUDB!$H$8:$H$2326,Use!$B54,TUDB!$F$8:$F$2326,Use!E$49) -> 0 | F54: =COUNTIFS(TUDB!$H$8:$H$2326,Use!$B54,TUDB!$F$8:$F$2326,Use!F$49) -> 2 | G54: =COUNTIFS(TUDB!$H$8:$H$2326,Use!$B54,TUDB!$F$8:$F$2326,Use!G$49) -> 29 | H54: =COUNTIFS(TUDB!$H$8:$H$2326,Use!$B54,TUDB!$F$8:$F$2326,Use!H$49) -> 32 | I54: =COUNTIFS(TUDB!$H$8:$H$2326,Use!$B54,TUDB!$F$8:$F$2326,Use!I$49) -> 38 | J54: =COUNTIFS(TUDB!$H$8:$H$2326,Use!$B54,TUDB!$F$8:$F$2326,Use!J$49) -> 59 | K54: =IF(AND(F54>0,SUM($E54)=0),1,0) -> 1 | L54: =IF(AND(G54>0,SUM($E54:F54)=0),1,0) -> 0 | M54: =IF(AND(H54>0,SUM($E54:G54)=0),1,0) -> 0 | N54: =IF(AND(I54>0,SUM($E54:H54)=0),1,0) -> 0 | O54: =IF(AND(J54>0,SUM($E54:I54)=0),1,0) -> 0 | S54: 2023 | T54: =COUNTIF(TU_DB[Year],$S54) -> 807 | U54: =COUNTIFS(TU_DB[Year],$S54,TU_DB[Source],"<>"&"") -> 769 | V54: =COUNTIFS(TU_DB[Year],$S54,TU_DB[[5n1 Flag ]],1) -> 714 | W54: =COUNTIFS(TU_DB[Year],$S54,TU_DB[[2n1 Flag ]],1) -> 706 | X54: =COUNTIFS(TU_DB[Year],$S54,TU_DB[Phos Flag],1) -> 669 | Y54: =COUNTIFS(TU_DB[Year],$S54,TU_DB[Water Temp Flag],1) -> 719 | Z54: =COUNTIFS(TU_DB[Year],$S54,TU_DB[Dis: Not Reported],0) -> 678 | AA54: =COUNTIFS(TU_DB[Year],$S54,TU_DB[Water Level Flag],1) -> 728
B55: H4dZvxTdViejefqREn5k066JVZG3 | C55: Hiawatha | D55: =SUM(E55:J55) -> 37 | E55: =COUNTIFS(TUDB!$H$8:$H$2326,Use!$B55,TUDB!$F$8:$F$2326,Use!E$49) -> 0 | F55: =COUNTIFS(TUDB!$H$8:$H$2326,Use!$B55,TUDB!$F$8:$F$2326,Use!F$49) -> 0 | G55: =COUNTIFS(TUDB!$H$8:$H$2326,Use!$B55,TUDB!$F$8:$F$2326,Use!G$49) -> 9 | H55: =COUNTIFS(TUDB!$H$8:$H$2326,Use!$B55,TUDB!$F$8:$F$2326,Use!H$49) -> 6 | I55: =COUNTIFS(TUDB!$H$8:$H$2326,Use!$B55,TUDB!$F$8:$F$2326,Use!I$49) -> 12 | J55: =COUNTIFS(TUDB!$H$8:$H$2326,Use!$B55,TUDB!$F$8:$F$2326,Use!J$49) -> 10 | K55: =IF(AND(F55>0,SUM($E55)=0),1,0) -> 0 | L55: =IF(AND(G55>0,SUM($E55:F55)=0),1,0) -> 1 | M55: =IF(AND(H55>0,SUM($E55:G55)=0),1,0) -> 0 | N55: =IF(AND(I55>0,SUM($E55:H55)=0),1,0) -> 0 | O55: =IF(AND(J55>0,SUM($E55:I55)=0),1,0) -> 0 | S55: 2024 | T55: =COUNTIF(TU_DB[Year],$S55) -> 442 | U55: =COUNTIFS(TU_DB[Year],$S55,TU_DB[Source],"<>"&"") -> 419 | V55: =COUNTIFS(TU_DB[Year],$S55,TU_DB[[5n1 Flag ]],1) -> 397 | W55: =COUNTIFS(TU_DB[Year],$S55,TU_DB[[2n1 Flag ]],1) -> 390 | X55: =COUNTIFS(TU_DB[Year],$S55,TU_DB[Phos Flag],1) -> 358 | Y55: =COUNTIFS(TU_DB[Year],$S55,TU_DB[Water Temp Flag],1) -> 369 | Z55: =COUNTIFS(TU_DB[Year],$S55,TU_DB[Dis: Not Reported],0) -> 386 | AA55: =COUNTIFS(TU_DB[Year],$S55,TU_DB[Water Level Flag],1) -> 403
B56: GFBS1bSIACUVgSmsBlw0BYkB9i72 | C56: TU Staff | D56: =SUM(E56:J56) -> 31 | E56: =COUNTIFS(TUDB!$H$8:$H$2326,Use!$B56,TUDB!$F$8:$F$2326,Use!E$49) -> 0 | F56: =COUNTIFS(TUDB!$H$8:$H$2326,Use!$B56,TUDB!$F$8:$F$2326,Use!F$49) -> 0 | G56: =COUNTIFS(TUDB!$H$8:$H$2326,Use!$B56,TUDB!$F$8:$F$2326,Use!G$49) -> 0 | H56: =COUNTIFS(TUDB!$H$8:$H$2326,Use!$B56,TUDB!$F$8:$F$2326,Use!H$49) -> 13 | I56: =COUNTIFS(TUDB!$H$8:$H$2326,Use!$B56,TUDB!$F$8:$F$2326,Use!I$49) -> 9 | J56: =COUNTIFS(TUDB!$H$8:$H$2326,Use!$B56,TUDB!$F$8:$F$2326,Use!J$49) -> 9 | K56: =IF(AND(F56>0,SUM($E56)=0),1,0) -> 0 | L56: =IF(AND(G56>0,SUM($E56:F56)=0),1,0) -> 0 | M56: =IF(AND(H56>0,SUM($E56:G56)=0),1,0) -> 1 | N56: =IF(AND(I56>0,SUM($E56:H56)=0),1,0) -> 0 | O56: =IF(AND(J56>0,SUM($E56:I56)=0),1,0) -> 0 | S56: 2025 | T56: =COUNTIF(TU_DB[Year],$S56) -> 0 | U56: =COUNTIFS(TU_DB[Year],$S56,TU_DB[Source],"<>"&"") -> 0 | V56: =COUNTIFS(TU_DB[Year],$S56,TU_DB[[5n1 Flag ]],1) -> 0 | W56: =COUNTIFS(TU_DB[Year],$S56,TU_DB[[2n1 Flag ]],1) -> 0 | X56: =COUNTIFS(TU_DB[Year],$S56,TU_DB[Phos Flag],1) -> 0 | Y56: =COUNTIFS(TU_DB[Year],$S56,TU_DB[Water Temp Flag],1) -> 0 | Z56: =COUNTIFS(TU_DB[Year],$S56,TU_DB[Dis: Not Reported],0) -> 0 | AA56: =COUNTIFS(TU_DB[Year],$S56,TU_DB[Water Level Flag],1) -> 0
B57: wOnBJTAV2CZK06CRnr5oUK45EDv1 | C57: US FWS | D57: =SUM(E57:J57) -> 45 | E57: =COUNTIFS(TUDB!$H$8:$H$2326,Use!$B57,TUDB!$F$8:$F$2326,Use!E$49) -> 0 | F57: =COUNTIFS(TUDB!$H$8:$H$2326,Use!$B57,TUDB!$F$8:$F$2326,Use!F$49) -> 0 | G57: =COUNTIFS(TUDB!$H$8:$H$2326,Use!$B57,TUDB!$F$8:$F$2326,Use!G$49) -> 0 | H57: =COUNTIFS(TUDB!$H$8:$H$2326,Use!$B57,TUDB!$F$8:$F$2326,Use!H$49) -> 0 | I57: =COUNTIFS(TUDB!$H$8:$H$2326,Use!$B57,TUDB!$F$8:$F$2326,Use!I$49) -> 29 | J57: =COUNTIFS(TUDB!$H$8:$H$2326,Use!$B57,TUDB!$F$8:$F$2326,Use!J$49) -> 16 | K57: =IF(AND(F57>0,SUM($E57)=0),1,0) -> 0 | L57: =IF(AND(G57>0,SUM($E57:F57)=0),1,0) -> 0 | M57: =IF(AND(H57>0,SUM($E57:G57)=0),1,0) -> 0 | N57: =IF(AND(I57>0,SUM($E57:H57)=0),1,0) -> 1 | O57: =IF(AND(J57>0,SUM($E57:I57)=0),1,0) -> 0 | S57: 2026 | T57: =COUNTIF(TU_DB[Year],$S57) -> 0 | U57: =COUNTIFS(TU_DB[Year],$S57,TU_DB[Source],"<>"&"") -> 0 | V57: =COUNTIFS(TU_DB[Year],$S57,TU_DB[[5n1 Flag ]],1) -> 0 | W57: =COUNTIFS(TU_DB[Year],$S57,TU_DB[[2n1 Flag ]],1) -> 0 | X57: =COUNTIFS(TU_DB[Year],$S57,TU_DB[Phos Flag],1) -> 0 | Y57: =COUNTIFS(TU_DB[Year],$S57,TU_DB[Water Temp Flag],1) -> 0 | Z57: =COUNTIFS(TU_DB[Year],$S57,TU_DB[Dis: Not Reported],0) -> 0 | AA57: =COUNTIFS(TU_DB[Year],$S57,TU_DB[Water Level Flag],1) -> 0
B58: 4etfOHFOLNgXiWPM6KYa0g0En8C2 | C58: Spring Creeks | D58: =SUM(E58:J58) -> 1 | E58: =COUNTIFS(TUDB!$H$8:$H$2326,Use!$B58,TUDB!$F$8:$F$2326,Use!E$49) -> 0 | F58: =COUNTIFS(TUDB!$H$8:$H$2326,Use!$B58,TUDB!$F$8:$F$2326,Use!F$49) -> 0 | G58: =COUNTIFS(TUDB!$H$8:$H$2326,Use!$B58,TUDB!$F$8:$F$2326,Use!G$49) -> 0 | H58: =COUNTIFS(TUDB!$H$8:$H$2326,Use!$B58,TUDB!$F$8:$F$2326,Use!H$49) -> 0 | I58: =COUNTIFS(TUDB!$H$8:$H$2326,Use!$B58,TUDB!$F$8:$F$2326,Use!I$49) -> 0 | J58: =COUNTIFS(TUDB!$H$8:$H$2326,Use!$B58,TUDB!$F$8:$F$2326,Use!J$49) -> 1 | K58: =IF(AND(F58>0,SUM($E58)=0),1,0) -> 0 | L58: =IF(AND(G58>0,SUM($E58:F58)=0),1,0) -> 0 | M58: =IF(AND(H58>0,SUM($E58:G58)=0),1,0) -> 0 | N58: =IF(AND(I58>0,SUM($E58:H58)=0),1,0) -> 0 | O58: =IF(AND(J58>0,SUM($E58:I58)=0),1,0) -> 1 | S58: Sum 2020-23 | T58: =SUM(T51:T54) -> 1817 | U58: =SUM(U51:U53) -> 936 | V58: =SUM(V51:V53) -> 888 | W58: =SUM(W51:W53) -> 778 | X58: =SUM(X51:X53) -> 782 | Y58: =SUM(Y51:Y53) -> 765 | Z58: =SUM(Z51:Z53) -> 740 | AA58: =SUM(AA51:AA53) -> 844
B59: mMKogvdinjOuckB5tkMQrxnYO852 | C59: Kiap-TU-Wish | D59: =SUM(E59:J59) -> 13 | E59: =COUNTIFS(TUDB!$H$8:$H$2326,Use!$B59,TUDB!$F$8:$F$2326,Use!E$49) -> 0 | F59: =COUNTIFS(TUDB!$H$8:$H$2326,Use!$B59,TUDB!$F$8:$F$2326,Use!F$49) -> 0 | G59: =COUNTIFS(TUDB!$H$8:$H$2326,Use!$B59,TUDB!$F$8:$F$2326,Use!G$49) -> 0 | H59: =COUNTIFS(TUDB!$H$8:$H$2326,Use!$B59,TUDB!$F$8:$F$2326,Use!H$49) -> 5 | I59: =COUNTIFS(TUDB!$H$8:$H$2326,Use!$B59,TUDB!$F$8:$F$2326,Use!I$49) -> 3 | J59: =COUNTIFS(TUDB!$H$8:$H$2326,Use!$B59,TUDB!$F$8:$F$2326,Use!J$49) -> 5 | K59: =IF(AND(F59>0,SUM($E59)=0),1,0) -> 0 | L59: =IF(AND(G59>0,SUM($E59:F59)=0),1,0) -> 0 | M59: =IF(AND(H59>0,SUM($E59:G59)=0),1,0) -> 1 | N59: =IF(AND(I59>0,SUM($E59:H59)=0),1,0) -> 0 | O59: =IF(AND(J59>0,SUM($E59:I59)=0),1,0) -> 0 | S59: Application of total samples
B60: f7qMRlnlkOgrA1xpaxXrTTeRGWX2 | C60: Kiap-TU-Wish | D60: =SUM(E60:J60) -> 96 | E60: =COUNTIFS(TUDB!$H$8:$H$2326,Use!$B60,TUDB!$F$8:$F$2326,Use!E$49) -> 0 | F60: =COUNTIFS(TUDB!$H$8:$H$2326,Use!$B60,TUDB!$F$8:$F$2326,Use!F$49) -> 34 | G60: =COUNTIFS(TUDB!$H$8:$H$2326,Use!$B60,TUDB!$F$8:$F$2326,Use!G$49) -> 25 | H60: =COUNTIFS(TUDB!$H$8:$H$2326,Use!$B60,TUDB!$F$8:$F$2326,Use!H$49) -> 16 | I60: =COUNTIFS(TUDB!$H$8:$H$2326,Use!$B60,TUDB!$F$8:$F$2326,Use!I$49) -> 10 | J60: =COUNTIFS(TUDB!$H$8:$H$2326,Use!$B60,TUDB!$F$8:$F$2326,Use!J$49) -> 11 | K60: =IF(AND(F60>0,SUM($E60)=0),1,0) -> 1 | L60: =IF(AND(G60>0,SUM($E60:F60)=0),1,0) -> 0 | M60: =IF(AND(H60>0,SUM($E60:G60)=0),1,0) -> 0 | N60: =IF(AND(I60>0,SUM($E60:H60)=0),1,0) -> 0 | O60: =IF(AND(J60>0,SUM($E60:I60)=0),1,0) -> 0 | S60: 2020 | T60: - | U60: =U51/$T51 -> 0.81944444 | V60: =V51/$T51 -> 0.75 | W60: =W51/$T51 -> 0.61805556 | X60: =X51/$T51 -> 0.58333333 | Y60: =Y51/$T51 -> 0.65972222 | Z60: =Z51/$T51 -> 0.71527778 | AA60: =AA51/$T51 -> 0.81944444
B61: AFSRTEftiTe1HDjxTst1HuMIU1l1 | C61: Kiap-TU-Wish | D61: =SUM(E61:J61) -> 19 | E61: =COUNTIFS(TUDB!$H$8:$H$2326,Use!$B61,TUDB!$F$8:$F$2326,Use!E$49) -> 0 | F61: =COUNTIFS(TUDB!$H$8:$H$2326,Use!$B61,TUDB!$F$8:$F$2326,Use!F$49) -> 0 | G61: =COUNTIFS(TUDB!$H$8:$H$2326,Use!$B61,TUDB!$F$8:$F$2326,Use!G$49) -> 0 | H61: =COUNTIFS(TUDB!$H$8:$H$2326,Use!$B61,TUDB!$F$8:$F$2326,Use!H$49) -> 8 | I61: =COUNTIFS(TUDB!$H$8:$H$2326,Use!$B61,TUDB!$F$8:$F$2326,Use!I$49) -> 7 | J61: =COUNTIFS(TUDB!$H$8:$H$2326,Use!$B61,TUDB!$F$8:$F$2326,Use!J$49) -> 4 | K61: =IF(AND(F61>0,SUM($E61)=0),1,0) -> 0 | L61: =IF(AND(G61>0,SUM($E61:F61)=0),1,0) -> 0 | M61: =IF(AND(H61>0,SUM($E61:G61)=0),1,0) -> 1 | N61: =IF(AND(I61>0,SUM($E61:H61)=0),1,0) -> 0 | O61: =IF(AND(J61>0,SUM($E61:I61)=0),1,0) -> 0 | S61: 2021 | T61: - | U61: =U52/$T52 -> 0.93857494 | V61: =V52/$T52 -> 0.88697789 | W61: =W52/$T52 -> 0.75675676 | X61: =X52/$T52 -> 0.7960688 | Y61: =Y52/$T52 -> 0.74692875 | Z61: =Z52/$T52 -> 0.69041769 | AA61: =AA52/$T52 -> 0.82800983
B62: M7nEAKQN9zgYz7BtxGWTXq0oso12 | C62: Kiap-TU-Wish | D62: =SUM(E62:J62) -> 8 | E62: =COUNTIFS(TUDB!$H$8:$H$2326,Use!$B62,TUDB!$F$8:$F$2326,Use!E$49) -> 0 | F62: =COUNTIFS(TUDB!$H$8:$H$2326,Use!$B62,TUDB!$F$8:$F$2326,Use!F$49) -> 0 | G62: =COUNTIFS(TUDB!$H$8:$H$2326,Use!$B62,TUDB!$F$8:$F$2326,Use!G$49) -> 0 | H62: =COUNTIFS(TUDB!$H$8:$H$2326,Use!$B62,TUDB!$F$8:$F$2326,Use!H$49) -> 0 | I62: =COUNTIFS(TUDB!$H$8:$H$2326,Use!$B62,TUDB!$F$8:$F$2326,Use!I$49) -> 3 | J62: =COUNTIFS(TUDB!$H$8:$H$2326,Use!$B62,TUDB!$F$8:$F$2326,Use!J$49) -> 5 | K62: =IF(AND(F62>0,SUM($E62)=0),1,0) -> 0 | L62: =IF(AND(G62>0,SUM($E62:F62)=0),1,0) -> 0 | M62: =IF(AND(H62>0,SUM($E62:G62)=0),1,0) -> 0 | N62: =IF(AND(I62>0,SUM($E62:H62)=0),1,0) -> 1 | O62: =IF(AND(J62>0,SUM($E62:I62)=0),1,0) -> 0 | S62: 2022 | T62: - | U62: =U53/$T53 -> 0.94989107 | V62: =V53/$T53 -> 0.91285403 | W62: =W53/$T53 -> 0.83006536 | X62: =X53/$T53 -> 0.81481481 | Y62: =Y53/$T53 -> 0.79738562 | Z62: =Z53/$T53 -> 0.77559913 | AA62: =AA53/$T53 -> 0.84749455
B63: DKq8OLTYViaAQZeR9ADiCfs22M63 | C63: TU Staff | D63: =SUM(E63:J63) -> 87 | E63: =COUNTIFS(TUDB!$H$8:$H$2326,Use!$B63,TUDB!$F$8:$F$2326,Use!E$49) -> 0 | F63: =COUNTIFS(TUDB!$H$8:$H$2326,Use!$B63,TUDB!$F$8:$F$2326,Use!F$49) -> 0 | G63: =COUNTIFS(TUDB!$H$8:$H$2326,Use!$B63,TUDB!$F$8:$F$2326,Use!G$49) -> 0 | H63: =COUNTIFS(TUDB!$H$8:$H$2326,Use!$B63,TUDB!$F$8:$F$2326,Use!H$49) -> 0 | I63: =COUNTIFS(TUDB!$H$8:$H$2326,Use!$B63,TUDB!$F$8:$F$2326,Use!I$49) -> 44 | J63: =COUNTIFS(TUDB!$H$8:$H$2326,Use!$B63,TUDB!$F$8:$F$2326,Use!J$49) -> 43 | K63: =IF(AND(F63>0,SUM($E63)=0),1,0) -> 0 | L63: =IF(AND(G63>0,SUM($E63:F63)=0),1,0) -> 0 | M63: =IF(AND(H63>0,SUM($E63:G63)=0),1,0) -> 0 | N63: =IF(AND(I63>0,SUM($E63:H63)=0),1,0) -> 1 | O63: =IF(AND(J63>0,SUM($E63:I63)=0),1,0) -> 0 | S63: 2023 | T63: - | U63: =U54/$T54 -> 0.95291202 | V63: =V54/$T54 -> 0.88475836 | W63: =W54/$T54 -> 0.87484511 | X63: =X54/$T54 -> 0.82899628 | Y63: =Y54/$T54 -> 0.89095415 | Z63: =Z54/$T54 -> 0.8401487 | AA63: =AA54/$T54 -> 0.90210657
B64: k4Pe0JRs4tfWvDzxrT35e1UE1ce2 | C64: TCTU | D64: =SUM(E64:J64) -> 7 | E64: =COUNTIFS(TUDB!$H$8:$H$2326,Use!$B64,TUDB!$F$8:$F$2326,Use!E$49) -> 0 | F64: =COUNTIFS(TUDB!$H$8:$H$2326,Use!$B64,TUDB!$F$8:$F$2326,Use!F$49) -> 0 | G64: =COUNTIFS(TUDB!$H$8:$H$2326,Use!$B64,TUDB!$F$8:$F$2326,Use!G$49) -> 0 | H64: =COUNTIFS(TUDB!$H$8:$H$2326,Use!$B64,TUDB!$F$8:$F$2326,Use!H$49) -> 4 | I64: =COUNTIFS(TUDB!$H$8:$H$2326,Use!$B64,TUDB!$F$8:$F$2326,Use!I$49) -> 2 | J64: =COUNTIFS(TUDB!$H$8:$H$2326,Use!$B64,TUDB!$F$8:$F$2326,Use!J$49) -> 1 | K64: =IF(AND(F64>0,SUM($E64)=0),1,0) -> 0 | L64: =IF(AND(G64>0,SUM($E64:F64)=0),1,0) -> 0 | M64: =IF(AND(H64>0,SUM($E64:G64)=0),1,0) -> 1 | N64: =IF(AND(I64>0,SUM($E64:H64)=0),1,0) -> 0 | O64: =IF(AND(J64>0,SUM($E64:I64)=0),1,0) -> 0 | S64: 2024 | T64: - | U64: =U55/$T55 -> 0.9479638 | V64: =V55/$T55 -> 0.89819005 | W64: =W55/$T55 -> 0.88235294 | X64: =X55/$T55 -> 0.80995475 | Y64: =Y55/$T55 -> 0.83484163 | Z64: =Z55/$T55 -> 0.87330317 | AA64: =AA55/$T55 -> 0.91176471
B65: K0EjhOrGL4NGhPVbB1pKi320lLr2 | C65: TCTU | D65: =SUM(E65:J65) -> 32 | E65: =COUNTIFS(TUDB!$H$8:$H$2326,Use!$B65,TUDB!$F$8:$F$2326,Use!E$49) -> 0 | F65: =COUNTIFS(TUDB!$H$8:$H$2326,Use!$B65,TUDB!$F$8:$F$2326,Use!F$49) -> 0 | G65: =COUNTIFS(TUDB!$H$8:$H$2326,Use!$B65,TUDB!$F$8:$F$2326,Use!G$49) -> 0 | H65: =COUNTIFS(TUDB!$H$8:$H$2326,Use!$B65,TUDB!$F$8:$F$2326,Use!H$49) -> 14 | I65: =COUNTIFS(TUDB!$H$8:$H$2326,Use!$B65,TUDB!$F$8:$F$2326,Use!I$49) -> 12 | J65: =COUNTIFS(TUDB!$H$8:$H$2326,Use!$B65,TUDB!$F$8:$F$2326,Use!J$49) -> 6 | K65: =IF(AND(F65>0,SUM($E65)=0),1,0) -> 0 | L65: =IF(AND(G65>0,SUM($E65:F65)=0),1,0) -> 0 | M65: =IF(AND(H65>0,SUM($E65:G65)=0),1,0) -> 1 | N65: =IF(AND(I65>0,SUM($E65:H65)=0),1,0) -> 0 | O65: =IF(AND(J65>0,SUM($E65:I65)=0),1,0) -> 0 | S65: 2025 | T65: - | U65: =U56/$T56 -> #DIV/0! | V65: =V56/$T56 -> #DIV/0! | W65: =W56/$T56 -> #DIV/0! | X65: =X56/$T56 -> #DIV/0! | Y65: =Y56/$T56 -> #DIV/0! | Z65: =Z56/$T56 -> #DIV/0! | AA65: =AA56/$T56 -> #DIV/0!
B66: Us7gjDbTcVWrjDL157enRZKC9Tw1 | C66: Agency/University | D66: =SUM(E66:J66) -> 27 | E66: =COUNTIFS(TUDB!$H$8:$H$2326,Use!$B66,TUDB!$F$8:$F$2326,Use!E$49) -> 0 | F66: =COUNTIFS(TUDB!$H$8:$H$2326,Use!$B66,TUDB!$F$8:$F$2326,Use!F$49) -> 0 | G66: =COUNTIFS(TUDB!$H$8:$H$2326,Use!$B66,TUDB!$F$8:$F$2326,Use!G$49) -> 0 | H66: =COUNTIFS(TUDB!$H$8:$H$2326,Use!$B66,TUDB!$F$8:$F$2326,Use!H$49) -> 0 | I66: =COUNTIFS(TUDB!$H$8:$H$2326,Use!$B66,TUDB!$F$8:$F$2326,Use!I$49) -> 0 | J66: =COUNTIFS(TUDB!$H$8:$H$2326,Use!$B66,TUDB!$F$8:$F$2326,Use!J$49) -> 27 | K66: =IF(AND(F66>0,SUM($E66)=0),1,0) -> 0 | L66: =IF(AND(G66>0,SUM($E66:F66)=0),1,0) -> 0 | M66: =IF(AND(H66>0,SUM($E66:G66)=0),1,0) -> 0 | N66: =IF(AND(I66>0,SUM($E66:H66)=0),1,0) -> 0 | O66: =IF(AND(J66>0,SUM($E66:I66)=0),1,0) -> 1 | S66: 2026 | T66: - | U66: =U57/$T57 -> #DIV/0! | V66: =V57/$T57 -> #DIV/0! | W66: =W57/$T57 -> #DIV/0! | X66: =X57/$T57 -> #DIV/0! | Y66: =Y57/$T57 -> #DIV/0! | Z66: =Z57/$T57 -> #DIV/0! | AA66: =AA57/$T57 -> #DIV/0!
B67: jhGh651Hl7cRangRQ2zqYMCZHdv1 | C67: TU Staff | D67: =SUM(E67:J67) -> 120 | E67: =COUNTIFS(TUDB!$H$8:$H$2326,Use!$B67,TUDB!$F$8:$F$2326,Use!E$49) -> 0 | F67: =COUNTIFS(TUDB!$H$8:$H$2326,Use!$B67,TUDB!$F$8:$F$2326,Use!F$49) -> 0 | G67: =COUNTIFS(TUDB!$H$8:$H$2326,Use!$B67,TUDB!$F$8:$F$2326,Use!G$49) -> 0 | H67: =COUNTIFS(TUDB!$H$8:$H$2326,Use!$B67,TUDB!$F$8:$F$2326,Use!H$49) -> 0 | I67: =COUNTIFS(TUDB!$H$8:$H$2326,Use!$B67,TUDB!$F$8:$F$2326,Use!I$49) -> 78 | J67: =COUNTIFS(TUDB!$H$8:$H$2326,Use!$B67,TUDB!$F$8:$F$2326,Use!J$49) -> 42 | K67: =IF(AND(F67>0,SUM($E67)=0),1,0) -> 0 | L67: =IF(AND(G67>0,SUM($E67:F67)=0),1,0) -> 0 | M67: =IF(AND(H67>0,SUM($E67:G67)=0),1,0) -> 0 | N67: =IF(AND(I67>0,SUM($E67:H67)=0),1,0) -> 1 | O67: =IF(AND(J67>0,SUM($E67:I67)=0),1,0) -> 0 | S67: *Due to further editing of the database, the number of observations in 2019 does not match the number reported in the 2019 and 2020 annual reports.
B68: JEzwKJMSjwPIH1FrrCgr3SuUPRL2 | C68: n/a | D68: =SUM(E68:J68) -> 22 | E68: =COUNTIFS(TUDB!$H$8:$H$2326,Use!$B68,TUDB!$F$8:$F$2326,Use!E$49) -> 0 | F68: =COUNTIFS(TUDB!$H$8:$H$2326,Use!$B68,TUDB!$F$8:$F$2326,Use!F$49) -> 0 | G68: =COUNTIFS(TUDB!$H$8:$H$2326,Use!$B68,TUDB!$F$8:$F$2326,Use!G$49) -> 0 | H68: =COUNTIFS(TUDB!$H$8:$H$2326,Use!$B68,TUDB!$F$8:$F$2326,Use!H$49) -> 0 | I68: =COUNTIFS(TUDB!$H$8:$H$2326,Use!$B68,TUDB!$F$8:$F$2326,Use!I$49) -> 0 | J68: =COUNTIFS(TUDB!$H$8:$H$2326,Use!$B68,TUDB!$F$8:$F$2326,Use!J$49) -> 22 | K68: =IF(AND(F68>0,SUM($E68)=0),1,0) -> 0 | L68: =IF(AND(G68>0,SUM($E68:F68)=0),1,0) -> 0 | M68: =IF(AND(H68>0,SUM($E68:G68)=0),1,0) -> 0 | N68: =IF(AND(I68>0,SUM($E68:H68)=0),1,0) -> 0 | O68: =IF(AND(J68>0,SUM($E68:I68)=0),1,0) -> 1
B69: hU1HbEHHdaU8AhuDtzvdtGI8zvo2 | C69: n/a | D69: =SUM(E69:J69) -> 3 | E69: =COUNTIFS(TUDB!$H$8:$H$2326,Use!$B69,TUDB!$F$8:$F$2326,Use!E$49) -> 0 | F69: =COUNTIFS(TUDB!$H$8:$H$2326,Use!$B69,TUDB!$F$8:$F$2326,Use!F$49) -> 2 | G69: =COUNTIFS(TUDB!$H$8:$H$2326,Use!$B69,TUDB!$F$8:$F$2326,Use!G$49) -> 0 | H69: =COUNTIFS(TUDB!$H$8:$H$2326,Use!$B69,TUDB!$F$8:$F$2326,Use!H$49) -> 0 | I69: =COUNTIFS(TUDB!$H$8:$H$2326,Use!$B69,TUDB!$F$8:$F$2326,Use!I$49) -> 0 | J69: =COUNTIFS(TUDB!$H$8:$H$2326,Use!$B69,TUDB!$F$8:$F$2326,Use!J$49) -> 1 | K69: =IF(AND(F69>0,SUM($E69)=0),1,0) -> 1 | L69: =IF(AND(G69>0,SUM($E69:F69)=0),1,0) -> 0 | M69: =IF(AND(H69>0,SUM($E69:G69)=0),1,0) -> 0 | N69: =IF(AND(I69>0,SUM($E69:H69)=0),1,0) -> 0 | O69: =IF(AND(J69>0,SUM($E69:I69)=0),1,0) -> 0
B70: AJPHx36wPHSujaw4neovr2XeqWM2 | C70: North Bear | D70: =SUM(E70:J70) -> 1 | E70: =COUNTIFS(TUDB!$H$8:$H$2326,Use!$B70,TUDB!$F$8:$F$2326,Use!E$49) -> 0 | F70: =COUNTIFS(TUDB!$H$8:$H$2326,Use!$B70,TUDB!$F$8:$F$2326,Use!F$49) -> 0 | G70: =COUNTIFS(TUDB!$H$8:$H$2326,Use!$B70,TUDB!$F$8:$F$2326,Use!G$49) -> 0 | H70: =COUNTIFS(TUDB!$H$8:$H$2326,Use!$B70,TUDB!$F$8:$F$2326,Use!H$49) -> 0 | I70: =COUNTIFS(TUDB!$H$8:$H$2326,Use!$B70,TUDB!$F$8:$F$2326,Use!I$49) -> 0 | J70: =COUNTIFS(TUDB!$H$8:$H$2326,Use!$B70,TUDB!$F$8:$F$2326,Use!J$49) -> 1 | K70: =IF(AND(F70>0,SUM($E70)=0),1,0) -> 0 | L70: =IF(AND(G70>0,SUM($E70:F70)=0),1,0) -> 0 | M70: =IF(AND(H70>0,SUM($E70:G70)=0),1,0) -> 0 | N70: =IF(AND(I70>0,SUM($E70:H70)=0),1,0) -> 0 | O70: =IF(AND(J70>0,SUM($E70:I70)=0),1,0) -> 1 | S70: Chapter Participation
B71: igQ02m0WmNOTceL8xZhL27yXJP33 | C71: Coulee Region | D71: =SUM(E71:J71) -> 2 | E71: =COUNTIFS(TUDB!$H$8:$H$2326,Use!$B71,TUDB!$F$8:$F$2326,Use!E$49) -> 0 | F71: =COUNTIFS(TUDB!$H$8:$H$2326,Use!$B71,TUDB!$F$8:$F$2326,Use!F$49) -> 0 | G71: =COUNTIFS(TUDB!$H$8:$H$2326,Use!$B71,TUDB!$F$8:$F$2326,Use!G$49) -> 0 | H71: =COUNTIFS(TUDB!$H$8:$H$2326,Use!$B71,TUDB!$F$8:$F$2326,Use!H$49) -> 0 | I71: =COUNTIFS(TUDB!$H$8:$H$2326,Use!$B71,TUDB!$F$8:$F$2326,Use!I$49) -> 0 | J71: =COUNTIFS(TUDB!$H$8:$H$2326,Use!$B71,TUDB!$F$8:$F$2326,Use!J$49) -> 2 | K71: =IF(AND(F71>0,SUM($E71)=0),1,0) -> 0 | L71: =IF(AND(G71>0,SUM($E71:F71)=0),1,0) -> 0 | M71: =IF(AND(H71>0,SUM($E71:G71)=0),1,0) -> 0 | N71: =IF(AND(I71>0,SUM($E71:H71)=0),1,0) -> 0 | O71: =IF(AND(J71>0,SUM($E71:I71)=0),1,0) -> 1 | S71: Chapters | T71: =COUNTIF(AF76:AF90,">"&0) -> 10 | U71: total obs | V71: =SUM(U75,W75,Y75,AA75) -> 1039
B72: rEc6EuX5NUh3rTE9GqpcbwQ7zZF2 | C72: TU Staff | D72: =SUM(E72:J72) -> 1 | E72: =COUNTIFS(TUDB!$H$8:$H$2326,Use!$B72,TUDB!$F$8:$F$2326,Use!E$49) -> 0 | F72: =COUNTIFS(TUDB!$H$8:$H$2326,Use!$B72,TUDB!$F$8:$F$2326,Use!F$49) -> 0 | G72: =COUNTIFS(TUDB!$H$8:$H$2326,Use!$B72,TUDB!$F$8:$F$2326,Use!G$49) -> 0 | H72: =COUNTIFS(TUDB!$H$8:$H$2326,Use!$B72,TUDB!$F$8:$F$2326,Use!H$49) -> 0 | I72: =COUNTIFS(TUDB!$H$8:$H$2326,Use!$B72,TUDB!$F$8:$F$2326,Use!I$49) -> 0 | J72: =COUNTIFS(TUDB!$H$8:$H$2326,Use!$B72,TUDB!$F$8:$F$2326,Use!J$49) -> 1 | K72: =IF(AND(F72>0,SUM($E72)=0),1,0) -> 0 | L72: =IF(AND(G72>0,SUM($E72:F72)=0),1,0) -> 0 | M72: =IF(AND(H72>0,SUM($E72:G72)=0),1,0) -> 0 | N72: =IF(AND(I72>0,SUM($E72:H72)=0),1,0) -> 0 | O72: =IF(AND(J72>0,SUM($E72:I72)=0),1,0) -> 1
B73: dhoYk7GqqQe8fPLKfhTBIIYiuaY2 | C73: Iowa Driftless | D73: =SUM(E73:J73) -> 54 | E73: =COUNTIFS(TUDB!$H$8:$H$2326,Use!$B73,TUDB!$F$8:$F$2326,Use!E$49) -> 0 | F73: =COUNTIFS(TUDB!$H$8:$H$2326,Use!$B73,TUDB!$F$8:$F$2326,Use!F$49) -> 0 | G73: =COUNTIFS(TUDB!$H$8:$H$2326,Use!$B73,TUDB!$F$8:$F$2326,Use!G$49) -> 0 | H73: =COUNTIFS(TUDB!$H$8:$H$2326,Use!$B73,TUDB!$F$8:$F$2326,Use!H$49) -> 0 | I73: =COUNTIFS(TUDB!$H$8:$H$2326,Use!$B73,TUDB!$F$8:$F$2326,Use!I$49) -> 0 | J73: =COUNTIFS(TUDB!$H$8:$H$2326,Use!$B73,TUDB!$F$8:$F$2326,Use!J$49) -> 54 | K73: =IF(AND(F73>0,SUM($E73)=0),1,0) -> 0 | L73: =IF(AND(G73>0,SUM($E73:F73)=0),1,0) -> 0 | M73: =IF(AND(H73>0,SUM($E73:G73)=0),1,0) -> 0 | N73: =IF(AND(I73>0,SUM($E73:H73)=0),1,0) -> 0 | O73: =IF(AND(J73>0,SUM($E73:I73)=0),1,0) -> 1 | S73: Organizations | T73: 2020 | V73: 2021 | X73: 2022 | Z73: 2023 | AB73: 2024 | AD73: Total
B74: KCxLpWVzDWbVaMFSRHn2CmI0Qmi1 | C74: Agency/University | D74: =SUM(E74:J74) -> 10 | E74: =COUNTIFS(TUDB!$H$8:$H$2326,Use!$B74,TUDB!$F$8:$F$2326,Use!E$49) -> 0 | F74: =COUNTIFS(TUDB!$H$8:$H$2326,Use!$B74,TUDB!$F$8:$F$2326,Use!F$49) -> 0 | G74: =COUNTIFS(TUDB!$H$8:$H$2326,Use!$B74,TUDB!$F$8:$F$2326,Use!G$49) -> 0 | H74: =COUNTIFS(TUDB!$H$8:$H$2326,Use!$B74,TUDB!$F$8:$F$2326,Use!H$49) -> 0 | I74: =COUNTIFS(TUDB!$H$8:$H$2326,Use!$B74,TUDB!$F$8:$F$2326,Use!I$49) -> 0 | J74: =COUNTIFS(TUDB!$H$8:$H$2326,Use!$B74,TUDB!$F$8:$F$2326,Use!J$49) -> 10 | K74: =IF(AND(F74>0,SUM($E74)=0),1,0) -> 0 | L74: =IF(AND(G74>0,SUM($E74:F74)=0),1,0) -> 0 | M74: =IF(AND(H74>0,SUM($E74:G74)=0),1,0) -> 0 | N74: =IF(AND(I74>0,SUM($E74:H74)=0),1,0) -> 0 | O74: =IF(AND(J74>0,SUM($E74:I74)=0),1,0) -> 1 | T74: Members | U74: Member Observations | V74: Members | W74: Member Observations | X74: Members | Y74: Member Observations | Z74: Members | AA74: Member Observations | AB74: Members | AC74: Member Observations | AD74: Members | AE74: Member Observations
B75: o5zic4ETzdd5PipfQYi5lwBQ6dP2 | C75: n/a | D75: =SUM(E75:J75) -> 10 | E75: =COUNTIFS(TUDB!$H$8:$H$2326,Use!$B75,TUDB!$F$8:$F$2326,Use!E$49) -> 0 | F75: =COUNTIFS(TUDB!$H$8:$H$2326,Use!$B75,TUDB!$F$8:$F$2326,Use!F$49) -> 0 | G75: =COUNTIFS(TUDB!$H$8:$H$2326,Use!$B75,TUDB!$F$8:$F$2326,Use!G$49) -> 0 | H75: =COUNTIFS(TUDB!$H$8:$H$2326,Use!$B75,TUDB!$F$8:$F$2326,Use!H$49) -> 0 | I75: =COUNTIFS(TUDB!$H$8:$H$2326,Use!$B75,TUDB!$F$8:$F$2326,Use!I$49) -> 0 | J75: =COUNTIFS(TUDB!$H$8:$H$2326,Use!$B75,TUDB!$F$8:$F$2326,Use!J$49) -> 10 | K75: =IF(AND(F75>0,SUM($E75)=0),1,0) -> 0 | L75: =IF(AND(G75>0,SUM($E75:F75)=0),1,0) -> 0 | M75: =IF(AND(H75>0,SUM($E75:G75)=0),1,0) -> 0 | N75: =IF(AND(I75>0,SUM($E75:H75)=0),1,0) -> 0 | O75: =IF(AND(J75>0,SUM($E75:I75)=0),1,0) -> 1 | S75: TU Chapters | T75: =SUM(T76:T90) -> 18 | U75: =SUM(U76:U90) -> 103 | V75: =SUM(V76:V90) -> 47 | W75: =SUM(W76:W90) -> 367 | X75: =SUM(X76:X90) -> 43 | Y75: =SUM(Y76:Y90) -> 275 | Z75: =SUM(Z76:Z90) -> 48 | AA75: =SUM(AA76:AA90) -> 294 | ... AE75: =SUM(AE76:AE90) -> 1158
B76: VcgQ0dTFt9QvzcwNDAN6mP3Yn2H2 | C76: n/a | D76: =SUM(E76:J76) -> 5 | E76: =COUNTIFS(TUDB!$H$8:$H$2326,Use!$B76,TUDB!$F$8:$F$2326,Use!E$49) -> 0 | F76: =COUNTIFS(TUDB!$H$8:$H$2326,Use!$B76,TUDB!$F$8:$F$2326,Use!F$49) -> 0 | G76: =COUNTIFS(TUDB!$H$8:$H$2326,Use!$B76,TUDB!$F$8:$F$2326,Use!G$49) -> 0 | H76: =COUNTIFS(TUDB!$H$8:$H$2326,Use!$B76,TUDB!$F$8:$F$2326,Use!H$49) -> 0 | I76: =COUNTIFS(TUDB!$H$8:$H$2326,Use!$B76,TUDB!$F$8:$F$2326,Use!I$49) -> 0 | J76: =COUNTIFS(TUDB!$H$8:$H$2326,Use!$B76,TUDB!$F$8:$F$2326,Use!J$49) -> 5 | K76: =IF(AND(F76>0,SUM($E76)=0),1,0) -> 0 | L76: =IF(AND(G76>0,SUM($E76:F76)=0),1,0) -> 0 | M76: =IF(AND(H76>0,SUM($E76:G76)=0),1,0) -> 0 | N76: =IF(AND(I76>0,SUM($E76:H76)=0),1,0) -> 0 | O76: =IF(AND(J76>0,SUM($E76:I76)=0),1,0) -> 1 | S76: Aldo Leopold | T76: =COUNTIFS($C$50:$C$549,$S76,$F$50:$F$549,">"&0) -> 0 | U76: =SUMIFS($F$50:$F$549,$C$50:$C$549,$S76) -> 0 | V76: =COUNTIFS($C$50:$C$549,$S76,$G$50:$G$549,">"&0) -> 0 | W76: =SUMIFS($G$50:$G$549,$C$50:$C$549,$S76) -> 0 | X76: =COUNTIFS($C$50:$C$549,$S76,$H$50:$H$549,">"&0) -> 0 | Y76: =SUMIFS($H$50:$H$549,$C$50:$C$549,$S76) -> 0 | Z76: =COUNTIFS($C$50:$C$549,$S76,$I$50:$I$549,">"&0) -> 0 | AA76: =SUMIFS($I$50:$I$549,$C$50:$C$549,$S76) -> 0 | AB76: =COUNTIFS($C$50:$C$549,$S76,$J$49:$J$548,">"&0) -> 0 | AC76: =SUMIFS($J$50:$J$549,$C$50:$C$549,$S76) -> 0 | AD76: =SUM(V76,X76,Z76,AB76) -> 0 | AE76: =SUM(W76,Y76,AA76,AC76) -> 0 | AF76: =SUM(T76,V76,X76,Z76) -> 0
B77: 5RQuWak2yTbCLXixyDsqyBCU9CA2 | C77: Kiap-TU-Wish | D77: =SUM(E77:J77) -> 9 | E77: =COUNTIFS(TUDB!$H$8:$H$2326,Use!$B77,TUDB!$F$8:$F$2326,Use!E$49) -> 0 | F77: =COUNTIFS(TUDB!$H$8:$H$2326,Use!$B77,TUDB!$F$8:$F$2326,Use!F$49) -> 0 | G77: =COUNTIFS(TUDB!$H$8:$H$2326,Use!$B77,TUDB!$F$8:$F$2326,Use!G$49) -> 4 | H77: =COUNTIFS(TUDB!$H$8:$H$2326,Use!$B77,TUDB!$F$8:$F$2326,Use!H$49) -> 4 | I77: =COUNTIFS(TUDB!$H$8:$H$2326,Use!$B77,TUDB!$F$8:$F$2326,Use!I$49) -> 0 | J77: =COUNTIFS(TUDB!$H$8:$H$2326,Use!$B77,TUDB!$F$8:$F$2326,Use!J$49) -> 1 | K77: =IF(AND(F77>0,SUM($E77)=0),1,0) -> 0 | L77: =IF(AND(G77>0,SUM($E77:F77)=0),1,0) -> 1 | M77: =IF(AND(H77>0,SUM($E77:G77)=0),1,0) -> 0 | N77: =IF(AND(I77>0,SUM($E77:H77)=0),1,0) -> 0 | O77: =IF(AND(J77>0,SUM($E77:I77)=0),1,0) -> 0 | S77: Blackhawk | T77: =COUNTIFS($C$50:$C$549,$S77,$F$50:$F$549,">"&0) -> 0 | U77: =SUMIFS($F$50:$F$549,$C$50:$C$549,$S77) -> 0 | V77: =COUNTIFS($C$50:$C$549,$S77,$G$50:$G$549,">"&0) -> 0 | W77: =SUMIFS($G$50:$G$549,$C$50:$C$549,$S77) -> 0 | X77: =COUNTIFS($C$50:$C$549,$S77,$H$50:$H$549,">"&0) -> 0 | Y77: =SUMIFS($H$50:$H$549,$C$50:$C$549,$S77) -> 0 | Z77: =COUNTIFS($C$50:$C$549,$S77,$I$50:$I$549,">"&0) -> 0 | AA77: =SUMIFS($I$50:$I$549,$C$50:$C$549,$S77) -> 0 | AB77: =COUNTIFS($C$50:$C$549,$S77,$J$49:$J$548,">"&0) -> 0 | AC77: =SUMIFS($J$50:$J$549,$C$50:$C$549,$S77) -> 0 | AD77: =SUM(V77,X77,Z77,AB77) -> 0 | AE77: =SUM(W77,Y77,AA77,AC77) -> 0 | AF77: =SUM(T77,V77,X77,Z77) -> 0
B78: Qa8zCFJze3TAFBtRlCzL60f4jez2 | C78: Kiap-TU-Wish | D78: =SUM(E78:J78) -> 5 | E78: =COUNTIFS(TUDB!$H$8:$H$2326,Use!$B78,TUDB!$F$8:$F$2326,Use!E$49) -> 0 | F78: =COUNTIFS(TUDB!$H$8:$H$2326,Use!$B78,TUDB!$F$8:$F$2326,Use!F$49) -> 0 | G78: =COUNTIFS(TUDB!$H$8:$H$2326,Use!$B78,TUDB!$F$8:$F$2326,Use!G$49) -> 0 | H78: =COUNTIFS(TUDB!$H$8:$H$2326,Use!$B78,TUDB!$F$8:$F$2326,Use!H$49) -> 0 | I78: =COUNTIFS(TUDB!$H$8:$H$2326,Use!$B78,TUDB!$F$8:$F$2326,Use!I$49) -> 4 | J78: =COUNTIFS(TUDB!$H$8:$H$2326,Use!$B78,TUDB!$F$8:$F$2326,Use!J$49) -> 1 | K78: =IF(AND(F78>0,SUM($E78)=0),1,0) -> 0 | L78: =IF(AND(G78>0,SUM($E78:F78)=0),1,0) -> 0 | M78: =IF(AND(H78>0,SUM($E78:G78)=0),1,0) -> 0 | N78: =IF(AND(I78>0,SUM($E78:H78)=0),1,0) -> 1 | O78: =IF(AND(J78>0,SUM($E78:I78)=0),1,0) -> 0 | S78: Coulee Region | T78: =COUNTIFS($C$50:$C$549,$S78,$F$50:$F$549,">"&0) -> 0 | U78: =SUMIFS($F$50:$F$549,$C$50:$C$549,$S78) -> 0 | V78: =COUNTIFS($C$50:$C$549,$S78,$G$50:$G$549,">"&0) -> 1 | W78: =SUMIFS($G$50:$G$549,$C$50:$C$549,$S78) -> 8 | X78: =COUNTIFS($C$50:$C$549,$S78,$H$50:$H$549,">"&0) -> 0 | Y78: =SUMIFS($H$50:$H$549,$C$50:$C$549,$S78) -> 0 | Z78: =COUNTIFS($C$50:$C$549,$S78,$I$50:$I$549,">"&0) -> 1 | AA78: =SUMIFS($I$50:$I$549,$C$50:$C$549,$S78) -> 12 | AB78: =COUNTIFS($C$50:$C$549,$S78,$J$49:$J$548,">"&0) -> 2 | AC78: =SUMIFS($J$50:$J$549,$C$50:$C$549,$S78) -> 5 | AD78: =SUM(V78,X78,Z78,AB78) -> 4 | AE78: =SUM(W78,Y78,AA78,AC78) -> 25 | AF78: =SUM(T78,V78,X78,Z78) -> 2
B79: amwdiMGvitOCDTrNZryY37rt5Vw1 | C79: Coulee Region | D79: =SUM(E79:J79) -> 3 | E79: =COUNTIFS(TUDB!$H$8:$H$2326,Use!$B79,TUDB!$F$8:$F$2326,Use!E$49) -> 0 | F79: =COUNTIFS(TUDB!$H$8:$H$2326,Use!$B79,TUDB!$F$8:$F$2326,Use!F$49) -> 0 | G79: =COUNTIFS(TUDB!$H$8:$H$2326,Use!$B79,TUDB!$F$8:$F$2326,Use!G$49) -> 0 | H79: =COUNTIFS(TUDB!$H$8:$H$2326,Use!$B79,TUDB!$F$8:$F$2326,Use!H$49) -> 0 | I79: =COUNTIFS(TUDB!$H$8:$H$2326,Use!$B79,TUDB!$F$8:$F$2326,Use!I$49) -> 0 | J79: =COUNTIFS(TUDB!$H$8:$H$2326,Use!$B79,TUDB!$F$8:$F$2326,Use!J$49) -> 3 | K79: =IF(AND(F79>0,SUM($E79)=0),1,0) -> 0 | L79: =IF(AND(G79>0,SUM($E79:F79)=0),1,0) -> 0 | M79: =IF(AND(H79>0,SUM($E79:G79)=0),1,0) -> 0 | N79: =IF(AND(I79>0,SUM($E79:H79)=0),1,0) -> 0 | O79: =IF(AND(J79>0,SUM($E79:I79)=0),1,0) -> 1 | S79: Harry & Laura Nohr | T79: =COUNTIFS($C$50:$C$549,$S79,$F$50:$F$549,">"&0) -> 0 | U79: =SUMIFS($F$50:$F$549,$C$50:$C$549,$S79) -> 0 | V79: =COUNTIFS($C$50:$C$549,$S79,$G$50:$G$549,">"&0) -> 0 | W79: =SUMIFS($G$50:$G$549,$C$50:$C$549,$S79) -> 0 | X79: =COUNTIFS($C$50:$C$549,$S79,$H$50:$H$549,">"&0) -> 0 | Y79: =SUMIFS($H$50:$H$549,$C$50:$C$549,$S79) -> 0 | Z79: =COUNTIFS($C$50:$C$549,$S79,$I$50:$I$549,">"&0) -> 0 | AA79: =SUMIFS($I$50:$I$549,$C$50:$C$549,$S79) -> 0 | AB79: =COUNTIFS($C$50:$C$549,$S79,$J$49:$J$548,">"&0) -> 0 | AC79: =SUMIFS($J$50:$J$549,$C$50:$C$549,$S79) -> 0 | AD79: =SUM(V79,X79,Z79,AB79) -> 0 | AE79: =SUM(W79,Y79,AA79,AC79) -> 0 | AF79: =SUM(T79,V79,X79,Z79) -> 0
B80: ODZAZt42ngf0K8HRsQw4BSqkli42 | C80: Agency/University | D80: =SUM(E80:J80) -> 69 | E80: =COUNTIFS(TUDB!$H$8:$H$2326,Use!$B80,TUDB!$F$8:$F$2326,Use!E$49) -> 0 | F80: =COUNTIFS(TUDB!$H$8:$H$2326,Use!$B80,TUDB!$F$8:$F$2326,Use!F$49) -> 0 | G80: =COUNTIFS(TUDB!$H$8:$H$2326,Use!$B80,TUDB!$F$8:$F$2326,Use!G$49) -> 0 | H80: =COUNTIFS(TUDB!$H$8:$H$2326,Use!$B80,TUDB!$F$8:$F$2326,Use!H$49) -> 8 | I80: =COUNTIFS(TUDB!$H$8:$H$2326,Use!$B80,TUDB!$F$8:$F$2326,Use!I$49) -> 49 | J80: =COUNTIFS(TUDB!$H$8:$H$2326,Use!$B80,TUDB!$F$8:$F$2326,Use!J$49) -> 12 | K80: =IF(AND(F80>0,SUM($E80)=0),1,0) -> 0 | L80: =IF(AND(G80>0,SUM($E80:F80)=0),1,0) -> 0 | M80: =IF(AND(H80>0,SUM($E80:G80)=0),1,0) -> 1 | N80: =IF(AND(I80>0,SUM($E80:H80)=0),1,0) -> 0 | O80: =IF(AND(J80>0,SUM($E80:I80)=0),1,0) -> 0 | S80: Hiawatha | T80: =COUNTIFS($C$50:$C$549,$S80,$F$50:$F$549,">"&0) -> 1 | U80: =SUMIFS($F$50:$F$549,$C$50:$C$549,$S80) -> 2 | V80: =COUNTIFS($C$50:$C$549,$S80,$G$50:$G$549,">"&0) -> 11 | W80: =SUMIFS($G$50:$G$549,$C$50:$C$549,$S80) -> 122 | X80: =COUNTIFS($C$50:$C$549,$S80,$H$50:$H$549,">"&0) -> 9 | Y80: =SUMIFS($H$50:$H$549,$C$50:$C$549,$S80) -> 75 | Z80: =COUNTIFS($C$50:$C$549,$S80,$I$50:$I$549,">"&0) -> 10 | AA80: =SUMIFS($I$50:$I$549,$C$50:$C$549,$S80) -> 118 | AB80: =COUNTIFS($C$50:$C$549,$S80,$J$49:$J$548,">"&0) -> 3 | AC80: =SUMIFS($J$50:$J$549,$C$50:$C$549,$S80) -> 116 | AD80: =SUM(V80,X80,Z80,AB80) -> 33 | AE80: =SUM(W80,Y80,AA80,AC80) -> 431 | AF80: =SUM(T80,V80,X80,Z80) -> 31
B81: b5Q5MWoIy9OOBrhn8HbZMPPsGST2 | C81: Agency/University | D81: =SUM(E81:J81) -> 55 | E81: =COUNTIFS(TUDB!$H$8:$H$2326,Use!$B81,TUDB!$F$8:$F$2326,Use!E$49) -> 0 | F81: =COUNTIFS(TUDB!$H$8:$H$2326,Use!$B81,TUDB!$F$8:$F$2326,Use!F$49) -> 9 | G81: =COUNTIFS(TUDB!$H$8:$H$2326,Use!$B81,TUDB!$F$8:$F$2326,Use!G$49) -> 16 | H81: =COUNTIFS(TUDB!$H$8:$H$2326,Use!$B81,TUDB!$F$8:$F$2326,Use!H$49) -> 12 | I81: =COUNTIFS(TUDB!$H$8:$H$2326,Use!$B81,TUDB!$F$8:$F$2326,Use!I$49) -> 17 | J81: =COUNTIFS(TUDB!$H$8:$H$2326,Use!$B81,TUDB!$F$8:$F$2326,Use!J$49) -> 1 | K81: =IF(AND(F81>0,SUM($E81)=0),1,0) -> 1 | L81: =IF(AND(G81>0,SUM($E81:F81)=0),1,0) -> 0 | M81: =IF(AND(H81>0,SUM($E81:G81)=0),1,0) -> 0 | N81: =IF(AND(I81>0,SUM($E81:H81)=0),1,0) -> 0 | O81: =IF(AND(J81>0,SUM($E81:I81)=0),1,0) -> 0 | S81: Iowa Driftless | T81: =COUNTIFS($C$50:$C$549,$S81,$F$50:$F$549,">"&0) -> 1 | U81: =SUMIFS($F$50:$F$549,$C$50:$C$549,$S81) -> 1 | V81: =COUNTIFS($C$50:$C$549,$S81,$G$50:$G$549,">"&0) -> 1 | W81: =SUMIFS($G$50:$G$549,$C$50:$C$549,$S81) -> 3 | X81: =COUNTIFS($C$50:$C$549,$S81,$H$50:$H$549,">"&0) -> 1 | Y81: =SUMIFS($H$50:$H$549,$C$50:$C$549,$S81) -> 1 | Z81: =COUNTIFS($C$50:$C$549,$S81,$I$50:$I$549,">"&0) -> 5 | AA81: =SUMIFS($I$50:$I$549,$C$50:$C$549,$S81) -> 10 | AB81: =COUNTIFS($C$50:$C$549,$S81,$J$49:$J$548,">"&0) -> 2 | AC81: =SUMIFS($J$50:$J$549,$C$50:$C$549,$S81) -> 54 | AD81: =SUM(V81,X81,Z81,AB81) -> 9 | AE81: =SUM(W81,Y81,AA81,AC81) -> 68 | AF81: =SUM(T81,V81,X81,Z81) -> 8
B82: 2XHDjq71v6QuQ2mR0YUjDtciKej1 | C82: Oak Brook | D82: =SUM(E82:J82) -> 3 | E82: =COUNTIFS(TUDB!$H$8:$H$2326,Use!$B82,TUDB!$F$8:$F$2326,Use!E$49) -> 0 | F82: =COUNTIFS(TUDB!$H$8:$H$2326,Use!$B82,TUDB!$F$8:$F$2326,Use!F$49) -> 0 | G82: =COUNTIFS(TUDB!$H$8:$H$2326,Use!$B82,TUDB!$F$8:$F$2326,Use!G$49) -> 0 | H82: =COUNTIFS(TUDB!$H$8:$H$2326,Use!$B82,TUDB!$F$8:$F$2326,Use!H$49) -> 0 | I82: =COUNTIFS(TUDB!$H$8:$H$2326,Use!$B82,TUDB!$F$8:$F$2326,Use!I$49) -> 1 | J82: =COUNTIFS(TUDB!$H$8:$H$2326,Use!$B82,TUDB!$F$8:$F$2326,Use!J$49) -> 2 | K82: =IF(AND(F82>0,SUM($E82)=0),1,0) -> 0 | L82: =IF(AND(G82>0,SUM($E82:F82)=0),1,0) -> 0 | M82: =IF(AND(H82>0,SUM($E82:G82)=0),1,0) -> 0 | N82: =IF(AND(I82>0,SUM($E82:H82)=0),1,0) -> 1 | O82: =IF(AND(J82>0,SUM($E82:I82)=0),1,0) -> 0 | S82: Kiap-TU-Wish | T82: =COUNTIFS($C$50:$C$549,$S82,$F$50:$F$549,">"&0) -> 10 | U82: =SUMIFS($F$50:$F$549,$C$50:$C$549,$S82) -> 77 | V82: =COUNTIFS($C$50:$C$549,$S82,$G$50:$G$549,">"&0) -> 13 | W82: =SUMIFS($G$50:$G$549,$C$50:$C$549,$S82) -> 105 | X82: =COUNTIFS($C$50:$C$549,$S82,$H$50:$H$549,">"&0) -> 9 | Y82: =SUMIFS($H$50:$H$549,$C$50:$C$549,$S82) -> 59 | Z82: =COUNTIFS($C$50:$C$549,$S82,$I$50:$I$549,">"&0) -> 9 | AA82: =SUMIFS($I$50:$I$549,$C$50:$C$549,$S82) -> 51 | AB82: =COUNTIFS($C$50:$C$549,$S82,$J$49:$J$548,">"&0) -> 8 | AC82: =SUMIFS($J$50:$J$549,$C$50:$C$549,$S82) -> 41 | AD82: =SUM(V82,X82,Z82,AB82) -> 39 | AE82: =SUM(W82,Y82,AA82,AC82) -> 256 | AF82: =SUM(T82,V82,X82,Z82) -> 41
B83: xYjaaWkJX4fiKpH7uMmSdC5YE0h2 | C83: Oak Brook | D83: =SUM(E83:J83) -> 6 | E83: =COUNTIFS(TUDB!$H$8:$H$2326,Use!$B83,TUDB!$F$8:$F$2326,Use!E$49) -> 0 | F83: =COUNTIFS(TUDB!$H$8:$H$2326,Use!$B83,TUDB!$F$8:$F$2326,Use!F$49) -> 2 | G83: =COUNTIFS(TUDB!$H$8:$H$2326,Use!$B83,TUDB!$F$8:$F$2326,Use!G$49) -> 0 | H83: =COUNTIFS(TUDB!$H$8:$H$2326,Use!$B83,TUDB!$F$8:$F$2326,Use!H$49) -> 0 | I83: =COUNTIFS(TUDB!$H$8:$H$2326,Use!$B83,TUDB!$F$8:$F$2326,Use!I$49) -> 2 | J83: =COUNTIFS(TUDB!$H$8:$H$2326,Use!$B83,TUDB!$F$8:$F$2326,Use!J$49) -> 2 | K83: =IF(AND(F83>0,SUM($E83)=0),1,0) -> 1 | L83: =IF(AND(G83>0,SUM($E83:F83)=0),1,0) -> 0 | M83: =IF(AND(H83>0,SUM($E83:G83)=0),1,0) -> 0 | N83: =IF(AND(I83>0,SUM($E83:H83)=0),1,0) -> 0 | O83: =IF(AND(J83>0,SUM($E83:I83)=0),1,0) -> 0 | S83: Lee Wulff | T83: =COUNTIFS($C$50:$C$549,$S83,$F$50:$F$549,">"&0) -> 0 | U83: =SUMIFS($F$50:$F$549,$C$50:$C$549,$S83) -> 0 | V83: =COUNTIFS($C$50:$C$549,$S83,$G$50:$G$549,">"&0) -> 0 | W83: =SUMIFS($G$50:$G$549,$C$50:$C$549,$S83) -> 0 | X83: =COUNTIFS($C$50:$C$549,$S83,$H$50:$H$549,">"&0) -> 0 | Y83: =SUMIFS($H$50:$H$549,$C$50:$C$549,$S83) -> 0 | Z83: =COUNTIFS($C$50:$C$549,$S83,$I$50:$I$549,">"&0) -> 0 | AA83: =SUMIFS($I$50:$I$549,$C$50:$C$549,$S83) -> 0 | AB83: =COUNTIFS($C$50:$C$549,$S83,$J$49:$J$548,">"&0) -> 0 | AC83: =SUMIFS($J$50:$J$549,$C$50:$C$549,$S83) -> 0 | AD83: =SUM(V83,X83,Z83,AB83) -> 0 | AE83: =SUM(W83,Y83,AA83,AC83) -> 0 | AF83: =SUM(T83,V83,X83,Z83) -> 0
B84: uAwaWPXw7rTLrlVyZQyBEHYE6SU2 | C84: TU Staff | D84: =SUM(E84:J84) -> 3 | E84: =COUNTIFS(TUDB!$H$8:$H$2326,Use!$B84,TUDB!$F$8:$F$2326,Use!E$49) -> 0 | F84: =COUNTIFS(TUDB!$H$8:$H$2326,Use!$B84,TUDB!$F$8:$F$2326,Use!F$49) -> 0 | G84: =COUNTIFS(TUDB!$H$8:$H$2326,Use!$B84,TUDB!$F$8:$F$2326,Use!G$49) -> 0 | H84: =COUNTIFS(TUDB!$H$8:$H$2326,Use!$B84,TUDB!$F$8:$F$2326,Use!H$49) -> 0 | I84: =COUNTIFS(TUDB!$H$8:$H$2326,Use!$B84,TUDB!$F$8:$F$2326,Use!I$49) -> 0 | J84: =COUNTIFS(TUDB!$H$8:$H$2326,Use!$B84,TUDB!$F$8:$F$2326,Use!J$49) -> 3 | K84: =IF(AND(F84>0,SUM($E84)=0),1,0) -> 0 | L84: =IF(AND(G84>0,SUM($E84:F84)=0),1,0) -> 0 | M84: =IF(AND(H84>0,SUM($E84:G84)=0),1,0) -> 0 | N84: =IF(AND(I84>0,SUM($E84:H84)=0),1,0) -> 0 | O84: =IF(AND(J84>0,SUM($E84:I84)=0),1,0) -> 1 | S84: North Bear | T84: =COUNTIFS($C$50:$C$549,$S84,$F$50:$F$549,">"&0) -> 0 | U84: =SUMIFS($F$50:$F$549,$C$50:$C$549,$S84) -> 0 | V84: =COUNTIFS($C$50:$C$549,$S84,$G$50:$G$549,">"&0) -> 0 | W84: =SUMIFS($G$50:$G$549,$C$50:$C$549,$S84) -> 0 | X84: =COUNTIFS($C$50:$C$549,$S84,$H$50:$H$549,">"&0) -> 0 | Y84: =SUMIFS($H$50:$H$549,$C$50:$C$549,$S84) -> 0 | Z84: =COUNTIFS($C$50:$C$549,$S84,$I$50:$I$549,">"&0) -> 0 | AA84: =SUMIFS($I$50:$I$549,$C$50:$C$549,$S84) -> 0 | AB84: =COUNTIFS($C$50:$C$549,$S84,$J$49:$J$548,">"&0) -> 1 | AC84: =SUMIFS($J$50:$J$549,$C$50:$C$549,$S84) -> 1 | AD84: =SUM(V84,X84,Z84,AB84) -> 1 | AE84: =SUM(W84,Y84,AA84,AC84) -> 1 | AF84: =SUM(T84,V84,X84,Z84) -> 0
B85: DqUTUWfFKyMmrCUAWxsXy8KRt4c2 | C85: TU Staff | D85: =SUM(E85:J85) -> 3 | E85: =COUNTIFS(TUDB!$H$8:$H$2326,Use!$B85,TUDB!$F$8:$F$2326,Use!E$49) -> 0 | F85: =COUNTIFS(TUDB!$H$8:$H$2326,Use!$B85,TUDB!$F$8:$F$2326,Use!F$49) -> 0 | G85: =COUNTIFS(TUDB!$H$8:$H$2326,Use!$B85,TUDB!$F$8:$F$2326,Use!G$49) -> 0 | H85: =COUNTIFS(TUDB!$H$8:$H$2326,Use!$B85,TUDB!$F$8:$F$2326,Use!H$49) -> 0 | I85: =COUNTIFS(TUDB!$H$8:$H$2326,Use!$B85,TUDB!$F$8:$F$2326,Use!I$49) -> 0 | J85: =COUNTIFS(TUDB!$H$8:$H$2326,Use!$B85,TUDB!$F$8:$F$2326,Use!J$49) -> 3 | K85: =IF(AND(F85>0,SUM($E85)=0),1,0) -> 0 | L85: =IF(AND(G85>0,SUM($E85:F85)=0),1,0) -> 0 | M85: =IF(AND(H85>0,SUM($E85:G85)=0),1,0) -> 0 | N85: =IF(AND(I85>0,SUM($E85:H85)=0),1,0) -> 0 | O85: =IF(AND(J85>0,SUM($E85:I85)=0),1,0) -> 1 | S85: Oak Brook | T85: =COUNTIFS($C$50:$C$549,$S85,$F$50:$F$549,">"&0) -> 1 | U85: =SUMIFS($F$50:$F$549,$C$50:$C$549,$S85) -> 2 | V85: =COUNTIFS($C$50:$C$549,$S85,$G$50:$G$549,">"&0) -> 1 | W85: =SUMIFS($G$50:$G$549,$C$50:$C$549,$S85) -> 1 | X85: =COUNTIFS($C$50:$C$549,$S85,$H$50:$H$549,">"&0) -> 1 | Y85: =SUMIFS($H$50:$H$549,$C$50:$C$549,$S85) -> 3 | Z85: =COUNTIFS($C$50:$C$549,$S85,$I$50:$I$549,">"&0) -> 2 | AA85: =SUMIFS($I$50:$I$549,$C$50:$C$549,$S85) -> 3 | AB85: =COUNTIFS($C$50:$C$549,$S85,$J$49:$J$548,">"&0) -> 2 | AC85: =SUMIFS($J$50:$J$549,$C$50:$C$549,$S85) -> 4 | AD85: =SUM(V85,X85,Z85,AB85) -> 6 | AE85: =SUM(W85,Y85,AA85,AC85) -> 11 | AF85: =SUM(T85,V85,X85,Z85) -> 5
B86: Tlazf0NRE2UoPEjeblvnepAUAAF3 | C86: TCTU | D86: =SUM(E86:J86) -> 4 | E86: =COUNTIFS(TUDB!$H$8:$H$2326,Use!$B86,TUDB!$F$8:$F$2326,Use!E$49) -> 0 | F86: =COUNTIFS(TUDB!$H$8:$H$2326,Use!$B86,TUDB!$F$8:$F$2326,Use!F$49) -> 0 | G86: =COUNTIFS(TUDB!$H$8:$H$2326,Use!$B86,TUDB!$F$8:$F$2326,Use!G$49) -> 0 | H86: =COUNTIFS(TUDB!$H$8:$H$2326,Use!$B86,TUDB!$F$8:$F$2326,Use!H$49) -> 3 | I86: =COUNTIFS(TUDB!$H$8:$H$2326,Use!$B86,TUDB!$F$8:$F$2326,Use!I$49) -> 0 | J86: =COUNTIFS(TUDB!$H$8:$H$2326,Use!$B86,TUDB!$F$8:$F$2326,Use!J$49) -> 1 | K86: =IF(AND(F86>0,SUM($E86)=0),1,0) -> 0 | L86: =IF(AND(G86>0,SUM($E86:F86)=0),1,0) -> 0 | M86: =IF(AND(H86>0,SUM($E86:G86)=0),1,0) -> 1 | N86: =IF(AND(I86>0,SUM($E86:H86)=0),1,0) -> 0 | O86: =IF(AND(J86>0,SUM($E86:I86)=0),1,0) -> 0 | S86: Southern Wisconsin | T86: =COUNTIFS($C$50:$C$549,$S86,$F$50:$F$549,">"&0) -> 1 | U86: =SUMIFS($F$50:$F$549,$C$50:$C$549,$S86) -> 1 | V86: =COUNTIFS($C$50:$C$549,$S86,$G$50:$G$549,">"&0) -> 2 | W86: =SUMIFS($G$50:$G$549,$C$50:$C$549,$S86) -> 8 | X86: =COUNTIFS($C$50:$C$549,$S86,$H$50:$H$549,">"&0) -> 0 | Y86: =SUMIFS($H$50:$H$549,$C$50:$C$549,$S86) -> 0 | Z86: =COUNTIFS($C$50:$C$549,$S86,$I$50:$I$549,">"&0) -> 0 | AA86: =SUMIFS($I$50:$I$549,$C$50:$C$549,$S86) -> 0 | AB86: =COUNTIFS($C$50:$C$549,$S86,$J$49:$J$548,">"&0) -> 0 | AC86: =SUMIFS($J$50:$J$549,$C$50:$C$549,$S86) -> 0 | AD86: =SUM(V86,X86,Z86,AB86) -> 2 | AE86: =SUM(W86,Y86,AA86,AC86) -> 8 | AF86: =SUM(T86,V86,X86,Z86) -> 3
B87: p4yu7gSyP5X56i8vIVA6AxqyR5D2 | C87: Iowa Driftless | D87: =SUM(E87:J87) -> 4 | E87: =COUNTIFS(TUDB!$H$8:$H$2326,Use!$B87,TUDB!$F$8:$F$2326,Use!E$49) -> 0 | F87: =COUNTIFS(TUDB!$H$8:$H$2326,Use!$B87,TUDB!$F$8:$F$2326,Use!F$49) -> 0 | G87: =COUNTIFS(TUDB!$H$8:$H$2326,Use!$B87,TUDB!$F$8:$F$2326,Use!G$49) -> 0 | H87: =COUNTIFS(TUDB!$H$8:$H$2326,Use!$B87,TUDB!$F$8:$F$2326,Use!H$49) -> 0 | I87: =COUNTIFS(TUDB!$H$8:$H$2326,Use!$B87,TUDB!$F$8:$F$2326,Use!I$49) -> 4 | J87: =COUNTIFS(TUDB!$H$8:$H$2326,Use!$B87,TUDB!$F$8:$F$2326,Use!J$49) -> 0 | K87: =IF(AND(F87>0,SUM($E87)=0),1,0) -> 0 | L87: =IF(AND(G87>0,SUM($E87:F87)=0),1,0) -> 0 | M87: =IF(AND(H87>0,SUM($E87:G87)=0),1,0) -> 0 | N87: =IF(AND(I87>0,SUM($E87:H87)=0),1,0) -> 1 | O87: =IF(AND(J87>0,SUM($E87:I87)=0),1,0) -> 0 | S87: Spring Creeks | T87: =COUNTIFS($C$50:$C$549,$S87,$F$50:$F$549,">"&0) -> 0 | U87: =SUMIFS($F$50:$F$549,$C$50:$C$549,$S87) -> 0 | V87: =COUNTIFS($C$50:$C$549,$S87,$G$50:$G$549,">"&0) -> 1 | W87: =SUMIFS($G$50:$G$549,$C$50:$C$549,$S87) -> 1 | X87: =COUNTIFS($C$50:$C$549,$S87,$H$50:$H$549,">"&0) -> 1 | Y87: =SUMIFS($H$50:$H$549,$C$50:$C$549,$S87) -> 5 | Z87: =COUNTIFS($C$50:$C$549,$S87,$I$50:$I$549,">"&0) -> 0 | AA87: =SUMIFS($I$50:$I$549,$C$50:$C$549,$S87) -> 0 | AB87: =COUNTIFS($C$50:$C$549,$S87,$J$49:$J$548,">"&0) -> 1 | AC87: =SUMIFS($J$50:$J$549,$C$50:$C$549,$S87) -> 1 | AD87: =SUM(V87,X87,Z87,AB87) -> 3 | AE87: =SUM(W87,Y87,AA87,AC87) -> 7 | AF87: =SUM(T87,V87,X87,Z87) -> 2
B88: XjAeVUSAWwR6YIfiotq1aVO8G8e2 | C88: Agency/University | D88: =SUM(E88:J88) -> 7 | E88: =COUNTIFS(TUDB!$H$8:$H$2326,Use!$B88,TUDB!$F$8:$F$2326,Use!E$49) -> 0 | F88: =COUNTIFS(TUDB!$H$8:$H$2326,Use!$B88,TUDB!$F$8:$F$2326,Use!F$49) -> 0 | G88: =COUNTIFS(TUDB!$H$8:$H$2326,Use!$B88,TUDB!$F$8:$F$2326,Use!G$49) -> 0 | H88: =COUNTIFS(TUDB!$H$8:$H$2326,Use!$B88,TUDB!$F$8:$F$2326,Use!H$49) -> 0 | I88: =COUNTIFS(TUDB!$H$8:$H$2326,Use!$B88,TUDB!$F$8:$F$2326,Use!I$49) -> 7 | J88: =COUNTIFS(TUDB!$H$8:$H$2326,Use!$B88,TUDB!$F$8:$F$2326,Use!J$49) -> 0 | K88: =IF(AND(F88>0,SUM($E88)=0),1,0) -> 0 | L88: =IF(AND(G88>0,SUM($E88:F88)=0),1,0) -> 0 | M88: =IF(AND(H88>0,SUM($E88:G88)=0),1,0) -> 0 | N88: =IF(AND(I88>0,SUM($E88:H88)=0),1,0) -> 1 | O88: =IF(AND(J88>0,SUM($E88:I88)=0),1,0) -> 0 | S88: Twin Cities (TCTU) | T88: =COUNTIFS($C$50:$C$549,"TCTU",$F$50:$F$549,">"&0) -> 1 | U88: =SUMIFS($F$50:$F$549,$C$50:$C$549,"TCTU") -> 4 | V88: =COUNTIFS($C$50:$C$549,"TCTU",$G$50:$G$549,">"&0) -> 17 | W88: =SUMIFS($G$50:$G$549,$C$50:$C$549,"TCTU") -> 119 | X88: =COUNTIFS($C$50:$C$549,"TCTU",$H$50:$H$549,">"&0) -> 21 | Y88: =SUMIFS($H$50:$H$549,$C$50:$C$549,"TCTU") -> 112 | Z88: =COUNTIFS($C$50:$C$549,"TCTU",$I$50:$I$549,">"&0) -> 20 | AA88: =SUMIFS($I$50:$I$549,$C$50:$C$549,"TCTU") -> 95 | AB88: =COUNTIFS($C$50:$C$549,$S88,$J$49:$J$548,">"&0) -> 0 | AC88: =SUMIFS($J$50:$J$549,$C$50:$C$549,$S88) -> 0 | AD88: =SUM(V88,X88,Z88,AB88) -> 58 | AE88: =SUM(W88,Y88,AA88,AC88) -> 326 | AF88: =SUM(T88,V88,X88,Z88) -> 59
B89: JXs3JH9frrZM0ZdjV8qFZY0NE3P2 | C89: Kiap-TU-Wish | D89: =SUM(E89:J89) -> 20 | E89: =COUNTIFS(TUDB!$H$8:$H$2326,Use!$B89,TUDB!$F$8:$F$2326,Use!E$49) -> 0 | F89: =COUNTIFS(TUDB!$H$8:$H$2326,Use!$B89,TUDB!$F$8:$F$2326,Use!F$49) -> 1 | G89: =COUNTIFS(TUDB!$H$8:$H$2326,Use!$B89,TUDB!$F$8:$F$2326,Use!G$49) -> 6 | H89: =COUNTIFS(TUDB!$H$8:$H$2326,Use!$B89,TUDB!$F$8:$F$2326,Use!H$49) -> 5 | I89: =COUNTIFS(TUDB!$H$8:$H$2326,Use!$B89,TUDB!$F$8:$F$2326,Use!I$49) -> 8 | J89: =COUNTIFS(TUDB!$H$8:$H$2326,Use!$B89,TUDB!$F$8:$F$2326,Use!J$49) -> 0 | K89: =IF(AND(F89>0,SUM($E89)=0),1,0) -> 1 | L89: =IF(AND(G89>0,SUM($E89:F89)=0),1,0) -> 0 | M89: =IF(AND(H89>0,SUM($E89:G89)=0),1,0) -> 0 | N89: =IF(AND(I89>0,SUM($E89:H89)=0),1,0) -> 0 | O89: =IF(AND(J89>0,SUM($E89:I89)=0),1,0) -> 0 | S89: Wisconsin Clear Waters | T89: =COUNTIFS($C$50:$C$549,$S89,$F$50:$F$549,">"&0) -> 2 | U89: =SUMIFS($F$50:$F$549,$C$50:$C$549,$S89) -> 10 | V89: =COUNTIFS($C$50:$C$549,$S89,$G$50:$G$549,">"&0) -> 0 | W89: =SUMIFS($G$50:$G$549,$C$50:$C$549,$S89) -> 0 | X89: =COUNTIFS($C$50:$C$549,$S89,$H$50:$H$549,">"&0) -> 1 | Y89: =SUMIFS($H$50:$H$549,$C$50:$C$549,$S89) -> 20 | Z89: =COUNTIFS($C$50:$C$549,$S89,$I$50:$I$549,">"&0) -> 1 | AA89: =SUMIFS($I$50:$I$549,$C$50:$C$549,$S89) -> 5 | AB89: =COUNTIFS($C$50:$C$549,$S89,$J$49:$J$548,">"&0) -> 0 | AC89: =SUMIFS($J$50:$J$549,$C$50:$C$549,$S89) -> 0 | AD89: =SUM(V89,X89,Z89,AB89) -> 2 | AE89: =SUM(W89,Y89,AA89,AC89) -> 25 | AF89: =SUM(T89,V89,X89,Z89) -> 4
B90: bmxwg22L1hbfcniR6e24vEvKK5u2 | C90: TCTU | D90: =SUM(E90:J90) -> 1 | E90: =COUNTIFS(TUDB!$H$8:$H$2326,Use!$B90,TUDB!$F$8:$F$2326,Use!E$49) -> 0 | F90: =COUNTIFS(TUDB!$H$8:$H$2326,Use!$B90,TUDB!$F$8:$F$2326,Use!F$49) -> 0 | G90: =COUNTIFS(TUDB!$H$8:$H$2326,Use!$B90,TUDB!$F$8:$F$2326,Use!G$49) -> 0 | H90: =COUNTIFS(TUDB!$H$8:$H$2326,Use!$B90,TUDB!$F$8:$F$2326,Use!H$49) -> 0 | I90: =COUNTIFS(TUDB!$H$8:$H$2326,Use!$B90,TUDB!$F$8:$F$2326,Use!I$49) -> 1 | J90: =COUNTIFS(TUDB!$H$8:$H$2326,Use!$B90,TUDB!$F$8:$F$2326,Use!J$49) -> 0 | K90: =IF(AND(F90>0,SUM($E90)=0),1,0) -> 0 | L90: =IF(AND(G90>0,SUM($E90:F90)=0),1,0) -> 0 | M90: =IF(AND(H90>0,SUM($E90:G90)=0),1,0) -> 0 | N90: =IF(AND(I90>0,SUM($E90:H90)=0),1,0) -> 1 | O90: =IF(AND(J90>0,SUM($E90:I90)=0),1,0) -> 0 | S90: Win-Cres | T90: =COUNTIFS($C$50:$C$549,$S90,$F$50:$F$549,">"&0) -> 1 | U90: =SUMIFS($F$50:$F$549,$C$50:$C$549,$S90) -> 6 | V90: =COUNTIFS($C$50:$C$549,$S90,$G$50:$G$549,">"&0) -> 0 | W90: =SUMIFS($G$50:$G$549,$C$50:$C$549,$S90) -> 0 | X90: =COUNTIFS($C$50:$C$549,$S90,$H$50:$H$549,">"&0) -> 0 | Y90: =SUMIFS($H$50:$H$549,$C$50:$C$549,$S90) -> 0 | Z90: =COUNTIFS($C$50:$C$549,$S90,$I$50:$I$549,">"&0) -> 0 | AA90: =SUMIFS($I$50:$I$549,$C$50:$C$549,$S90) -> 0 | AB90: =COUNTIFS($C$50:$C$549,$S90,$J$49:$J$548,">"&0) -> 0 | AC90: =SUMIFS($J$50:$J$549,$C$50:$C$549,$S90) -> 0 | AD90: =SUM(V90,X90,Z90,AB90) -> 0 | AE90: =SUM(W90,Y90,AA90,AC90) -> 0 | AF90: =SUM(T90,V90,X90,Z90) -> 1
B91: 1lKBGtvFeSbEVNlbIt9EhqtOO7u2 | C91: Unknown | D91: =SUM(E91:J91) -> 39 | E91: =COUNTIFS(TUDB!$H$8:$H$2326,Use!$B91,TUDB!$F$8:$F$2326,Use!E$49) -> 0 | F91: =COUNTIFS(TUDB!$H$8:$H$2326,Use!$B91,TUDB!$F$8:$F$2326,Use!F$49) -> 0 | G91: =COUNTIFS(TUDB!$H$8:$H$2326,Use!$B91,TUDB!$F$8:$F$2326,Use!G$49) -> 0 | H91: =COUNTIFS(TUDB!$H$8:$H$2326,Use!$B91,TUDB!$F$8:$F$2326,Use!H$49) -> 0 | I91: =COUNTIFS(TUDB!$H$8:$H$2326,Use!$B91,TUDB!$F$8:$F$2326,Use!I$49) -> 39 | J91: =COUNTIFS(TUDB!$H$8:$H$2326,Use!$B91,TUDB!$F$8:$F$2326,Use!J$49) -> 0 | K91: =IF(AND(F91>0,SUM($E91)=0),1,0) -> 0 | L91: =IF(AND(G91>0,SUM($E91:F91)=0),1,0) -> 0 | M91: =IF(AND(H91>0,SUM($E91:G91)=0),1,0) -> 0 | N91: =IF(AND(I91>0,SUM($E91:H91)=0),1,0) -> 1 | O91: =IF(AND(J91>0,SUM($E91:I91)=0),1,0) -> 0 | S91: Other | T91: =SUM(T92:T95) -> 3 | U91: =SUM(U92:U95) -> 27 | V91: =SUM(V92:V95) -> 6 | W91: =SUM(W92:W95) -> 34 | X91: =SUM(X92:X95) -> 18 | Y91: =SUM(Y92:Y95) -> 184 | Z91: =SUM(Z92:Z95) -> 32 | AA91: =SUM(AA92:AA95) -> 484 | AB91: =COUNTIFS($C$50:$C$549,$S91,$J$49:$J$548,">"&0) -> 0 | AC91: =SUMIFS($J$50:$J$549,$C$50:$C$549,$S91) -> 0 | AD91: =SUM(V91,X91,Z91,AB91) -> 56 | AE91: =SUM(W91,Y91,AA91,AC91) -> 702
B92: MZ8CvOB6bBeEPjwpBrk2zCVH7bk2 | C92: TCTU | D92: =SUM(E92:J92) -> 8 | E92: =COUNTIFS(TUDB!$H$8:$H$2326,Use!$B92,TUDB!$F$8:$F$2326,Use!E$49) -> 0 | F92: =COUNTIFS(TUDB!$H$8:$H$2326,Use!$B92,TUDB!$F$8:$F$2326,Use!F$49) -> 0 | G92: =COUNTIFS(TUDB!$H$8:$H$2326,Use!$B92,TUDB!$F$8:$F$2326,Use!G$49) -> 0 | H92: =COUNTIFS(TUDB!$H$8:$H$2326,Use!$B92,TUDB!$F$8:$F$2326,Use!H$49) -> 0 | I92: =COUNTIFS(TUDB!$H$8:$H$2326,Use!$B92,TUDB!$F$8:$F$2326,Use!I$49) -> 8 | J92: =COUNTIFS(TUDB!$H$8:$H$2326,Use!$B92,TUDB!$F$8:$F$2326,Use!J$49) -> 0 | K92: =IF(AND(F92>0,SUM($E92)=0),1,0) -> 0 | L92: =IF(AND(G92>0,SUM($E92:F92)=0),1,0) -> 0 | M92: =IF(AND(H92>0,SUM($E92:G92)=0),1,0) -> 0 | N92: =IF(AND(I92>0,SUM($E92:H92)=0),1,0) -> 1 | O92: =IF(AND(J92>0,SUM($E92:I92)=0),1,0) -> 0 | S92: TU Staff | T92: =COUNTIFS($C$50:$C$549,$S92,$F$50:$F$549,">"&0) -> 1 | U92: =SUMIFS($F$50:$F$549,$C$50:$C$549,$S92) -> 1 | V92: =COUNTIFS($C$50:$C$549,$S92,$G$50:$G$549,">"&0) -> 0 | W92: =SUMIFS($G$50:$G$549,$C$50:$C$549,$S92) -> 0 | X92: =COUNTIFS($C$50:$C$549,$S92,$H$50:$H$549,">"&0) -> 2 | Y92: =SUMIFS($H$50:$H$549,$C$50:$C$549,$S92) -> 15 | Z92: =COUNTIFS($C$50:$C$549,$S92,$I$50:$I$549,">"&0) -> 7 | AA92: =SUMIFS($I$50:$I$549,$C$50:$C$549,$S92) -> 265 | AB92: =COUNTIFS($C$50:$C$549,$S92,$J$49:$J$548,">"&0) -> 6 | AC92: =SUMIFS($J$50:$J$549,$C$50:$C$549,$S92) -> 101 | AD92: =SUM(V92,X92,Z92,AB92) -> 15 | AE92: =SUM(W92,Y92,AA92,AC92) -> 381
B93: 7fp9eoNK1RTW0XUKFpn9oieJe1W2 | C93: TU Staff | D93: =SUM(E93:J93) -> 14 | E93: =COUNTIFS(TUDB!$H$8:$H$2326,Use!$B93,TUDB!$F$8:$F$2326,Use!E$49) -> 0 | F93: =COUNTIFS(TUDB!$H$8:$H$2326,Use!$B93,TUDB!$F$8:$F$2326,Use!F$49) -> 0 | G93: =COUNTIFS(TUDB!$H$8:$H$2326,Use!$B93,TUDB!$F$8:$F$2326,Use!G$49) -> 0 | H93: =COUNTIFS(TUDB!$H$8:$H$2326,Use!$B93,TUDB!$F$8:$F$2326,Use!H$49) -> 2 | I93: =COUNTIFS(TUDB!$H$8:$H$2326,Use!$B93,TUDB!$F$8:$F$2326,Use!I$49) -> 12 | J93: =COUNTIFS(TUDB!$H$8:$H$2326,Use!$B93,TUDB!$F$8:$F$2326,Use!J$49) -> 0 | K93: =IF(AND(F93>0,SUM($E93)=0),1,0) -> 0 | L93: =IF(AND(G93>0,SUM($E93:F93)=0),1,0) -> 0 | M93: =IF(AND(H93>0,SUM($E93:G93)=0),1,0) -> 1 | N93: =IF(AND(I93>0,SUM($E93:H93)=0),1,0) -> 0 | O93: =IF(AND(J93>0,SUM($E93:I93)=0),1,0) -> 0 | S93: Kinni Corridor Collaborative | T93: =COUNTIFS($C$50:$C$549,$S93,$F$50:$F$549,">"&0) -> 0 | U93: =SUMIFS($F$50:$F$549,$C$50:$C$549,$S93) -> 0 | V93: =COUNTIFS($C$50:$C$549,$S93,$G$50:$G$549,">"&0) -> 0 | W93: =SUMIFS($G$50:$G$549,$C$50:$C$549,$S93) -> 0 | X93: =COUNTIFS($C$50:$C$549,$S93,$H$50:$H$549,">"&0) -> 3 | Y93: =SUMIFS($H$50:$H$549,$C$50:$C$549,$S93) -> 122 | Z93: =COUNTIFS($C$50:$C$549,$S93,$I$50:$I$549,">"&0) -> 4 | AA93: =SUMIFS($I$50:$I$549,$C$50:$C$549,$S93) -> 46 | AB93: =COUNTIFS($C$50:$C$549,$S93,$J$49:$J$548,">"&0) -> 0 | AC93: =SUMIFS($J$50:$J$549,$C$50:$C$549,$S93) -> 0 | AD93: =SUM(V93,X93,Z93,AB93) -> 7 | AE93: =SUM(W93,Y93,AA93,AC93) -> 168
B94: cJZVjbWzjsRfePMeXT5aflRnGhh1 | C94: TCTU | D94: =SUM(E94:J94) -> 12 | E94: =COUNTIFS(TUDB!$H$8:$H$2326,Use!$B94,TUDB!$F$8:$F$2326,Use!E$49) -> 0 | F94: =COUNTIFS(TUDB!$H$8:$H$2326,Use!$B94,TUDB!$F$8:$F$2326,Use!F$49) -> 0 | G94: =COUNTIFS(TUDB!$H$8:$H$2326,Use!$B94,TUDB!$F$8:$F$2326,Use!G$49) -> 5 | H94: =COUNTIFS(TUDB!$H$8:$H$2326,Use!$B94,TUDB!$F$8:$F$2326,Use!H$49) -> 2 | I94: =COUNTIFS(TUDB!$H$8:$H$2326,Use!$B94,TUDB!$F$8:$F$2326,Use!I$49) -> 5 | J94: =COUNTIFS(TUDB!$H$8:$H$2326,Use!$B94,TUDB!$F$8:$F$2326,Use!J$49) -> 0 | K94: =IF(AND(F94>0,SUM($E94)=0),1,0) -> 0 | L94: =IF(AND(G94>0,SUM($E94:F94)=0),1,0) -> 1 | M94: =IF(AND(H94>0,SUM($E94:G94)=0),1,0) -> 0 | N94: =IF(AND(I94>0,SUM($E94:H94)=0),1,0) -> 0 | O94: =IF(AND(J94>0,SUM($E94:I94)=0),1,0) -> 0 | S94: Agency/University* | T94: =COUNTIFS($C$50:$C$549,$S94,$F$50:$F$549,">"&0) -> 2 | U94: =SUMIFS($F$50:$F$549,$C$50:$C$549,$S94) -> 26 | V94: =COUNTIFS($C$50:$C$549,$S94,$G$50:$G$549,">"&0) -> 1 | W94: =SUMIFS($G$50:$G$549,$C$50:$C$549,$S94) -> 16 | X94: =COUNTIFS($C$50:$C$549,$S94,$H$50:$H$549,">"&0) -> 7 | Y94: =SUMIFS($H$50:$H$549,$C$50:$C$549,$S94) -> 33 | Z94: =COUNTIFS($C$50:$C$549,$S94,$I$50:$I$549,">"&0) -> 7 | AA94: =SUMIFS($I$50:$I$549,$C$50:$C$549,$S94) -> 101 | AB94: =COUNTIFS($C$50:$C$549,$S94,$J$49:$J$548,">"&0) -> 4 | AC94: =SUMIFS($J$50:$J$549,$C$50:$C$549,$S94) -> 50 | AD94: =SUM(V94,X94,Z94,AB94) -> 19 | AE94: =SUM(W94,Y94,AA94,AC94) -> 200
B95: 5sE4Yqji6nO193vOJEyE5nVk3V33 | C95: TCTU | D95: =SUM(E95:J95) -> 11 | E95: =COUNTIFS(TUDB!$H$8:$H$2326,Use!$B95,TUDB!$F$8:$F$2326,Use!E$49) -> 0 | F95: =COUNTIFS(TUDB!$H$8:$H$2326,Use!$B95,TUDB!$F$8:$F$2326,Use!F$49) -> 0 | G95: =COUNTIFS(TUDB!$H$8:$H$2326,Use!$B95,TUDB!$F$8:$F$2326,Use!G$49) -> 4 | H95: =COUNTIFS(TUDB!$H$8:$H$2326,Use!$B95,TUDB!$F$8:$F$2326,Use!H$49) -> 0 | I95: =COUNTIFS(TUDB!$H$8:$H$2326,Use!$B95,TUDB!$F$8:$F$2326,Use!I$49) -> 7 | J95: =COUNTIFS(TUDB!$H$8:$H$2326,Use!$B95,TUDB!$F$8:$F$2326,Use!J$49) -> 0 | K95: =IF(AND(F95>0,SUM($E95)=0),1,0) -> 0 | L95: =IF(AND(G95>0,SUM($E95:F95)=0),1,0) -> 1 | M95: =IF(AND(H95>0,SUM($E95:G95)=0),1,0) -> 0 | N95: =IF(AND(I95>0,SUM($E95:H95)=0),1,0) -> 0 | O95: =IF(AND(J95>0,SUM($E95:I95)=0),1,0) -> 0 | S95: Unknown | T95: =COUNTIFS($C$50:$C$549,$S95,$F$50:$F$549,">"&0) -> 0 | U95: =SUMIFS($F$50:$F$549,$C$50:$C$549,$S95) -> 0 | V95: =COUNTIFS($C$50:$C$549,$S95,$G$50:$G$549,">"&0) -> 5 | W95: =SUMIFS($G$50:$G$549,$C$50:$C$549,$S95) -> 18 | X95: =COUNTIFS($C$50:$C$549,$S95,$H$50:$H$549,">"&0) -> 6 | Y95: =SUMIFS($H$50:$H$549,$C$50:$C$549,$S95) -> 14 | Z95: =COUNTIFS($C$50:$C$549,$S95,$I$50:$I$549,">"&0) -> 14 | AA95: =SUMIFS($I$50:$I$549,$C$50:$C$549,$S95) -> 72 | AB95: =COUNTIFS($C$50:$C$549,$S95,$J$49:$J$548,">"&0) -> 1 | AC95: =SUMIFS($J$50:$J$549,$C$50:$C$549,$S95) -> 7 | AD95: =SUM(V95,X95,Z95,AB95) -> 26 | AE95: =SUM(W95,Y95,AA95,AC95) -> 111
B96: sV8r8QoTpTQ81023RxB7QRB9qBu1 | C96: TCTU | D96: =SUM(E96:J96) -> 9 | E96: =COUNTIFS(TUDB!$H$8:$H$2326,Use!$B96,TUDB!$F$8:$F$2326,Use!E$49) -> 0 | F96: =COUNTIFS(TUDB!$H$8:$H$2326,Use!$B96,TUDB!$F$8:$F$2326,Use!F$49) -> 0 | G96: =COUNTIFS(TUDB!$H$8:$H$2326,Use!$B96,TUDB!$F$8:$F$2326,Use!G$49) -> 1 | H96: =COUNTIFS(TUDB!$H$8:$H$2326,Use!$B96,TUDB!$F$8:$F$2326,Use!H$49) -> 4 | I96: =COUNTIFS(TUDB!$H$8:$H$2326,Use!$B96,TUDB!$F$8:$F$2326,Use!I$49) -> 4 | J96: =COUNTIFS(TUDB!$H$8:$H$2326,Use!$B96,TUDB!$F$8:$F$2326,Use!J$49) -> 0 | K96: =IF(AND(F96>0,SUM($E96)=0),1,0) -> 0 | L96: =IF(AND(G96>0,SUM($E96:F96)=0),1,0) -> 1 | M96: =IF(AND(H96>0,SUM($E96:G96)=0),1,0) -> 0 | N96: =IF(AND(I96>0,SUM($E96:H96)=0),1,0) -> 0 | O96: =IF(AND(J96>0,SUM($E96:I96)=0),1,0) -> 0 | S96: *Includes staff from Minnesota DNR, Wisconsin DNR, USFWS, Saint Marys University, Upper Iowa University, Holmen Middle School
B97: MHFdkCj8zqhw6MGszjwZYx49QR22 | C97: TCTU | D97: =SUM(E97:J97) -> 10 | E97: =COUNTIFS(TUDB!$H$8:$H$2326,Use!$B97,TUDB!$F$8:$F$2326,Use!E$49) -> 0 | F97: =COUNTIFS(TUDB!$H$8:$H$2326,Use!$B97,TUDB!$F$8:$F$2326,Use!F$49) -> 0 | G97: =COUNTIFS(TUDB!$H$8:$H$2326,Use!$B97,TUDB!$F$8:$F$2326,Use!G$49) -> 0 | H97: =COUNTIFS(TUDB!$H$8:$H$2326,Use!$B97,TUDB!$F$8:$F$2326,Use!H$49) -> 4 | I97: =COUNTIFS(TUDB!$H$8:$H$2326,Use!$B97,TUDB!$F$8:$F$2326,Use!I$49) -> 6 | J97: =COUNTIFS(TUDB!$H$8:$H$2326,Use!$B97,TUDB!$F$8:$F$2326,Use!J$49) -> 0 | K97: =IF(AND(F97>0,SUM($E97)=0),1,0) -> 0 | L97: =IF(AND(G97>0,SUM($E97:F97)=0),1,0) -> 0 | M97: =IF(AND(H97>0,SUM($E97:G97)=0),1,0) -> 1 | N97: =IF(AND(I97>0,SUM($E97:H97)=0),1,0) -> 0 | O97: =IF(AND(J97>0,SUM($E97:I97)=0),1,0) -> 0
B98: jr4xjZvRQFP5TMTbzZ3WFt91JbZ2 | C98: TCTU | D98: =SUM(E98:J98) -> 6 | E98: =COUNTIFS(TUDB!$H$8:$H$2326,Use!$B98,TUDB!$F$8:$F$2326,Use!E$49) -> 0 | F98: =COUNTIFS(TUDB!$H$8:$H$2326,Use!$B98,TUDB!$F$8:$F$2326,Use!F$49) -> 0 | G98: =COUNTIFS(TUDB!$H$8:$H$2326,Use!$B98,TUDB!$F$8:$F$2326,Use!G$49) -> 0 | H98: =COUNTIFS(TUDB!$H$8:$H$2326,Use!$B98,TUDB!$F$8:$F$2326,Use!H$49) -> 0 | I98: =COUNTIFS(TUDB!$H$8:$H$2326,Use!$B98,TUDB!$F$8:$F$2326,Use!I$49) -> 6 | J98: =COUNTIFS(TUDB!$H$8:$H$2326,Use!$B98,TUDB!$F$8:$F$2326,Use!J$49) -> 0 | K98: =IF(AND(F98>0,SUM($E98)=0),1,0) -> 0 | L98: =IF(AND(G98>0,SUM($E98:F98)=0),1,0) -> 0 | M98: =IF(AND(H98>0,SUM($E98:G98)=0),1,0) -> 0 | N98: =IF(AND(I98>0,SUM($E98:H98)=0),1,0) -> 1 | O98: =IF(AND(J98>0,SUM($E98:I98)=0),1,0) -> 0
B99: wQCfNJcgkMPI4m2bsIm33lNVmqH2 | C99: TCTU | D99: =SUM(E99:J99) -> 8 | E99: =COUNTIFS(TUDB!$H$8:$H$2326,Use!$B99,TUDB!$F$8:$F$2326,Use!E$49) -> 0 | F99: =COUNTIFS(TUDB!$H$8:$H$2326,Use!$B99,TUDB!$F$8:$F$2326,Use!F$49) -> 0 | G99: =COUNTIFS(TUDB!$H$8:$H$2326,Use!$B99,TUDB!$F$8:$F$2326,Use!G$49) -> 1 | H99: =COUNTIFS(TUDB!$H$8:$H$2326,Use!$B99,TUDB!$F$8:$F$2326,Use!H$49) -> 3 | I99: =COUNTIFS(TUDB!$H$8:$H$2326,Use!$B99,TUDB!$F$8:$F$2326,Use!I$49) -> 4 | J99: =COUNTIFS(TUDB!$H$8:$H$2326,Use!$B99,TUDB!$F$8:$F$2326,Use!J$49) -> 0 | K99: =IF(AND(F99>0,SUM($E99)=0),1,0) -> 0 | L99: =IF(AND(G99>0,SUM($E99:F99)=0),1,0) -> 1 | M99: =IF(AND(H99>0,SUM($E99:G99)=0),1,0) -> 0 | N99: =IF(AND(I99>0,SUM($E99:H99)=0),1,0) -> 0 | O99: =IF(AND(J99>0,SUM($E99:I99)=0),1,0) -> 0 | S99: Obs per TU Chapter Area
B100: qg0Gw2Z5bFP7xIvHpN2bfZB65d62 | C100: TCTU | D100: =SUM(E100:J100) -> 6 | E100: =COUNTIFS(TUDB!$H$8:$H$2326,Use!$B100,TUDB!$F$8:$F$2326,Use!E$49) -> 0 | F100: =COUNTIFS(TUDB!$H$8:$H$2326,Use!$B100,TUDB!$F$8:$F$2326,Use!F$49) -> 0 | G100: =COUNTIFS(TUDB!$H$8:$H$2326,Use!$B100,TUDB!$F$8:$F$2326,Use!G$49) -> 0 | H100: =COUNTIFS(TUDB!$H$8:$H$2326,Use!$B100,TUDB!$F$8:$F$2326,Use!H$49) -> 0 | I100: =COUNTIFS(TUDB!$H$8:$H$2326,Use!$B100,TUDB!$F$8:$F$2326,Use!I$49) -> 6 | J100: =COUNTIFS(TUDB!$H$8:$H$2326,Use!$B100,TUDB!$F$8:$F$2326,Use!J$49) -> 0 | K100: =IF(AND(F100>0,SUM($E100)=0),1,0) -> 0 | L100: =IF(AND(G100>0,SUM($E100:F100)=0),1,0) -> 0 | M100: =IF(AND(H100>0,SUM($E100:G100)=0),1,0) -> 0 | N100: =IF(AND(I100>0,SUM($E100:H100)=0),1,0) -> 1 | O100: =IF(AND(J100>0,SUM($E100:I100)=0),1,0) -> 0
B101: ZMmGOOwucYXE3nEMRlAJSj4Cg8c2 | C101: TCTU | D101: =SUM(E101:J101) -> 25 | E101: =COUNTIFS(TUDB!$H$8:$H$2326,Use!$B101,TUDB!$F$8:$F$2326,Use!E$49) -> 0 | F101: =COUNTIFS(TUDB!$H$8:$H$2326,Use!$B101,TUDB!$F$8:$F$2326,Use!F$49) -> 0 | G101: =COUNTIFS(TUDB!$H$8:$H$2326,Use!$B101,TUDB!$F$8:$F$2326,Use!G$49) -> 9 | H101: =COUNTIFS(TUDB!$H$8:$H$2326,Use!$B101,TUDB!$F$8:$F$2326,Use!H$49) -> 10 | I101: =COUNTIFS(TUDB!$H$8:$H$2326,Use!$B101,TUDB!$F$8:$F$2326,Use!I$49) -> 6 | J101: =COUNTIFS(TUDB!$H$8:$H$2326,Use!$B101,TUDB!$F$8:$F$2326,Use!J$49) -> 0 | K101: =IF(AND(F101>0,SUM($E101)=0),1,0) -> 0 | L101: =IF(AND(G101>0,SUM($E101:F101)=0),1,0) -> 1 | M101: =IF(AND(H101>0,SUM($E101:G101)=0),1,0) -> 0 | N101: =IF(AND(I101>0,SUM($E101:H101)=0),1,0) -> 0 | O101: =IF(AND(J101>0,SUM($E101:I101)=0),1,0) -> 0 | S101: TU Chapters | T101: Total | U101: 2020 | V101: 2021 | W101: 2022 | X101: 2023 | Y101: 2024 | Z101: 2025 | AA101: 2026 | AB101: 2027 | AC101: 2028 | AD101: DB Labels
B102: mOliWfJ8EcTqb0crRnvVrqCHyEi1 | C102: TCTU | D102: =SUM(E102:J102) -> 6 | E102: =COUNTIFS(TUDB!$H$8:$H$2326,Use!$B102,TUDB!$F$8:$F$2326,Use!E$49) -> 0 | F102: =COUNTIFS(TUDB!$H$8:$H$2326,Use!$B102,TUDB!$F$8:$F$2326,Use!F$49) -> 0 | G102: =COUNTIFS(TUDB!$H$8:$H$2326,Use!$B102,TUDB!$F$8:$F$2326,Use!G$49) -> 0 | H102: =COUNTIFS(TUDB!$H$8:$H$2326,Use!$B102,TUDB!$F$8:$F$2326,Use!H$49) -> 5 | I102: =COUNTIFS(TUDB!$H$8:$H$2326,Use!$B102,TUDB!$F$8:$F$2326,Use!I$49) -> 1 | J102: =COUNTIFS(TUDB!$H$8:$H$2326,Use!$B102,TUDB!$F$8:$F$2326,Use!J$49) -> 0 | K102: =IF(AND(F102>0,SUM($E102)=0),1,0) -> 0 | L102: =IF(AND(G102>0,SUM($E102:F102)=0),1,0) -> 0 | M102: =IF(AND(H102>0,SUM($E102:G102)=0),1,0) -> 1 | N102: =IF(AND(I102>0,SUM($E102:H102)=0),1,0) -> 0 | O102: =IF(AND(J102>0,SUM($E102:I102)=0),1,0) -> 0 | S102: Aldo Leopold | T102: =SUM(U102:AC102) -> 18 | U102: =COUNTIFS(TU_DB[[TU Chapter Area]:[TU Chapter Area]],$AD102,TU_DB[[Year]:[Year]],U$101) -> 1 | V102: =COUNTIFS(TU_DB[[TU Chapter Area]:[TU Chapter Area]],$AD102,TU_DB[[Year]:[Year]],V$101) -> 0 | W102: =COUNTIFS(TU_DB[[TU Chapter Area]:[TU Chapter Area]],$AD102,TU_DB[[Year]:[Year]],W$101) -> 0 | X102: =COUNTIFS(TU_DB[[TU Chapter Area]:[TU Chapter Area]],$AD102,TU_DB[[Year]:[Year]],X$101) -> 15 | Y102: =COUNTIFS(TU_DB[[TU Chapter Area]:[TU Chapter Area]],$AD102,TU_DB[[Year]:[Year]],Y$101) -> 2 | Z102: =COUNTIFS(TU_DB[[TU Chapter Area]:[TU Chapter Area]],$AD102,TU_DB[[Year]:[Year]],Z$101) -> 0 | AA102: =COUNTIFS(TU_DB[[TU Chapter Area]:[TU Chapter Area]],$S102,TU_DB[[Year]:[Year]],AA$101) -> 0 | AB102: =COUNTIFS(TU_DB[[TU Chapter Area]:[TU Chapter Area]],$AD102,TU_DB[[Year]:[Year]],AB$101) -> 0 | AC102: =COUNTIFS(TU_DB[[TU Chapter Area]:[TU Chapter Area]],$S102,TU_DB[[Year]:[Year]],AC$101) -> 0 | AD102: Aldo Leopold
B103: inidBfHzkzPKUyeLROUq9PMQemF2 | C103: Agency/University | D103: =SUM(E103:J103) -> 23 | E103: =COUNTIFS(TUDB!$H$8:$H$2326,Use!$B103,TUDB!$F$8:$F$2326,Use!E$49) -> 0 | F103: =COUNTIFS(TUDB!$H$8:$H$2326,Use!$B103,TUDB!$F$8:$F$2326,Use!F$49) -> 0 | G103: =COUNTIFS(TUDB!$H$8:$H$2326,Use!$B103,TUDB!$F$8:$F$2326,Use!G$49) -> 0 | H103: =COUNTIFS(TUDB!$H$8:$H$2326,Use!$B103,TUDB!$F$8:$F$2326,Use!H$49) -> 0 | I103: =COUNTIFS(TUDB!$H$8:$H$2326,Use!$B103,TUDB!$F$8:$F$2326,Use!I$49) -> 23 | J103: =COUNTIFS(TUDB!$H$8:$H$2326,Use!$B103,TUDB!$F$8:$F$2326,Use!J$49) -> 0 | K103: =IF(AND(F103>0,SUM($E103)=0),1,0) -> 0 | L103: =IF(AND(G103>0,SUM($E103:F103)=0),1,0) -> 0 | M103: =IF(AND(H103>0,SUM($E103:G103)=0),1,0) -> 0 | N103: =IF(AND(I103>0,SUM($E103:H103)=0),1,0) -> 1 | O103: =IF(AND(J103>0,SUM($E103:I103)=0),1,0) -> 0 | S103: Blackhawk | T103: =SUM(U103:AC103) -> 8 | U103: =COUNTIFS(TU_DB[[TU Chapter Area]:[TU Chapter Area]],$AD103,TU_DB[[Year]:[Year]],U$101) -> 0 | V103: =COUNTIFS(TU_DB[[TU Chapter Area]:[TU Chapter Area]],$AD103,TU_DB[[Year]:[Year]],V$101) -> 0 | W103: =COUNTIFS(TU_DB[[TU Chapter Area]:[TU Chapter Area]],$AD103,TU_DB[[Year]:[Year]],W$101) -> 0 | X103: =COUNTIFS(TU_DB[[TU Chapter Area]:[TU Chapter Area]],$AD103,TU_DB[[Year]:[Year]],X$101) -> 6 | Y103: =COUNTIFS(TU_DB[[TU Chapter Area]:[TU Chapter Area]],$AD103,TU_DB[[Year]:[Year]],Y$101) -> 2 | Z103: =COUNTIFS(TU_DB[[TU Chapter Area]:[TU Chapter Area]],$AD103,TU_DB[[Year]:[Year]],Z$101) -> 0 | AA103: =COUNTIFS(TU_DB[[TU Chapter Area]:[TU Chapter Area]],$S103,TU_DB[[Year]:[Year]],AA$101) -> 0 | AB103: =COUNTIFS(TU_DB[[TU Chapter Area]:[TU Chapter Area]],$AD103,TU_DB[[Year]:[Year]],AB$101) -> 0 | AC103: =COUNTIFS(TU_DB[[TU Chapter Area]:[TU Chapter Area]],$S103,TU_DB[[Year]:[Year]],AC$101) -> 0 | AD103: Blackhawk
B104: 45rXX7ilGVVrOJRshsY6hOrN1Hd2 | C104: Hiawatha | D104: =SUM(E104:J104) -> 4 | E104: =COUNTIFS(TUDB!$H$8:$H$2326,Use!$B104,TUDB!$F$8:$F$2326,Use!E$49) -> 0 | F104: =COUNTIFS(TUDB!$H$8:$H$2326,Use!$B104,TUDB!$F$8:$F$2326,Use!F$49) -> 0 | G104: =COUNTIFS(TUDB!$H$8:$H$2326,Use!$B104,TUDB!$F$8:$F$2326,Use!G$49) -> 0 | H104: =COUNTIFS(TUDB!$H$8:$H$2326,Use!$B104,TUDB!$F$8:$F$2326,Use!H$49) -> 0 | I104: =COUNTIFS(TUDB!$H$8:$H$2326,Use!$B104,TUDB!$F$8:$F$2326,Use!I$49) -> 4 | J104: =COUNTIFS(TUDB!$H$8:$H$2326,Use!$B104,TUDB!$F$8:$F$2326,Use!J$49) -> 0 | K104: =IF(AND(F104>0,SUM($E104)=0),1,0) -> 0 | L104: =IF(AND(G104>0,SUM($E104:F104)=0),1,0) -> 0 | M104: =IF(AND(H104>0,SUM($E104:G104)=0),1,0) -> 0 | N104: =IF(AND(I104>0,SUM($E104:H104)=0),1,0) -> 1 | O104: =IF(AND(J104>0,SUM($E104:I104)=0),1,0) -> 0 | S104: Coulee Region | T104: =SUM(U104:AC104) -> 230 | U104: =COUNTIFS(TU_DB[[TU Chapter Area]:[TU Chapter Area]],$AD104,TU_DB[[Year]:[Year]],U$101) -> 11 | V104: =COUNTIFS(TU_DB[[TU Chapter Area]:[TU Chapter Area]],$AD104,TU_DB[[Year]:[Year]],V$101) -> 14 | W104: =COUNTIFS(TU_DB[[TU Chapter Area]:[TU Chapter Area]],$AD104,TU_DB[[Year]:[Year]],W$101) -> 13 | X104: =COUNTIFS(TU_DB[[TU Chapter Area]:[TU Chapter Area]],$AD104,TU_DB[[Year]:[Year]],X$101) -> 177 | Y104: =COUNTIFS(TU_DB[[TU Chapter Area]:[TU Chapter Area]],$AD104,TU_DB[[Year]:[Year]],Y$101) -> 15 | Z104: =COUNTIFS(TU_DB[[TU Chapter Area]:[TU Chapter Area]],$AD104,TU_DB[[Year]:[Year]],Z$101) -> 0 | AA104: =COUNTIFS(TU_DB[[TU Chapter Area]:[TU Chapter Area]],$S104,TU_DB[[Year]:[Year]],AA$101) -> 0 | AB104: =COUNTIFS(TU_DB[[TU Chapter Area]:[TU Chapter Area]],$AD104,TU_DB[[Year]:[Year]],AB$101) -> 0 | AC104: =COUNTIFS(TU_DB[[TU Chapter Area]:[TU Chapter Area]],$S104,TU_DB[[Year]:[Year]],AC$101) -> 0 | AD104: Coulee Region
B105: aPffmw8BEWfof4TYloC3SpL9sQk1 | C105: Hiawatha | D105: =SUM(E105:J105) -> 7 | E105: =COUNTIFS(TUDB!$H$8:$H$2326,Use!$B105,TUDB!$F$8:$F$2326,Use!E$49) -> 0 | F105: =COUNTIFS(TUDB!$H$8:$H$2326,Use!$B105,TUDB!$F$8:$F$2326,Use!F$49) -> 0 | G105: =COUNTIFS(TUDB!$H$8:$H$2326,Use!$B105,TUDB!$F$8:$F$2326,Use!G$49) -> 5 | H105: =COUNTIFS(TUDB!$H$8:$H$2326,Use!$B105,TUDB!$F$8:$F$2326,Use!H$49) -> 0 | I105: =COUNTIFS(TUDB!$H$8:$H$2326,Use!$B105,TUDB!$F$8:$F$2326,Use!I$49) -> 2 | J105: =COUNTIFS(TUDB!$H$8:$H$2326,Use!$B105,TUDB!$F$8:$F$2326,Use!J$49) -> 0 | K105: =IF(AND(F105>0,SUM($E105)=0),1,0) -> 0 | L105: =IF(AND(G105>0,SUM($E105:F105)=0),1,0) -> 1 | M105: =IF(AND(H105>0,SUM($E105:G105)=0),1,0) -> 0 | N105: =IF(AND(I105>0,SUM($E105:H105)=0),1,0) -> 0 | O105: =IF(AND(J105>0,SUM($E105:I105)=0),1,0) -> 0 | S105: Harry & Laura Nohr | T105: =SUM(U105:AC105) -> 80 | U105: =COUNTIFS(TU_DB[[TU Chapter Area]:[TU Chapter Area]],$AD105,TU_DB[[Year]:[Year]],U$101) -> 0 | V105: =COUNTIFS(TU_DB[[TU Chapter Area]:[TU Chapter Area]],$AD105,TU_DB[[Year]:[Year]],V$101) -> 1 | W105: =COUNTIFS(TU_DB[[TU Chapter Area]:[TU Chapter Area]],$AD105,TU_DB[[Year]:[Year]],W$101) -> 0 | X105: =COUNTIFS(TU_DB[[TU Chapter Area]:[TU Chapter Area]],$AD105,TU_DB[[Year]:[Year]],X$101) -> 48 | Y105: =COUNTIFS(TU_DB[[TU Chapter Area]:[TU Chapter Area]],$AD105,TU_DB[[Year]:[Year]],Y$101) -> 31 | Z105: =COUNTIFS(TU_DB[[TU Chapter Area]:[TU Chapter Area]],$AD105,TU_DB[[Year]:[Year]],Z$101) -> 0 | AA105: =COUNTIFS(TU_DB[[TU Chapter Area]:[TU Chapter Area]],$S105,TU_DB[[Year]:[Year]],AA$101) -> 0 | AB105: =COUNTIFS(TU_DB[[TU Chapter Area]:[TU Chapter Area]],$AD105,TU_DB[[Year]:[Year]],AB$101) -> 0 | AC105: =COUNTIFS(TU_DB[[TU Chapter Area]:[TU Chapter Area]],$S105,TU_DB[[Year]:[Year]],AC$101) -> 0 | AD105: Harry & Laura Nohr
B106: iL4InQVt0eQdf8HXXiLJJxA4dTA2 | C106: Coulee Region | D106: =SUM(E106:J106) -> 12 | E106: =COUNTIFS(TUDB!$H$8:$H$2326,Use!$B106,TUDB!$F$8:$F$2326,Use!E$49) -> 0 | F106: =COUNTIFS(TUDB!$H$8:$H$2326,Use!$B106,TUDB!$F$8:$F$2326,Use!F$49) -> 0 | G106: =COUNTIFS(TUDB!$H$8:$H$2326,Use!$B106,TUDB!$F$8:$F$2326,Use!G$49) -> 0 | H106: =COUNTIFS(TUDB!$H$8:$H$2326,Use!$B106,TUDB!$F$8:$F$2326,Use!H$49) -> 0 | I106: =COUNTIFS(TUDB!$H$8:$H$2326,Use!$B106,TUDB!$F$8:$F$2326,Use!I$49) -> 12 | J106: =COUNTIFS(TUDB!$H$8:$H$2326,Use!$B106,TUDB!$F$8:$F$2326,Use!J$49) -> 0 | K106: =IF(AND(F106>0,SUM($E106)=0),1,0) -> 0 | L106: =IF(AND(G106>0,SUM($E106:F106)=0),1,0) -> 0 | M106: =IF(AND(H106>0,SUM($E106:G106)=0),1,0) -> 0 | N106: =IF(AND(I106>0,SUM($E106:H106)=0),1,0) -> 1 | O106: =IF(AND(J106>0,SUM($E106:I106)=0),1,0) -> 0 | S106: Hiawatha | T106: =SUM(U106:AC106) -> 337 | U106: =COUNTIFS(TU_DB[[TU Chapter Area]:[TU Chapter Area]],$AD106,TU_DB[[Year]:[Year]],U$101) -> 8 | V106: =COUNTIFS(TU_DB[[TU Chapter Area]:[TU Chapter Area]],$AD106,TU_DB[[Year]:[Year]],V$101) -> 105 | W106: =COUNTIFS(TU_DB[[TU Chapter Area]:[TU Chapter Area]],$AD106,TU_DB[[Year]:[Year]],W$101) -> 60 | X106: =COUNTIFS(TU_DB[[TU Chapter Area]:[TU Chapter Area]],$AD106,TU_DB[[Year]:[Year]],X$101) -> 86 | Y106: =COUNTIFS(TU_DB[[TU Chapter Area]:[TU Chapter Area]],$AD106,TU_DB[[Year]:[Year]],Y$101) -> 78 | Z106: =COUNTIFS(TU_DB[[TU Chapter Area]:[TU Chapter Area]],$AD106,TU_DB[[Year]:[Year]],Z$101) -> 0 | AA106: =COUNTIFS(TU_DB[[TU Chapter Area]:[TU Chapter Area]],$S106,TU_DB[[Year]:[Year]],AA$101) -> 0 | AB106: =COUNTIFS(TU_DB[[TU Chapter Area]:[TU Chapter Area]],$AD106,TU_DB[[Year]:[Year]],AB$101) -> 0 | AC106: =COUNTIFS(TU_DB[[TU Chapter Area]:[TU Chapter Area]],$S106,TU_DB[[Year]:[Year]],AC$101) -> 0 | AD106: Hiawatha
B107: UlOTIjO5fRXyX2NgghYvxYXOF0j2 | C107: Unknown | D107: =SUM(E107:J107) -> 8 | E107: =COUNTIFS(TUDB!$H$8:$H$2326,Use!$B107,TUDB!$F$8:$F$2326,Use!E$49) -> 0 | F107: =COUNTIFS(TUDB!$H$8:$H$2326,Use!$B107,TUDB!$F$8:$F$2326,Use!F$49) -> 0 | G107: =COUNTIFS(TUDB!$H$8:$H$2326,Use!$B107,TUDB!$F$8:$F$2326,Use!G$49) -> 0 | H107: =COUNTIFS(TUDB!$H$8:$H$2326,Use!$B107,TUDB!$F$8:$F$2326,Use!H$49) -> 0 | I107: =COUNTIFS(TUDB!$H$8:$H$2326,Use!$B107,TUDB!$F$8:$F$2326,Use!I$49) -> 8 | J107: =COUNTIFS(TUDB!$H$8:$H$2326,Use!$B107,TUDB!$F$8:$F$2326,Use!J$49) -> 0 | K107: =IF(AND(F107>0,SUM($E107)=0),1,0) -> 0 | L107: =IF(AND(G107>0,SUM($E107:F107)=0),1,0) -> 0 | M107: =IF(AND(H107>0,SUM($E107:G107)=0),1,0) -> 0 | N107: =IF(AND(I107>0,SUM($E107:H107)=0),1,0) -> 1 | O107: =IF(AND(J107>0,SUM($E107:I107)=0),1,0) -> 0 | S107: Iowa Driftless | T107: =SUM(U107:AC107) -> 112 | U107: =COUNTIFS(TU_DB[[TU Chapter Area]:[TU Chapter Area]],$AD107,TU_DB[[Year]:[Year]],U$101) -> 1 | V107: =COUNTIFS(TU_DB[[TU Chapter Area]:[TU Chapter Area]],$AD107,TU_DB[[Year]:[Year]],V$101) -> 7 | W107: =COUNTIFS(TU_DB[[TU Chapter Area]:[TU Chapter Area]],$AD107,TU_DB[[Year]:[Year]],W$101) -> 21 | X107: =COUNTIFS(TU_DB[[TU Chapter Area]:[TU Chapter Area]],$AD107,TU_DB[[Year]:[Year]],X$101) -> 38 | Y107: =COUNTIFS(TU_DB[[TU Chapter Area]:[TU Chapter Area]],$AD107,TU_DB[[Year]:[Year]],Y$101) -> 45 | Z107: =COUNTIFS(TU_DB[[TU Chapter Area]:[TU Chapter Area]],$AD107,TU_DB[[Year]:[Year]],Z$101) -> 0 | AA107: =COUNTIFS(TU_DB[[TU Chapter Area]:[TU Chapter Area]],$S107,TU_DB[[Year]:[Year]],AA$101) -> 0 | AB107: =COUNTIFS(TU_DB[[TU Chapter Area]:[TU Chapter Area]],$AD107,TU_DB[[Year]:[Year]],AB$101) -> 0 | AC107: =COUNTIFS(TU_DB[[TU Chapter Area]:[TU Chapter Area]],$S107,TU_DB[[Year]:[Year]],AC$101) -> 0 | AD107: Iowa Driftless
B108: sPbTkTzcbybDduQDEAb0F4hUDHf2 | C108: TCTU | D108: =SUM(E108:J108) -> 16 | E108: =COUNTIFS(TUDB!$H$8:$H$2326,Use!$B108,TUDB!$F$8:$F$2326,Use!E$49) -> 0 | F108: =COUNTIFS(TUDB!$H$8:$H$2326,Use!$B108,TUDB!$F$8:$F$2326,Use!F$49) -> 0 | G108: =COUNTIFS(TUDB!$H$8:$H$2326,Use!$B108,TUDB!$F$8:$F$2326,Use!G$49) -> 0 | H108: =COUNTIFS(TUDB!$H$8:$H$2326,Use!$B108,TUDB!$F$8:$F$2326,Use!H$49) -> 9 | I108: =COUNTIFS(TUDB!$H$8:$H$2326,Use!$B108,TUDB!$F$8:$F$2326,Use!I$49) -> 7 | J108: =COUNTIFS(TUDB!$H$8:$H$2326,Use!$B108,TUDB!$F$8:$F$2326,Use!J$49) -> 0 | K108: =IF(AND(F108>0,SUM($E108)=0),1,0) -> 0 | L108: =IF(AND(G108>0,SUM($E108:F108)=0),1,0) -> 0 | M108: =IF(AND(H108>0,SUM($E108:G108)=0),1,0) -> 1 | N108: =IF(AND(I108>0,SUM($E108:H108)=0),1,0) -> 0 | O108: =IF(AND(J108>0,SUM($E108:I108)=0),1,0) -> 0 | S108: Kiap-TU-Wish | T108: =SUM(U108:AC108) -> 518 | U108: =COUNTIFS(TU_DB[[TU Chapter Area]:[TU Chapter Area]],$AD108,TU_DB[[Year]:[Year]],U$101) -> 65 | V108: =COUNTIFS(TU_DB[[TU Chapter Area]:[TU Chapter Area]],$AD108,TU_DB[[Year]:[Year]],V$101) -> 91 | W108: =COUNTIFS(TU_DB[[TU Chapter Area]:[TU Chapter Area]],$AD108,TU_DB[[Year]:[Year]],W$101) -> 184 | X108: =COUNTIFS(TU_DB[[TU Chapter Area]:[TU Chapter Area]],$AD108,TU_DB[[Year]:[Year]],X$101) -> 100 | Y108: =COUNTIFS(TU_DB[[TU Chapter Area]:[TU Chapter Area]],$AD108,TU_DB[[Year]:[Year]],Y$101) -> 78 | Z108: =COUNTIFS(TU_DB[[TU Chapter Area]:[TU Chapter Area]],$AD108,TU_DB[[Year]:[Year]],Z$101) -> 0 | AA108: =COUNTIFS(TU_DB[[TU Chapter Area]:[TU Chapter Area]],$S108,TU_DB[[Year]:[Year]],AA$101) -> 0 | AB108: =COUNTIFS(TU_DB[[TU Chapter Area]:[TU Chapter Area]],$AD108,TU_DB[[Year]:[Year]],AB$101) -> 0 | AC108: =COUNTIFS(TU_DB[[TU Chapter Area]:[TU Chapter Area]],$S108,TU_DB[[Year]:[Year]],AC$101) -> 0 | AD108: Kiap-TU-Wish
B109: dzm5kGoaEqWZ3aoqMW65dlUm5g92 | C109: TCTU | D109: =SUM(E109:J109) -> 18 | E109: =COUNTIFS(TUDB!$H$8:$H$2326,Use!$B109,TUDB!$F$8:$F$2326,Use!E$49) -> 0 | F109: =COUNTIFS(TUDB!$H$8:$H$2326,Use!$B109,TUDB!$F$8:$F$2326,Use!F$49) -> 0 | G109: =COUNTIFS(TUDB!$H$8:$H$2326,Use!$B109,TUDB!$F$8:$F$2326,Use!G$49) -> 0 | H109: =COUNTIFS(TUDB!$H$8:$H$2326,Use!$B109,TUDB!$F$8:$F$2326,Use!H$49) -> 12 | I109: =COUNTIFS(TUDB!$H$8:$H$2326,Use!$B109,TUDB!$F$8:$F$2326,Use!I$49) -> 6 | J109: =COUNTIFS(TUDB!$H$8:$H$2326,Use!$B109,TUDB!$F$8:$F$2326,Use!J$49) -> 0 | K109: =IF(AND(F109>0,SUM($E109)=0),1,0) -> 0 | L109: =IF(AND(G109>0,SUM($E109:F109)=0),1,0) -> 0 | M109: =IF(AND(H109>0,SUM($E109:G109)=0),1,0) -> 1 | N109: =IF(AND(I109>0,SUM($E109:H109)=0),1,0) -> 0 | O109: =IF(AND(J109>0,SUM($E109:I109)=0),1,0) -> 0 | S109: Lee Wulff | T109: =SUM(U109:AC109) -> 0 | U109: =COUNTIFS(TU_DB[[TU Chapter Area]:[TU Chapter Area]],$AD109,TU_DB[[Year]:[Year]],U$101) -> 0 | V109: =COUNTIFS(TU_DB[[TU Chapter Area]:[TU Chapter Area]],$AD109,TU_DB[[Year]:[Year]],V$101) -> 0 | W109: =COUNTIFS(TU_DB[[TU Chapter Area]:[TU Chapter Area]],$AD109,TU_DB[[Year]:[Year]],W$101) -> 0 | X109: =COUNTIFS(TU_DB[[TU Chapter Area]:[TU Chapter Area]],$AD109,TU_DB[[Year]:[Year]],X$101) -> 0 | Y109: =COUNTIFS(TU_DB[[TU Chapter Area]:[TU Chapter Area]],$AD109,TU_DB[[Year]:[Year]],Y$101) -> 0 | Z109: =COUNTIFS(TU_DB[[TU Chapter Area]:[TU Chapter Area]],$AD109,TU_DB[[Year]:[Year]],Z$101) -> 0 | AA109: =COUNTIFS(TU_DB[[TU Chapter Area]:[TU Chapter Area]],$S109,TU_DB[[Year]:[Year]],AA$101) -> 0 | AB109: =COUNTIFS(TU_DB[[TU Chapter Area]:[TU Chapter Area]],$AD109,TU_DB[[Year]:[Year]],AB$101) -> 0 | AC109: =COUNTIFS(TU_DB[[TU Chapter Area]:[TU Chapter Area]],$S109,TU_DB[[Year]:[Year]],AC$101) -> 0 | AD109: Lee Wulff
...

Sheet ALK
A1: TU DARE Angler Science DB
B2: Water Analysis | C2: Alkalinity
B3: Download | C3: =TUDB!B3 -> 45580
B5: Overview Stats
B6: Alkalinity [ppm CaCO3] | C6: Observations | D6: % Total Obs. | E6: Cum. % | F6: 2019 | G6: 2020 | H6: 2021 | I6: 2022 | J6: 2023 | K6: 2024
B7: 0 | C7: =COUNTIFS(TU_DB[ALK Bin (ppm)],B7) -> 184 | D7: =C7/$C$13 -> 0.091862207 | E7: =D7 -> 0.091862207 | F7: =COUNTIFS(TU_DB[[ALK Bin (ppm)]:[ALK Bin (ppm)]],$B7,TU_DB[[Year]:[Year]],F$6) -> 0 | G7: =COUNTIFS(TU_DB[[ALK Bin (ppm)]:[ALK Bin (ppm)]],$B7,TU_DB[[Year]:[Year]],G$6) -> 16 | H7: =COUNTIFS(TU_DB[[ALK Bin (ppm)]:[ALK Bin (ppm)]],$B7,TU_DB[[Year]:[Year]],H$6) -> 44 | I7: =COUNTIFS(TU_DB[[ALK Bin (ppm)]:[ALK Bin (ppm)]],$B7,TU_DB[[Year]:[Year]],I$6) -> 41 | J7: =COUNTIFS(TU_DB[[ALK Bin (ppm)]:[ALK Bin (ppm)]],$B7,TU_DB[[Year]:[Year]],J$6) -> 58 | K7: =COUNTIFS(TU_DB[[ALK Bin (ppm)]:[ALK Bin (ppm)]],$B7,TU_DB[[Year]:[Year]],K$6) -> 25
B8: 40 | C8: =COUNTIFS(TU_DB[ALK Bin (ppm)],B8) -> 203 | D8: =C8/$C$13 -> 0.10134798 | E8: =D8+E7 -> 0.19321018 | F8: =COUNTIFS(TU_DB[[ALK Bin (ppm)]:[ALK Bin (ppm)]],$B8,TU_DB[[Year]:[Year]],F$6) -> 0 | G8: =COUNTIFS(TU_DB[[ALK Bin (ppm)]:[ALK Bin (ppm)]],$B8,TU_DB[[Year]:[Year]],G$6) -> 6 | H8: =COUNTIFS(TU_DB[[ALK Bin (ppm)]:[ALK Bin (ppm)]],$B8,TU_DB[[Year]:[Year]],H$6) -> 14 | I8: =COUNTIFS(TU_DB[[ALK Bin (ppm)]:[ALK Bin (ppm)]],$B8,TU_DB[[Year]:[Year]],I$6) -> 36 | J8: =COUNTIFS(TU_DB[[ALK Bin (ppm)]:[ALK Bin (ppm)]],$B8,TU_DB[[Year]:[Year]],J$6) -> 106 | K8: =COUNTIFS(TU_DB[[ALK Bin (ppm)]:[ALK Bin (ppm)]],$B8,TU_DB[[Year]:[Year]],K$6) -> 41
B9: 80 | C9: =COUNTIFS(TU_DB[ALK Bin (ppm)],B9) -> 405 | D9: =C9/$C$13 -> 0.2021967 | E9: =D9+E8 -> 0.39540689 | F9: =COUNTIFS(TU_DB[[ALK Bin (ppm)]:[ALK Bin (ppm)]],$B9,TU_DB[[Year]:[Year]],F$6) -> 0 | G9: =COUNTIFS(TU_DB[[ALK Bin (ppm)]:[ALK Bin (ppm)]],$B9,TU_DB[[Year]:[Year]],G$6) -> 15 | H9: =COUNTIFS(TU_DB[[ALK Bin (ppm)]:[ALK Bin (ppm)]],$B9,TU_DB[[Year]:[Year]],H$6) -> 78 | I9: =COUNTIFS(TU_DB[[ALK Bin (ppm)]:[ALK Bin (ppm)]],$B9,TU_DB[[Year]:[Year]],I$6) -> 91 | J9: =COUNTIFS(TU_DB[[ALK Bin (ppm)]:[ALK Bin (ppm)]],$B9,TU_DB[[Year]:[Year]],J$6) -> 126 | K9: =COUNTIFS(TU_DB[[ALK Bin (ppm)]:[ALK Bin (ppm)]],$B9,TU_DB[[Year]:[Year]],K$6) -> 95
B10: 120 | C10: =COUNTIFS(TU_DB[ALK Bin (ppm)],B10) -> 290 | D10: =C10/$C$13 -> 0.14478283 | E10: =D10+E9 -> 0.54018972 | F10: =COUNTIFS(TU_DB[[ALK Bin (ppm)]:[ALK Bin (ppm)]],$B10,TU_DB[[Year]:[Year]],F$6) -> 0 | G10: =COUNTIFS(TU_DB[[ALK Bin (ppm)]:[ALK Bin (ppm)]],$B10,TU_DB[[Year]:[Year]],G$6) -> 20 | H10: =COUNTIFS(TU_DB[[ALK Bin (ppm)]:[ALK Bin (ppm)]],$B10,TU_DB[[Year]:[Year]],H$6) -> 54 | I10: =COUNTIFS(TU_DB[[ALK Bin (ppm)]:[ALK Bin (ppm)]],$B10,TU_DB[[Year]:[Year]],I$6) -> 61 | J10: =COUNTIFS(TU_DB[[ALK Bin (ppm)]:[ALK Bin (ppm)]],$B10,TU_DB[[Year]:[Year]],J$6) -> 98 | K10: =COUNTIFS(TU_DB[[ALK Bin (ppm)]:[ALK Bin (ppm)]],$B10,TU_DB[[Year]:[Year]],K$6) -> 57
B11: 180 | C11: =COUNTIFS(TU_DB[ALK Bin (ppm)],B11) -> 897 | D11: =C11/$C$13 -> 0.44782826 | E11: =D11+E10 -> 0.98801797 | F11: =COUNTIFS(TU_DB[[ALK Bin (ppm)]:[ALK Bin (ppm)]],$B11,TU_DB[[Year]:[Year]],F$6) -> 4 | G11: =COUNTIFS(TU_DB[[ALK Bin (ppm)]:[ALK Bin (ppm)]],$B11,TU_DB[[Year]:[Year]],G$6) -> 41 | H11: =COUNTIFS(TU_DB[[ALK Bin (ppm)]:[ALK Bin (ppm)]],$B11,TU_DB[[Year]:[Year]],H$6) -> 168 | I11: =COUNTIFS(TU_DB[[ALK Bin (ppm)]:[ALK Bin (ppm)]],$B11,TU_DB[[Year]:[Year]],I$6) -> 188 | J11: =COUNTIFS(TU_DB[[ALK Bin (ppm)]:[ALK Bin (ppm)]],$B11,TU_DB[[Year]:[Year]],J$6) -> 322 | K11: =COUNTIFS(TU_DB[[ALK Bin (ppm)]:[ALK Bin (ppm)]],$B11,TU_DB[[Year]:[Year]],K$6) -> 174
B12: 240 | C12: =COUNTIFS(TU_DB[ALK Bin (ppm)],B12) -> 24 | D12: =C12/$C$13 -> 0.011982027 | E12: =D12+E11 -> 1 | F12: =COUNTIFS(TU_DB[[ALK Bin (ppm)]:[ALK Bin (ppm)]],$B12,TU_DB[[Year]:[Year]],F$6) -> 0 | G12: =COUNTIFS(TU_DB[[ALK Bin (ppm)]:[ALK Bin (ppm)]],$B12,TU_DB[[Year]:[Year]],G$6) -> 10 | H12: =COUNTIFS(TU_DB[[ALK Bin (ppm)]:[ALK Bin (ppm)]],$B12,TU_DB[[Year]:[Year]],H$6) -> 3 | I12: =COUNTIFS(TU_DB[[ALK Bin (ppm)]:[ALK Bin (ppm)]],$B12,TU_DB[[Year]:[Year]],I$6) -> 2 | J12: =COUNTIFS(TU_DB[[ALK Bin (ppm)]:[ALK Bin (ppm)]],$B12,TU_DB[[Year]:[Year]],J$6) -> 4 | K12: =COUNTIFS(TU_DB[[ALK Bin (ppm)]:[ALK Bin (ppm)]],$B12,TU_DB[[Year]:[Year]],K$6) -> 5
B13: Total | C13: =SUM(C7:C12) -> 2003 | F13: =SUM(F7:F12) -> 4 | G13: =SUM(G7:G12) -> 108 | H13: =SUM(H7:H12) -> 361 | I13: =SUM(I7:I12) -> 419 | J13: =SUM(J7:J12) -> 714 | K13: =SUM(K7:K12) -> 397
B17: Weather Conditions
C18: Alkalinity [ppm CaCO3] | K18: Table Labels
B19: Weather Conditions | C19: 0 | D19: 40 | E19: 80 | F19: 120 | G19: 180 | H19: 240 | I19: Sum | J19: % Total
B20: Local Thunderstorm | C20: =COUNTIFS(TU_DB[[ALK Bin (ppm)]:[ALK Bin (ppm)]],C$19,TU_DB[[Weather]:[Weather]],$B20) -> 7 | D20: =COUNTIFS(TU_DB[[ALK Bin (ppm)]:[ALK Bin (ppm)]],D$19,TU_DB[[Weather]:[Weather]],$B20) -> 7 | E20: =COUNTIFS(TU_DB[[ALK Bin (ppm)]:[ALK Bin (ppm)]],E$19,TU_DB[[Weather]:[Weather]],$B20) -> 25 | F20: =COUNTIFS(TU_DB[[ALK Bin (ppm)]:[ALK Bin (ppm)]],F$19,TU_DB[[Weather]:[Weather]],$B20) -> 7 | G20: =COUNTIFS(TU_DB[[ALK Bin (ppm)]:[ALK Bin (ppm)]],G$19,TU_DB[[Weather]:[Weather]],$B20) -> 37 | H20: =COUNTIFS(TU_DB[[ALK Bin (ppm)]:[ALK Bin (ppm)]],H$19,TU_DB[[Weather]:[Weather]],$B20) -> 1 | I20: =SUM(C20:H20) -> 84 | J20: =SUM(I20)/SUM($I$20:$I$25) -> 0.047457627 | K20: LT
B21: Regional Rainfall | C21: =COUNTIFS(TU_DB[[ALK Bin (ppm)]:[ALK Bin (ppm)]],C$19,TU_DB[[Weather]:[Weather]],$B21) -> 24 | D21: =COUNTIFS(TU_DB[[ALK Bin (ppm)]:[ALK Bin (ppm)]],D$19,TU_DB[[Weather]:[Weather]],$B21) -> 39 | E21: =COUNTIFS(TU_DB[[ALK Bin (ppm)]:[ALK Bin (ppm)]],E$19,TU_DB[[Weather]:[Weather]],$B21) -> 51 | F21: =COUNTIFS(TU_DB[[ALK Bin (ppm)]:[ALK Bin (ppm)]],F$19,TU_DB[[Weather]:[Weather]],$B21) -> 40 | G21: =COUNTIFS(TU_DB[[ALK Bin (ppm)]:[ALK Bin (ppm)]],G$19,TU_DB[[Weather]:[Weather]],$B21) -> 89 | H21: =COUNTIFS(TU_DB[[ALK Bin (ppm)]:[ALK Bin (ppm)]],H$19,TU_DB[[Weather]:[Weather]],$B21) -> 2 | I21: =SUM(C21:H21) -> 245 | J21: =SUM(I21)/SUM($I$20:$I$25) -> 0.13841808 | K21: RR
B22: Regional Rainfall,Local Thunderstorm | C22: =COUNTIFS(TU_DB[[ALK Bin (ppm)]:[ALK Bin (ppm)]],C$19,TU_DB[[Weather]:[Weather]],$B22) -> 0 | D22: =COUNTIFS(TU_DB[[ALK Bin (ppm)]:[ALK Bin (ppm)]],D$19,TU_DB[[Weather]:[Weather]],$B22) -> 1 | E22: =COUNTIFS(TU_DB[[ALK Bin (ppm)]:[ALK Bin (ppm)]],E$19,TU_DB[[Weather]:[Weather]],$B22) -> 5 | F22: =COUNTIFS(TU_DB[[ALK Bin (ppm)]:[ALK Bin (ppm)]],F$19,TU_DB[[Weather]:[Weather]],$B22) -> 1 | G22: =COUNTIFS(TU_DB[[ALK Bin (ppm)]:[ALK Bin (ppm)]],G$19,TU_DB[[Weather]:[Weather]],$B22) -> 3 | H22: =COUNTIFS(TU_DB[[ALK Bin (ppm)]:[ALK Bin (ppm)]],H$19,TU_DB[[Weather]:[Weather]],$B22) -> 0 | I22: =SUM(C22:H22) -> 10 | J22: =SUM(I22)/SUM($I$20:$I$25) -> 0.0056497175 | K22: RR, LT
B23: Regional Rainfall,Warmth Causing Snowmelt | C23: =COUNTIFS(TU_DB[[ALK Bin (ppm)]:[ALK Bin (ppm)]],C$19,TU_DB[[Weather]:[Weather]],$B23) -> 0 | D23: =COUNTIFS(TU_DB[[ALK Bin (ppm)]:[ALK Bin (ppm)]],D$19,TU_DB[[Weather]:[Weather]],$B23) -> 0 | E23: =COUNTIFS(TU_DB[[ALK Bin (ppm)]:[ALK Bin (ppm)]],E$19,TU_DB[[Weather]:[Weather]],$B23) -> 0 | F23: =COUNTIFS(TU_DB[[ALK Bin (ppm)]:[ALK Bin (ppm)]],F$19,TU_DB[[Weather]:[Weather]],$B23) -> 2 | G23: =COUNTIFS(TU_DB[[ALK Bin (ppm)]:[ALK Bin (ppm)]],G$19,TU_DB[[Weather]:[Weather]],$B23) -> 2 | H23: =COUNTIFS(TU_DB[[ALK Bin (ppm)]:[ALK Bin (ppm)]],H$19,TU_DB[[Weather]:[Weather]],$B23) -> 1 | I23: =SUM(C23:H23) -> 5 | J23: =SUM(I23)/SUM($I$20:$I$25) -> 0.0028248588 | K23: RR, SM
B24: Warmth Causing Snowmelt | C24: =COUNTIFS(TU_DB[[ALK Bin (ppm)]:[ALK Bin (ppm)]],C$19,TU_DB[[Weather]:[Weather]],$B24) -> 2 | D24: =COUNTIFS(TU_DB[[ALK Bin (ppm)]:[ALK Bin (ppm)]],D$19,TU_DB[[Weather]:[Weather]],$B24) -> 2 | E24: =COUNTIFS(TU_DB[[ALK Bin (ppm)]:[ALK Bin (ppm)]],E$19,TU_DB[[Weather]:[Weather]],$B24) -> 4 | F24: =COUNTIFS(TU_DB[[ALK Bin (ppm)]:[ALK Bin (ppm)]],F$19,TU_DB[[Weather]:[Weather]],$B24) -> 0 | G24: =COUNTIFS(TU_DB[[ALK Bin (ppm)]:[ALK Bin (ppm)]],G$19,TU_DB[[Weather]:[Weather]],$B24) -> 8 | H24: =COUNTIFS(TU_DB[[ALK Bin (ppm)]:[ALK Bin (ppm)]],H$19,TU_DB[[Weather]:[Weather]],$B24) -> 4 | I24: =SUM(C24:H24) -> 20 | J24: =SUM(I24)/SUM($I$20:$I$25) -> 0.011299435 | K24: SM
B25: None | C25: =COUNTIFS(TU_DB[[ALK Bin (ppm)]:[ALK Bin (ppm)]],C$19,TU_DB[[Weather]:[Weather]],$B25) -> 122 | D25: =COUNTIFS(TU_DB[[ALK Bin (ppm)]:[ALK Bin (ppm)]],D$19,TU_DB[[Weather]:[Weather]],$B25) -> 130 | E25: =COUNTIFS(TU_DB[[ALK Bin (ppm)]:[ALK Bin (ppm)]],E$19,TU_DB[[Weather]:[Weather]],$B25) -> 279 | F25: =COUNTIFS(TU_DB[[ALK Bin (ppm)]:[ALK Bin (ppm)]],F$19,TU_DB[[Weather]:[Weather]],$B25) -> 200 | G25: =COUNTIFS(TU_DB[[ALK Bin (ppm)]:[ALK Bin (ppm)]],G$19,TU_DB[[Weather]:[Weather]],$B25) -> 661 | H25: =COUNTIFS(TU_DB[[ALK Bin (ppm)]:[ALK Bin (ppm)]],H$19,TU_DB[[Weather]:[Weather]],$B25) -> 14 | I25: =SUM(C25:H25) -> 1406 | J25: =SUM(I25)/SUM($I$20:$I$25) -> 0.79435028 | K25: None
B26: Total | C26: =SUM(C20:C25) -> 155 | D26: =SUM(D20:D25) -> 179 | E26: =SUM(E20:E25) -> 364 | F26: =SUM(F20:F25) -> 250 | G26: =SUM(G20:G25) -> 800 | H26: =SUM(H20:H25) -> 22 | I26: =SUM(I20:I25) -> 1770
B28: Water Level
C29: Alkalinity [ppm CaCO3]
B30: Water Level | C30: 0 | D30: 40 | E30: 80 | F30: 120 | G30: 180 | H30: 240 | I30: Sum | J30: % Total
B31: Baseflow | C31: =COUNTIFS(TU_DB[[ALK Bin (ppm)]:[ALK Bin (ppm)]],C$19,TU_DB[[Water Level]:[Water Level]],$B31) -> 112 | D31: =COUNTIFS(TU_DB[[ALK Bin (ppm)]:[ALK Bin (ppm)]],D$19,TU_DB[[Water Level]:[Water Level]],$B31) -> 132 | E31: =COUNTIFS(TU_DB[[ALK Bin (ppm)]:[ALK Bin (ppm)]],E$19,TU_DB[[Water Level]:[Water Level]],$B31) -> 252 | F31: =COUNTIFS(TU_DB[[ALK Bin (ppm)]:[ALK Bin (ppm)]],F$19,TU_DB[[Water Level]:[Water Level]],$B31) -> 206 | G31: =COUNTIFS(TU_DB[[ALK Bin (ppm)]:[ALK Bin (ppm)]],G$19,TU_DB[[Water Level]:[Water Level]],$B31) -> 655 | H31: =COUNTIFS(TU_DB[[ALK Bin (ppm)]:[ALK Bin (ppm)]],H$19,TU_DB[[Water Level]:[Water Level]],$B31) -> 16 | I31: =SUM(C31:H31) -> 1373 | J31: =SUM(I31)/SUM($I$31:$I$34) -> 0.75814467
B32: Mid-Stage | C32: =COUNTIFS(TU_DB[[ALK Bin (ppm)]:[ALK Bin (ppm)]],C$19,TU_DB[[Water Level]:[Water Level]],$B32) -> 35 | D32: =COUNTIFS(TU_DB[[ALK Bin (ppm)]:[ALK Bin (ppm)]],D$19,TU_DB[[Water Level]:[Water Level]],$B32) -> 47 | E32: =COUNTIFS(TU_DB[[ALK Bin (ppm)]:[ALK Bin (ppm)]],E$19,TU_DB[[Water Level]:[Water Level]],$B32) -> 90 | F32: =COUNTIFS(TU_DB[[ALK Bin (ppm)]:[ALK Bin (ppm)]],F$19,TU_DB[[Water Level]:[Water Level]],$B32) -> 34 | G32: =COUNTIFS(TU_DB[[ALK Bin (ppm)]:[ALK Bin (ppm)]],G$19,TU_DB[[Water Level]:[Water Level]],$B32) -> 145 | H32: =COUNTIFS(TU_DB[[ALK Bin (ppm)]:[ALK Bin (ppm)]],H$19,TU_DB[[Water Level]:[Water Level]],$B32) -> 6 | I32: =SUM(C32:H32) -> 357 | J32: =SUM(I32)/SUM($I$31:$I$34) -> 0.19712866
B33: Bankfull Stage | C33: =COUNTIFS(TU_DB[[ALK Bin (ppm)]:[ALK Bin (ppm)]],C$19,TU_DB[[Water Level]:[Water Level]],$B33) -> 5 | D33: =COUNTIFS(TU_DB[[ALK Bin (ppm)]:[ALK Bin (ppm)]],D$19,TU_DB[[Water Level]:[Water Level]],$B33) -> 3 | E33: =COUNTIFS(TU_DB[[ALK Bin (ppm)]:[ALK Bin (ppm)]],E$19,TU_DB[[Water Level]:[Water Level]],$B33) -> 24 | F33: =COUNTIFS(TU_DB[[ALK Bin (ppm)]:[ALK Bin (ppm)]],F$19,TU_DB[[Water Level]:[Water Level]],$B33) -> 19 | G33: =COUNTIFS(TU_DB[[ALK Bin (ppm)]:[ALK Bin (ppm)]],G$19,TU_DB[[Water Level]:[Water Level]],$B33) -> 24 | H33: =COUNTIFS(TU_DB[[ALK Bin (ppm)]:[ALK Bin (ppm)]],H$19,TU_DB[[Water Level]:[Water Level]],$B33) -> 0 | I33: =SUM(C33:H33) -> 75 | J33: =SUM(I33)/SUM($I$31:$I$34) -> 0.041413584
B34: Overbank Flooding | C34: 1 | D34: 1 | E34: 1 | F34: 1 | G34: 2 | H34: 0 | I34: 6 | J34: =SUM(I34)/SUM($I$31:$I$34) -> 0.0033130867
B35: Total | C35: =SUM(C31:C34) -> 153 | D35: =SUM(D31:D34) -> 183 | E35: =SUM(E31:E34) -> 367 | F35: =SUM(F31:F34) -> 260 | G35: =SUM(G31:G34) -> 826 | H35: =SUM(H31:H34) -> 22 | I35: =SUM(I31:I34) -> 1811
B44: Water Clarity
C45: Alkalinity [ppm CaCO3]
B46: Water Clarity | C46: 0 | D46: 40 | E46: 80 | F46: 120 | G46: 180 | H46: 240 | I46: Sum | J46: % Total
B47: Clear | C47: =COUNTIFS(TU_DB[[ALK Bin (ppm)]:[ALK Bin (ppm)]],C$19,TU_DB[[Clarity]:[Clarity]],$B47) -> 117 | D47: =COUNTIFS(TU_DB[[ALK Bin (ppm)]:[ALK Bin (ppm)]],D$19,TU_DB[[Clarity]:[Clarity]],$B47) -> 125 | E47: =COUNTIFS(TU_DB[[ALK Bin (ppm)]:[ALK Bin (ppm)]],E$19,TU_DB[[Clarity]:[Clarity]],$B47) -> 279 | F47: =COUNTIFS(TU_DB[[ALK Bin (ppm)]:[ALK Bin (ppm)]],F$19,TU_DB[[Clarity]:[Clarity]],$B47) -> 204 | G47: =COUNTIFS(TU_DB[[ALK Bin (ppm)]:[ALK Bin (ppm)]],G$19,TU_DB[[Clarity]:[Clarity]],$B47) -> 664 | H47: =COUNTIFS(TU_DB[[ALK Bin (ppm)]:[ALK Bin (ppm)]],H$19,TU_DB[[Clarity]:[Clarity]],$B47) -> 17 | I47: =SUM(C47:H47) -> 1406 | J47: =SUM(I47)/SUM($I$47:$I$49) -> 0.77125617
B48: Muddy | C48: =COUNTIFS(TU_DB[[ALK Bin (ppm)]:[ALK Bin (ppm)]],C$19,TU_DB[[Clarity]:[Clarity]],$B48) -> 7 | D48: =COUNTIFS(TU_DB[[ALK Bin (ppm)]:[ALK Bin (ppm)]],D$19,TU_DB[[Clarity]:[Clarity]],$B48) -> 8 | E48: =COUNTIFS(TU_DB[[ALK Bin (ppm)]:[ALK Bin (ppm)]],E$19,TU_DB[[Clarity]:[Clarity]],$B48) -> 31 | F48: =COUNTIFS(TU_DB[[ALK Bin (ppm)]:[ALK Bin (ppm)]],F$19,TU_DB[[Clarity]:[Clarity]],$B48) -> 14 | G48: =COUNTIFS(TU_DB[[ALK Bin (ppm)]:[ALK Bin (ppm)]],G$19,TU_DB[[Clarity]:[Clarity]],$B48) -> 26 | H48: =COUNTIFS(TU_DB[[ALK Bin (ppm)]:[ALK Bin (ppm)]],H$19,TU_DB[[Clarity]:[Clarity]],$B48) -> 1 | I48: =SUM(C48:H48) -> 87 | J48: =SUM(I48)/SUM($I$47:$I$49) -> 0.047723533
B49: Murky | C49: =COUNTIFS(TU_DB[[ALK Bin (ppm)]:[ALK Bin (ppm)]],C$19,TU_DB[[Clarity]:[Clarity]],$B49) -> 32 | D49: =COUNTIFS(TU_DB[[ALK Bin (ppm)]:[ALK Bin (ppm)]],D$19,TU_DB[[Clarity]:[Clarity]],$B49) -> 49 | E49: =COUNTIFS(TU_DB[[ALK Bin (ppm)]:[ALK Bin (ppm)]],E$19,TU_DB[[Clarity]:[Clarity]],$B49) -> 66 | F49: =COUNTIFS(TU_DB[[ALK Bin (ppm)]:[ALK Bin (ppm)]],F$19,TU_DB[[Clarity]:[Clarity]],$B49) -> 43 | G49: =COUNTIFS(TU_DB[[ALK Bin (ppm)]:[ALK Bin (ppm)]],G$19,TU_DB[[Clarity]:[Clarity]],$B49) -> 136 | H49: =COUNTIFS(TU_DB[[ALK Bin (ppm)]:[ALK Bin (ppm)]],H$19,TU_DB[[Clarity]:[Clarity]],$B49) -> 4 | I49: =SUM(C49:H49) -> 330 | J49: =SUM(I49)/SUM($I$47:$I$49) -> 0.1810203
B50: Total | C50: =SUM(C47:C49) -> 156 | D50: =SUM(D47:D49) -> 182 | E50: =SUM(E47:E49) -> 376 | F50: =SUM(F47:F49) -> 261 | G50: =SUM(G47:G49) -> 826 | H50: =SUM(H47:H49) -> 22 | I50: =SUM(I47:I49) -> 1823
B61: Monitoring Stations
C62: Alkalinity [ppm CaCO3] | M62: Station to Plot | N62: Kiat-TU-Wish
B63: Monitoring Site | C63: 0 | D63: 40 | E63: 80 | F63: 120 | G63: 180 | H63: 240 | I63: Sum | J63: % Total
B64: Kiat-TU-Wish | C64: =SUM(C65:C74) -> 17 | D64: =SUM(D65:D74) -> 5 | E64: =SUM(E65:E74) -> 40 | F64: =SUM(F65:F74) -> 27 | G64: =SUM(G65:G74) -> 92 | H64: =SUM(H65:H74) -> 6 | I64: =SUM(I65:I74) -> 187
B65: Cady Creek @ 50th St | C65: =COUNTIFS(TU_DB[[ALK Bin (ppm)]:[ALK Bin (ppm)]],C$19,TU_DB[[Monitoring Site]:[Monitoring Site]],$B65) -> 4 | D65: =COUNTIFS(TU_DB[[ALK Bin (ppm)]:[ALK Bin (ppm)]],D$19,TU_DB[[Monitoring Site]:[Monitoring Site]],$B65) -> 1 | E65: =COUNTIFS(TU_DB[[ALK Bin (ppm)]:[ALK Bin (ppm)]],E$19,TU_DB[[Monitoring Site]:[Monitoring Site]],$B65) -> 4 | F65: =COUNTIFS(TU_DB[[ALK Bin (ppm)]:[ALK Bin (ppm)]],F$19,TU_DB[[Monitoring Site]:[Monitoring Site]],$B65) -> 2 | G65: =COUNTIFS(TU_DB[[ALK Bin (ppm)]:[ALK Bin (ppm)]],G$19,TU_DB[[Monitoring Site]:[Monitoring Site]],$B65) -> 5 | H65: =COUNTIFS(TU_DB[[ALK Bin (ppm)]:[ALK Bin (ppm)]],H$19,TU_DB[[Monitoring Site]:[Monitoring Site]],$B65) -> 0 | I65: =SUM(C65:H65) -> 16 | J65: =SUM(I65)/$I$64 -> 0.085561497
B66: =Use!S125 -> Eau Galle River @ WI Hwy 29 | C66: =COUNTIFS(TU_DB[[ALK Bin (ppm)]:[ALK Bin (ppm)]],C$19,TU_DB[[Monitoring Site]:[Monitoring Site]],$B66) -> 1 | D66: =COUNTIFS(TU_DB[[ALK Bin (ppm)]:[ALK Bin (ppm)]],D$19,TU_DB[[Monitoring Site]:[Monitoring Site]],$B66) -> 2 | E66: =COUNTIFS(TU_DB[[ALK Bin (ppm)]:[ALK Bin (ppm)]],E$19,TU_DB[[Monitoring Site]:[Monitoring Site]],$B66) -> 6 | F66: =COUNTIFS(TU_DB[[ALK Bin (ppm)]:[ALK Bin (ppm)]],F$19,TU_DB[[Monitoring Site]:[Monitoring Site]],$B66) -> 0 | G66: =COUNTIFS(TU_DB[[ALK Bin (ppm)]:[ALK Bin (ppm)]],G$19,TU_DB[[Monitoring Site]:[Monitoring Site]],$B66) -> 2 | H66: =COUNTIFS(TU_DB[[ALK Bin (ppm)]:[ALK Bin (ppm)]],H$19,TU_DB[[Monitoring Site]:[Monitoring Site]],$B66) -> 0 | I66: =SUM(C66:H66) -> 11 | J66: =SUM(I66)/$I$64 -> 0.058823529
B67: =Use!S126 -> Isabelle Creek @ County Rd. EE | C67: =COUNTIFS(TU_DB[[ALK Bin (ppm)]:[ALK Bin (ppm)]],C$19,TU_DB[[Monitoring Site]:[Monitoring Site]],$B67) -> 1 | D67: =COUNTIFS(TU_DB[[ALK Bin (ppm)]:[ALK Bin (ppm)]],D$19,TU_DB[[Monitoring Site]:[Monitoring Site]],$B67) -> 1 | E67: =COUNTIFS(TU_DB[[ALK Bin (ppm)]:[ALK Bin (ppm)]],E$19,TU_DB[[Monitoring Site]:[Monitoring Site]],$B67) -> 3 | F67: =COUNTIFS(TU_DB[[ALK Bin (ppm)]:[ALK Bin (ppm)]],F$19,TU_DB[[Monitoring Site]:[Monitoring Site]],$B67) -> 6 | G67: =COUNTIFS(TU_DB[[ALK Bin (ppm)]:[ALK Bin (ppm)]],G$19,TU_DB[[Monitoring Site]:[Monitoring Site]],$B67) -> 11 | H67: =COUNTIFS(TU_DB[[ALK Bin (ppm)]:[ALK Bin (ppm)]],H$19,TU_DB[[Monitoring Site]:[Monitoring Site]],$B67) -> 0 | I67: =SUM(C67:H67) -> 22 | J67: =SUM(I67)/$I$64 -> 0.11764706
B68: =Use!S127 -> Kinnickinnic River, Lower Glen Park | C68: =COUNTIFS(TU_DB[[ALK Bin (ppm)]:[ALK Bin (ppm)]],C$19,TU_DB[[Monitoring Site]:[Monitoring Site]],$B68) -> 9 | D68: =COUNTIFS(TU_DB[[ALK Bin (ppm)]:[ALK Bin (ppm)]],D$19,TU_DB[[Monitoring Site]:[Monitoring Site]],$B68) -> 0 | E68: =COUNTIFS(TU_DB[[ALK Bin (ppm)]:[ALK Bin (ppm)]],E$19,TU_DB[[Monitoring Site]:[Monitoring Site]],$B68) -> 9 | F68: =COUNTIFS(TU_DB[[ALK Bin (ppm)]:[ALK Bin (ppm)]],F$19,TU_DB[[Monitoring Site]:[Monitoring Site]],$B68) -> 6 | G68: =COUNTIFS(TU_DB[[ALK Bin (ppm)]:[ALK Bin (ppm)]],G$19,TU_DB[[Monitoring Site]:[Monitoring Site]],$B68) -> 13 | H68: =COUNTIFS(TU_DB[[ALK Bin (ppm)]:[ALK Bin (ppm)]],H$19,TU_DB[[Monitoring Site]:[Monitoring Site]],$B68) -> 0 | I68: =SUM(C68:H68) -> 37 | J68: =SUM(I68)/$I$64 -> 0.19786096
B69: =Use!S128 -> Pine Creek @ County Rd. AA | C69: =COUNTIFS(TU_DB[[ALK Bin (ppm)]:[ALK Bin (ppm)]],C$19,TU_DB[[Monitoring Site]:[Monitoring Site]],$B69) -> 0 | D69: =COUNTIFS(TU_DB[[ALK Bin (ppm)]:[ALK Bin (ppm)]],D$19,TU_DB[[Monitoring Site]:[Monitoring Site]],$B69) -> 0 | E69: =COUNTIFS(TU_DB[[ALK Bin (ppm)]:[ALK Bin (ppm)]],E$19,TU_DB[[Monitoring Site]:[Monitoring Site]],$B69) -> 2 | F69: =COUNTIFS(TU_DB[[ALK Bin (ppm)]:[ALK Bin (ppm)]],F$19,TU_DB[[Monitoring Site]:[Monitoring Site]],$B69) -> 3 | G69: =COUNTIFS(TU_DB[[ALK Bin (ppm)]:[ALK Bin (ppm)]],G$19,TU_DB[[Monitoring Site]:[Monitoring Site]],$B69) -> 25 | H69: =COUNTIFS(TU_DB[[ALK Bin (ppm)]:[ALK Bin (ppm)]],H$19,TU_DB[[Monitoring Site]:[Monitoring Site]],$B69) -> 0 | I69: =SUM(C69:H69) -> 30 | J69: =SUM(I69)/$I$64 -> 0.16042781
B70: =Use!S129 -> Plum Creek @ Plum CIty Park | C70: =COUNTIFS(TU_DB[[ALK Bin (ppm)]:[ALK Bin (ppm)]],C$19,TU_DB[[Monitoring Site]:[Monitoring Site]],$B70) -> 0 | D70: =COUNTIFS(TU_DB[[ALK Bin (ppm)]:[ALK Bin (ppm)]],D$19,TU_DB[[Monitoring Site]:[Monitoring Site]],$B70) -> 0 | E70: =COUNTIFS(TU_DB[[ALK Bin (ppm)]:[ALK Bin (ppm)]],E$19,TU_DB[[Monitoring Site]:[Monitoring Site]],$B70) -> 4 | F70: =COUNTIFS(TU_DB[[ALK Bin (ppm)]:[ALK Bin (ppm)]],F$19,TU_DB[[Monitoring Site]:[Monitoring Site]],$B70) -> 6 | G70: =COUNTIFS(TU_DB[[ALK Bin (ppm)]:[ALK Bin (ppm)]],G$19,TU_DB[[Monitoring Site]:[Monitoring Site]],$B70) -> 7 | H70: =COUNTIFS(TU_DB[[ALK Bin (ppm)]:[ALK Bin (ppm)]],H$19,TU_DB[[Monitoring Site]:[Monitoring Site]],$B70) -> 0 | I70: =SUM(C70:H70) -> 17 | J70: =SUM(I70)/$I$64 -> 0.090909091
B71: =Use!S130 -> Rocky Branch Creek, Lower Glen Park | C71: =COUNTIFS(TU_DB[[ALK Bin (ppm)]:[ALK Bin (ppm)]],C$19,TU_DB[[Monitoring Site]:[Monitoring Site]],$B71) -> 1 | D71: =COUNTIFS(TU_DB[[ALK Bin (ppm)]:[ALK Bin (ppm)]],D$19,TU_DB[[Monitoring Site]:[Monitoring Site]],$B71) -> 1 | E71: =COUNTIFS(TU_DB[[ALK Bin (ppm)]:[ALK Bin (ppm)]],E$19,TU_DB[[Monitoring Site]:[Monitoring Site]],$B71) -> 5 | F71: =COUNTIFS(TU_DB[[ALK Bin (ppm)]:[ALK Bin (ppm)]],F$19,TU_DB[[Monitoring Site]:[Monitoring Site]],$B71) -> 2 | G71: =COUNTIFS(TU_DB[[ALK Bin (ppm)]:[ALK Bin (ppm)]],G$19,TU_DB[[Monitoring Site]:[Monitoring Site]],$B71) -> 1 | H71: =COUNTIFS(TU_DB[[ALK Bin (ppm)]:[ALK Bin (ppm)]],H$19,TU_DB[[Monitoring Site]:[Monitoring Site]],$B71) -> 0 | I71: =SUM(C71:H71) -> 10 | J71: =SUM(I71)/$I$64 -> 0.053475936
B72: =Use!S131 -> Rush River @ 570th Ave | C72: =COUNTIFS(TU_DB[[ALK Bin (ppm)]:[ALK Bin (ppm)]],C$19,TU_DB[[Monitoring Site]:[Monitoring Site]],$B72) -> 1 | D72: =COUNTIFS(TU_DB[[ALK Bin (ppm)]:[ALK Bin (ppm)]],D$19,TU_DB[[Monitoring Site]:[Monitoring Site]],$B72) -> 0 | E72: =COUNTIFS(TU_DB[[ALK Bin (ppm)]:[ALK Bin (ppm)]],E$19,TU_DB[[Monitoring Site]:[Monitoring Site]],$B72) -> 5 | F72: =COUNTIFS(TU_DB[[ALK Bin (ppm)]:[ALK Bin (ppm)]],F$19,TU_DB[[Monitoring Site]:[Monitoring Site]],$B72) -> 1 | G72: =COUNTIFS(TU_DB[[ALK Bin (ppm)]:[ALK Bin (ppm)]],G$19,TU_DB[[Monitoring Site]:[Monitoring Site]],$B72) -> 12 | H72: =COUNTIFS(TU_DB[[ALK Bin (ppm)]:[ALK Bin (ppm)]],H$19,TU_DB[[Monitoring Site]:[Monitoring Site]],$B72) -> 6 | I72: =SUM(C72:H72) -> 25 | J72: =SUM(I72)/$I$64 -> 0.13368984
B73: =Use!S132 -> SF Kinnickinnic River @ 900th St | C73: =COUNTIFS(TU_DB[[ALK Bin (ppm)]:[ALK Bin (ppm)]],C$19,TU_DB[[Monitoring Site]:[Monitoring Site]],$B73) -> 0 | D73: =COUNTIFS(TU_DB[[ALK Bin (ppm)]:[ALK Bin (ppm)]],D$19,TU_DB[[Monitoring Site]:[Monitoring Site]],$B73) -> 0 | E73: =COUNTIFS(TU_DB[[ALK Bin (ppm)]:[ALK Bin (ppm)]],E$19,TU_DB[[Monitoring Site]:[Monitoring Site]],$B73) -> 1 | F73: =COUNTIFS(TU_DB[[ALK Bin (ppm)]:[ALK Bin (ppm)]],F$19,TU_DB[[Monitoring Site]:[Monitoring Site]],$B73) -> 1 | G73: =COUNTIFS(TU_DB[[ALK Bin (ppm)]:[ALK Bin (ppm)]],G$19,TU_DB[[Monitoring Site]:[Monitoring Site]],$B73) -> 10 | H73: =COUNTIFS(TU_DB[[ALK Bin (ppm)]:[ALK Bin (ppm)]],H$19,TU_DB[[Monitoring Site]:[Monitoring Site]],$B73) -> 0 | I73: =SUM(C73:H73) -> 12 | J73: =SUM(I73)/$I$64 -> 0.064171123
B74: =Use!S133 -> Trimbelle River @ County Rd W | C74: =COUNTIFS(TU_DB[[ALK Bin (ppm)]:[ALK Bin (ppm)]],C$19,TU_DB[[Monitoring Site]:[Monitoring Site]],$B74) -> 0 | D74: =COUNTIFS(TU_DB[[ALK Bin (ppm)]:[ALK Bin (ppm)]],D$19,TU_DB[[Monitoring Site]:[Monitoring Site]],$B74) -> 0 | E74: =COUNTIFS(TU_DB[[ALK Bin (ppm)]:[ALK Bin (ppm)]],E$19,TU_DB[[Monitoring Site]:[Monitoring Site]],$B74) -> 1 | F74: =COUNTIFS(TU_DB[[ALK Bin (ppm)]:[ALK Bin (ppm)]],F$19,TU_DB[[Monitoring Site]:[Monitoring Site]],$B74) -> 0 | G74: =COUNTIFS(TU_DB[[ALK Bin (ppm)]:[ALK Bin (ppm)]],G$19,TU_DB[[Monitoring Site]:[Monitoring Site]],$B74) -> 6 | H74: =COUNTIFS(TU_DB[[ALK Bin (ppm)]:[ALK Bin (ppm)]],H$19,TU_DB[[Monitoring Site]:[Monitoring Site]],$B74) -> 0 | I74: =SUM(C74:H74) -> 7 | J74: =SUM(I74)/$I$64 -> 0.037433155
B75: Twin Cities Trout Unlimited | C75: =SUM(C76:C85) -> 14 | D75: =SUM(D76:D85) -> 3 | E75: =SUM(E76:E85) -> 30 | F75: =SUM(F76:F85) -> 24 | G75: =SUM(G76:G85) -> 33 | H75: =SUM(H76:H85) -> 0 | I75: =SUM(I76:I83) -> 104
B76: =Use!S135 -> Belle Creek | C76: =COUNTIFS(TU_DB[[ALK Bin (ppm)]:[ALK Bin (ppm)]],C$19,TU_DB[[Monitoring Site]:[Monitoring Site]],$B76) -> 7 | D76: =COUNTIFS(TU_DB[[ALK Bin (ppm)]:[ALK Bin (ppm)]],D$19,TU_DB[[Monitoring Site]:[Monitoring Site]],$B76) -> 0 | E76: =COUNTIFS(TU_DB[[ALK Bin (ppm)]:[ALK Bin (ppm)]],E$19,TU_DB[[Monitoring Site]:[Monitoring Site]],$B76) -> 0 | F76: =COUNTIFS(TU_DB[[ALK Bin (ppm)]:[ALK Bin (ppm)]],F$19,TU_DB[[Monitoring Site]:[Monitoring Site]],$B76) -> 0 | G76: =COUNTIFS(TU_DB[[ALK Bin (ppm)]:[ALK Bin (ppm)]],G$19,TU_DB[[Monitoring Site]:[Monitoring Site]],$B76) -> 0 | H76: =COUNTIFS(TU_DB[[ALK Bin (ppm)]:[ALK Bin (ppm)]],H$19,TU_DB[[Monitoring Site]:[Monitoring Site]],$B76) -> 0 | I76: =SUM(C76:H76) -> 7 | J76: =SUM(I76)/$I$75 -> 0.067307692
B77: =Use!S136 -> Hay Creek @ 320th St | C77: =COUNTIFS(TU_DB[[ALK Bin (ppm)]:[ALK Bin (ppm)]],C$19,TU_DB[[Monitoring Site]:[Monitoring Site]],$B77) -> 0 | D77: =COUNTIFS(TU_DB[[ALK Bin (ppm)]:[ALK Bin (ppm)]],D$19,TU_DB[[Monitoring Site]:[Monitoring Site]],$B77) -> 0 | E77: =COUNTIFS(TU_DB[[ALK Bin (ppm)]:[ALK Bin (ppm)]],E$19,TU_DB[[Monitoring Site]:[Monitoring Site]],$B77) -> 0 | F77: =COUNTIFS(TU_DB[[ALK Bin (ppm)]:[ALK Bin (ppm)]],F$19,TU_DB[[Monitoring Site]:[Monitoring Site]],$B77) -> 0 | G77: =COUNTIFS(TU_DB[[ALK Bin (ppm)]:[ALK Bin (ppm)]],G$19,TU_DB[[Monitoring Site]:[Monitoring Site]],$B77) -> 0 | H77: =COUNTIFS(TU_DB[[ALK Bin (ppm)]:[ALK Bin (ppm)]],H$19,TU_DB[[Monitoring Site]:[Monitoring Site]],$B77) -> 0 | I77: =SUM(C77:H77) -> 0 | J77: =SUM(I77)/$I$75 -> 0
B78: =Use!S137 -> Hay Creek @ 325th St | C78: =COUNTIFS(TU_DB[[ALK Bin (ppm)]:[ALK Bin (ppm)]],C$19,TU_DB[[Monitoring Site]:[Monitoring Site]],$B78) -> 0 | D78: =COUNTIFS(TU_DB[[ALK Bin (ppm)]:[ALK Bin (ppm)]],D$19,TU_DB[[Monitoring Site]:[Monitoring Site]],$B78) -> 0 | E78: =COUNTIFS(TU_DB[[ALK Bin (ppm)]:[ALK Bin (ppm)]],E$19,TU_DB[[Monitoring Site]:[Monitoring Site]],$B78) -> 0 | F78: =COUNTIFS(TU_DB[[ALK Bin (ppm)]:[ALK Bin (ppm)]],F$19,TU_DB[[Monitoring Site]:[Monitoring Site]],$B78) -> 0 | G78: =COUNTIFS(TU_DB[[ALK Bin (ppm)]:[ALK Bin (ppm)]],G$19,TU_DB[[Monitoring Site]:[Monitoring Site]],$B78) -> 0 | H78: =COUNTIFS(TU_DB[[ALK Bin (ppm)]:[ALK Bin (ppm)]],H$19,TU_DB[[Monitoring Site]:[Monitoring Site]],$B78) -> 0 | I78: =SUM(C78:H78) -> 0 | J78: =SUM(I78)/$I$75 -> 0
B79: =Use!S138 -> Eagle Creek | C79: =COUNTIFS(TU_DB[[ALK Bin (ppm)]:[ALK Bin (ppm)]],C$19,TU_DB[[Monitoring Site]:[Monitoring Site]],$B79) -> 0 | D79: =COUNTIFS(TU_DB[[ALK Bin (ppm)]:[ALK Bin (ppm)]],D$19,TU_DB[[Monitoring Site]:[Monitoring Site]],$B79) -> 0 | E79: =COUNTIFS(TU_DB[[ALK Bin (ppm)]:[ALK Bin (ppm)]],E$19,TU_DB[[Monitoring Site]:[Monitoring Site]],$B79) -> 0 | F79: =COUNTIFS(TU_DB[[ALK Bin (ppm)]:[ALK Bin (ppm)]],F$19,TU_DB[[Monitoring Site]:[Monitoring Site]],$B79) -> 0 | G79: =COUNTIFS(TU_DB[[ALK Bin (ppm)]:[ALK Bin (ppm)]],G$19,TU_DB[[Monitoring Site]:[Monitoring Site]],$B79) -> 2 | H79: =COUNTIFS(TU_DB[[ALK Bin (ppm)]:[ALK Bin (ppm)]],H$19,TU_DB[[Monitoring Site]:[Monitoring Site]],$B79) -> 0 | I79: =SUM(C79:H79) -> 2 | J79: =SUM(I79)/$I$75 -> 0.019230769
B80: =Use!S139 -> Little Cannon River | C80: =COUNTIFS(TU_DB[[ALK Bin (ppm)]:[ALK Bin (ppm)]],C$19,TU_DB[[Monitoring Site]:[Monitoring Site]],$B80) -> 0 | D80: =COUNTIFS(TU_DB[[ALK Bin (ppm)]:[ALK Bin (ppm)]],D$19,TU_DB[[Monitoring Site]:[Monitoring Site]],$B80) -> 0 | E80: =COUNTIFS(TU_DB[[ALK Bin (ppm)]:[ALK Bin (ppm)]],E$19,TU_DB[[Monitoring Site]:[Monitoring Site]],$B80) -> 0 | F80: =COUNTIFS(TU_DB[[ALK Bin (ppm)]:[ALK Bin (ppm)]],F$19,TU_DB[[Monitoring Site]:[Monitoring Site]],$B80) -> 0 | G80: =COUNTIFS(TU_DB[[ALK Bin (ppm)]:[ALK Bin (ppm)]],G$19,TU_DB[[Monitoring Site]:[Monitoring Site]],$B80) -> 0 | H80: =COUNTIFS(TU_DB[[ALK Bin (ppm)]:[ALK Bin (ppm)]],H$19,TU_DB[[Monitoring Site]:[Monitoring Site]],$B80) -> 0 | I80: =SUM(C80:H80) -> 0 | J80: =SUM(I80)/$I$75 -> 0
B81: =Use!S140 -> MOA Creek | C81: =COUNTIFS(TU_DB[[ALK Bin (ppm)]:[ALK Bin (ppm)]],C$19,TU_DB[[Monitoring Site]:[Monitoring Site]],$B81) -> 2 | D81: =COUNTIFS(TU_DB[[ALK Bin (ppm)]:[ALK Bin (ppm)]],D$19,TU_DB[[Monitoring Site]:[Monitoring Site]],$B81) -> 0 | E81: =COUNTIFS(TU_DB[[ALK Bin (ppm)]:[ALK Bin (ppm)]],E$19,TU_DB[[Monitoring Site]:[Monitoring Site]],$B81) -> 2 | F81: =COUNTIFS(TU_DB[[ALK Bin (ppm)]:[ALK Bin (ppm)]],F$19,TU_DB[[Monitoring Site]:[Monitoring Site]],$B81) -> 4 | G81: =COUNTIFS(TU_DB[[ALK Bin (ppm)]:[ALK Bin (ppm)]],G$19,TU_DB[[Monitoring Site]:[Monitoring Site]],$B81) -> 14 | H81: =COUNTIFS(TU_DB[[ALK Bin (ppm)]:[ALK Bin (ppm)]],H$19,TU_DB[[Monitoring Site]:[Monitoring Site]],$B81) -> 0 | I81: =SUM(C81:H81) -> 22 | J81: =SUM(I81)/$I$75 -> 0.21153846
B82: =Use!S141 -> Trout Brook | C82: =COUNTIFS(TU_DB[[ALK Bin (ppm)]:[ALK Bin (ppm)]],C$19,TU_DB[[Monitoring Site]:[Monitoring Site]],$B82) -> 2 | D82: =COUNTIFS(TU_DB[[ALK Bin (ppm)]:[ALK Bin (ppm)]],D$19,TU_DB[[Monitoring Site]:[Monitoring Site]],$B82) -> 1 | E82: =COUNTIFS(TU_DB[[ALK Bin (ppm)]:[ALK Bin (ppm)]],E$19,TU_DB[[Monitoring Site]:[Monitoring Site]],$B82) -> 23 | F82: =COUNTIFS(TU_DB[[ALK Bin (ppm)]:[ALK Bin (ppm)]],F$19,TU_DB[[Monitoring Site]:[Monitoring Site]],$B82) -> 10 | G82: =COUNTIFS(TU_DB[[ALK Bin (ppm)]:[ALK Bin (ppm)]],G$19,TU_DB[[Monitoring Site]:[Monitoring Site]],$B82) -> 2 | H82: =COUNTIFS(TU_DB[[ALK Bin (ppm)]:[ALK Bin (ppm)]],H$19,TU_DB[[Monitoring Site]:[Monitoring Site]],$B82) -> 0 | I82: =SUM(C82:H82) -> 38 | J82: =SUM(I82)/$I$75 -> 0.36538462
B83: =Use!S142 -> Vermillion River, South Branch | C83: =COUNTIFS(TU_DB[[ALK Bin (ppm)]:[ALK Bin (ppm)]],C$19,TU_DB[[Monitoring Site]:[Monitoring Site]],$B83) -> 3 | D83: =COUNTIFS(TU_DB[[ALK Bin (ppm)]:[ALK Bin (ppm)]],D$19,TU_DB[[Monitoring Site]:[Monitoring Site]],$B83) -> 2 | E83: =COUNTIFS(TU_DB[[ALK Bin (ppm)]:[ALK Bin (ppm)]],E$19,TU_DB[[Monitoring Site]:[Monitoring Site]],$B83) -> 5 | F83: =COUNTIFS(TU_DB[[ALK Bin (ppm)]:[ALK Bin (ppm)]],F$19,TU_DB[[Monitoring Site]:[Monitoring Site]],$B83) -> 10 | G83: =COUNTIFS(TU_DB[[ALK Bin (ppm)]:[ALK Bin (ppm)]],G$19,TU_DB[[Monitoring Site]:[Monitoring Site]],$B83) -> 15 | H83: =COUNTIFS(TU_DB[[ALK Bin (ppm)]:[ALK Bin (ppm)]],H$19,TU_DB[[Monitoring Site]:[Monitoring Site]],$B83) -> 0 | I83: =SUM(C83:H83) -> 35 | J83: =SUM(I83)/$I$75 -> 0.33653846
M86: Plotting Data | N86: 0 | O86: 40 | P86: 80 | Q86: 120 | R86: 180 | S86: 240
M87: =INDEX(B65:B82,MATCH($N$62,$B$65:$B$82,0)) -> #N/A | N87: =INDEX(C64:C83,MATCH($N$62,$B$64:$B$83,0)) -> 17 | O87: =INDEX(D64:D83,MATCH($N$62,$B$64:$B$83,0)) -> 5 | P87: =INDEX(E64:E83,MATCH($N$62,$B$64:$B$83,0)) -> 40 | Q87: =INDEX(F64:F83,MATCH($N$62,$B$64:$B$83,0)) -> 27 | R87: =INDEX(G64:G83,MATCH($N$62,$B$64:$B$83,0)) -> 92 | S87: =INDEX(H64:H83,MATCH($N$62,$B$64:$B$83,0)) -> 6

Sheet HRD
A1: TU DARE Angler Science DB
B2: Water Analysis | C2: Hardness
B3: Download | C3: =TUDB!B3 -> 45580
B5: Overview Stats
B6: Hardness [ppm CaCO3] | C6: Observations | D6: % Total Obs. | E6: Cum. % | F6: 2019 | G6: 2020 | H6: 2021 | I6: 2022 | J6: 2023 | K6: 2024
B7: 0 | C7: =COUNTIFS(TU_DB[HRD Bin (ppm)],B7) -> 122 | D7: =C7/$C$12 -> 0.060908637 | E7: =D7 -> 0.060908637 | F7: =COUNTIFS(TU_DB[[HRD Bin (ppm)]:[HRD Bin (ppm)]],$B7,TU_DB[[Year]:[Year]],F$6) -> 0 | G7: =COUNTIFS(TU_DB[[HRD Bin (ppm)]:[HRD Bin (ppm)]],$B7,TU_DB[[Year]:[Year]],G$6) -> 8 | H7: =COUNTIFS(TU_DB[[HRD Bin (ppm)]:[HRD Bin (ppm)]],$B7,TU_DB[[Year]:[Year]],H$6) -> 20 | I7: =COUNTIFS(TU_DB[[HRD Bin (ppm)]:[HRD Bin (ppm)]],$B7,TU_DB[[Year]:[Year]],I$6) -> 24 | J7: =COUNTIFS(TU_DB[[HRD Bin (ppm)]:[HRD Bin (ppm)]],$B7,TU_DB[[Year]:[Year]],J$6) -> 39 | K7: =COUNTIFS(TU_DB[[HRD Bin (ppm)]:[HRD Bin (ppm)]],$B7,TU_DB[[Year]:[Year]],K$6) -> 31
B8: 30 | C8: =COUNTIFS(TU_DB[HRD Bin (ppm)],B8) -> 139 | D8: =C8/$C$12 -> 0.069395906 | E8: =D8+E7 -> 0.13030454 | F8: =COUNTIFS(TU_DB[[HRD Bin (ppm)]:[HRD Bin (ppm)]],$B8,TU_DB[[Year]:[Year]],F$6) -> 0 | G8: =COUNTIFS(TU_DB[[HRD Bin (ppm)]:[HRD Bin (ppm)]],$B8,TU_DB[[Year]:[Year]],G$6) -> 18 | H8: =COUNTIFS(TU_DB[[HRD Bin (ppm)]:[HRD Bin (ppm)]],$B8,TU_DB[[Year]:[Year]],H$6) -> 28 | I8: =COUNTIFS(TU_DB[[HRD Bin (ppm)]:[HRD Bin (ppm)]],$B8,TU_DB[[Year]:[Year]],I$6) -> 31 | J8: =COUNTIFS(TU_DB[[HRD Bin (ppm)]:[HRD Bin (ppm)]],$B8,TU_DB[[Year]:[Year]],J$6) -> 46 | K8: =COUNTIFS(TU_DB[[HRD Bin (ppm)]:[HRD Bin (ppm)]],$B8,TU_DB[[Year]:[Year]],K$6) -> 16
B9: 60 | C9: =COUNTIFS(TU_DB[HRD Bin (ppm)],B9) -> 206 | D9: =C9/$C$12 -> 0.10284573 | E9: =D9+E8 -> 0.23315027 | F9: =COUNTIFS(TU_DB[[HRD Bin (ppm)]:[HRD Bin (ppm)]],$B9,TU_DB[[Year]:[Year]],F$6) -> 0 | G9: =COUNTIFS(TU_DB[[HRD Bin (ppm)]:[HRD Bin (ppm)]],$B9,TU_DB[[Year]:[Year]],G$6) -> 23 | H9: =COUNTIFS(TU_DB[[HRD Bin (ppm)]:[HRD Bin (ppm)]],$B9,TU_DB[[Year]:[Year]],H$6) -> 35 | I9: =COUNTIFS(TU_DB[[HRD Bin (ppm)]:[HRD Bin (ppm)]],$B9,TU_DB[[Year]:[Year]],I$6) -> 31 | J9: =COUNTIFS(TU_DB[[HRD Bin (ppm)]:[HRD Bin (ppm)]],$B9,TU_DB[[Year]:[Year]],J$6) -> 80 | K9: =COUNTIFS(TU_DB[[HRD Bin (ppm)]:[HRD Bin (ppm)]],$B9,TU_DB[[Year]:[Year]],K$6) -> 37
B10: 120 | C10: =COUNTIFS(TU_DB[HRD Bin (ppm)],B10) -> 674 | D10: =C10/$C$12 -> 0.33649526 | E10: =D10+E9 -> 0.56964553 | F10: =COUNTIFS(TU_DB[[HRD Bin (ppm)]:[HRD Bin (ppm)]],$B10,TU_DB[[Year]:[Year]],F$6) -> 1 | G10: =COUNTIFS(TU_DB[[HRD Bin (ppm)]:[HRD Bin (ppm)]],$B10,TU_DB[[Year]:[Year]],G$6) -> 35 | H10: =COUNTIFS(TU_DB[[HRD Bin (ppm)]:[HRD Bin (ppm)]],$B10,TU_DB[[Year]:[Year]],H$6) -> 139 | I10: =COUNTIFS(TU_DB[[HRD Bin (ppm)]:[HRD Bin (ppm)]],$B10,TU_DB[[Year]:[Year]],I$6) -> 140 | J10: =COUNTIFS(TU_DB[[HRD Bin (ppm)]:[HRD Bin (ppm)]],$B10,TU_DB[[Year]:[Year]],J$6) -> 226 | K10: =COUNTIFS(TU_DB[[HRD Bin (ppm)]:[HRD Bin (ppm)]],$B10,TU_DB[[Year]:[Year]],K$6) -> 133
B11: 180 | C11: =COUNTIFS(TU_DB[HRD Bin (ppm)],B11) -> 862 | D11: =C11/$C$12 -> 0.43035447 | E11: =D11+E10 -> 1 | F11: =COUNTIFS(TU_DB[[HRD Bin (ppm)]:[HRD Bin (ppm)]],$B11,TU_DB[[Year]:[Year]],F$6) -> 3 | G11: =COUNTIFS(TU_DB[[HRD Bin (ppm)]:[HRD Bin (ppm)]],$B11,TU_DB[[Year]:[Year]],G$6) -> 24 | H11: =COUNTIFS(TU_DB[[HRD Bin (ppm)]:[HRD Bin (ppm)]],$B11,TU_DB[[Year]:[Year]],H$6) -> 139 | I11: =COUNTIFS(TU_DB[[HRD Bin (ppm)]:[HRD Bin (ppm)]],$B11,TU_DB[[Year]:[Year]],I$6) -> 193 | J11: =COUNTIFS(TU_DB[[HRD Bin (ppm)]:[HRD Bin (ppm)]],$B11,TU_DB[[Year]:[Year]],J$6) -> 323 | K11: =COUNTIFS(TU_DB[[HRD Bin (ppm)]:[HRD Bin (ppm)]],$B11,TU_DB[[Year]:[Year]],K$6) -> 180
B12: Total | C12: =SUM(C7:C11) -> 2003 | F12: =SUM(F7:F11) -> 4 | G12: =SUM(G7:G11) -> 108 | H12: =SUM(H7:H11) -> 361 | I12: =SUM(I7:I11) -> 419 | J12: =SUM(J7:J11) -> 714 | K12: =SUM(K7:K11) -> 397
B17: Weather Conditions
C18: Hardness [ppm CaCO3] | J18: Table Labels
B19: Weather Conditions | C19: 0 | D19: 30 | E19: 60 | F19: 120 | G19: 180 | H19: Sum | I19: % Total
B20: Local Thunderstorm | C20: =COUNTIFS(TU_DB[[HRD Bin (ppm)]:[HRD Bin (ppm)]],C$19,TU_DB[[Weather]:[Weather]],$B20) -> 2 | D20: =COUNTIFS(TU_DB[[HRD Bin (ppm)]:[HRD Bin (ppm)]],D$19,TU_DB[[Weather]:[Weather]],$B20) -> 5 | E20: =COUNTIFS(TU_DB[[HRD Bin (ppm)]:[HRD Bin (ppm)]],E$19,TU_DB[[Weather]:[Weather]],$B20) -> 19 | F20: =COUNTIFS(TU_DB[[HRD Bin (ppm)]:[HRD Bin (ppm)]],F$19,TU_DB[[Weather]:[Weather]],$B20) -> 27 | G20: =COUNTIFS(TU_DB[[HRD Bin (ppm)]:[HRD Bin (ppm)]],G$19,TU_DB[[Weather]:[Weather]],$B20) -> 31 | H20: =SUM(C20:G20) -> 84 | I20: =SUM(H20)/SUM($H$20:$H$25) -> 0.047457627 | J20: LT
B21: Regional Rainfall | C21: =COUNTIFS(TU_DB[[HRD Bin (ppm)]:[HRD Bin (ppm)]],C$19,TU_DB[[Weather]:[Weather]],$B21) -> 25 | D21: =COUNTIFS(TU_DB[[HRD Bin (ppm)]:[HRD Bin (ppm)]],D$19,TU_DB[[Weather]:[Weather]],$B21) -> 16 | E21: =COUNTIFS(TU_DB[[HRD Bin (ppm)]:[HRD Bin (ppm)]],E$19,TU_DB[[Weather]:[Weather]],$B21) -> 33 | F21: =COUNTIFS(TU_DB[[HRD Bin (ppm)]:[HRD Bin (ppm)]],F$19,TU_DB[[Weather]:[Weather]],$B21) -> 87 | G21: =COUNTIFS(TU_DB[[HRD Bin (ppm)]:[HRD Bin (ppm)]],G$19,TU_DB[[Weather]:[Weather]],$B21) -> 84 | H21: =SUM(C21:G21) -> 245 | I21: =SUM(H21)/SUM($H$20:$H$25) -> 0.13841808 | J21: RR
